Workbook

Sheet PROJECT DETAILS
A1: DETAILS
A2: PROJECT TITLE | B2: ONE STOREY RESIDENTIAL BUILDING
A3: LOCATION | B3: BARANGAY BENITEZ, BANGA, SOUTH COTABATO
A4: DURATION | B4: 200
A5: CONTRACTOR | B5: GEMMA CONSTRUCTION
A6: PROJECT SOURCE | B6: SLF 2018
A8: C1 | E8: C2 | I8: C3 | M8: C4 | Q8: C5
A10: Hbc= | B10: 2.5 | C10: m | E10: Hbc= | F10: 2 | G10: m | I10: Hbc= | J10: 0.55 | K10: m | M10: Hbc= | N10: 0.55 | O10: m
A11: L= | B11: 0.7 | C11: m | E11: L= | F11: 0.6 | G11: m | I11: L= | J11: 0.35 | K11: m | M11: L= | N11: 0.35 | O11: m | Q11: L= | R11: 1 | S11: m
A12: W= | B12: 1.1 | C12: m | E12: W= | F12: 0.6 | G12: m | I12: W= | J12: 0.35 | K12: m | M12: W= | N12: 0.35 | O12: m | Q12: W= | S12: m
A13: H= | B13: 3.6 | C13: m | E13: H= | F13: 1.2 | G13: m | I13: H= | J13: 3 | K13: m | M13: H= | N13: 3 | O13: m | Q13: H= | S13: m
A14: NO. OF PCS = | B14: 10 | C14: pcs | E14: NO. OF PCS = | F14: 20 | G14: pcs | I14: NO. OF PCS = | J14: 9 | K14: pcs | M14: NO. OF PCS = | N14: 9 | O14: pcs | Q14: NO. OF PCS = | S14: pcs
A15: V= | B15: =B13*B12*B11*B14 -> 27.72 | C15: cu.m. | E15: V= | F15: =F13*F12*F11*F14 -> 8.64 | G15: cu.m. | I15: V= | J15: =J13*J12*J11*J14 -> 3.3075 | K15: cu.m. | M15: V= | N15: =N13*N12*N11*N14 -> 3.3075 | O15: cu.m. | Q15: V= | R15: =R13*R12*R11*R14 -> 0 | S15: cu.m.
A16: BAR SIZE = | B16: 20 | C16: mm | E16: BAR SIZE = | F16: 20 | G16: mm | I16: BAR SIZE = | J16: 12 | K16: mm | M16: BAR SIZE = | N16: 12 | O16: mm
A17: NO.OF BAR | E17: NO.OF BAR | I17: NO.OF BAR | M17: NO.OF BAR
A18: PER ONE | B18: 14 | C18: pcs | E18: PER ONE | F18: 12 | G18: pcs | I18: PER ONE | J18: 4 | K18: pcs | M18: PER ONE | N18: 4 | O18: pcs
A19: COLUMN | E19: COLUMN | I19: COLUMN | M19: COLUMN
A21: lateral ties | E21: lateral ties | I21: lateral ties | M21: lateral ties
A22: BAR SIZE = | B22: 10 | C22: mm | E22: BAR SIZE = | F22: 10 | G22: mm | I22: BAR SIZE = | J22: 0 | K22: mm | M22: BAR SIZE = | N22: 0 | O22: mm
A23: n1= | B23: 5 | C23: s1= | D23: 0.05 | E23: n1= | F23: 5 | G23: s1= | H23: 0.05 | I23: n1= | J23: 0 | K23: s1= | L23: 0 | M23: n1= | N23: 0 | O23: s1= | P23: 0
A24: n2= | B24: 5 | C24: s2= | D24: 0.1 | E24: n2= | F24: 5 | G24: s2= | H24: 0.1 | I24: n2= | J24: 0 | K24: s2= | L24: 0 | M24: n2= | N24: 0 | O24: s2= | P24: 0
A25: n3= | B25: 5 | C25: s3= | D25: 0.15 | E25: n3= | F25: 0 | G25: s3= | H25: 0 | I25: n3= | J25: 0 | K25: s3= | L25: 0 | M25: n3= | N25: 0 | O25: s3= | P25: 0
A26: n4= | B26: 0 | C26: s4= | D26: 0 | E26: n4= | F26: 0 | G26: s4= | H26: 0 | I26: n4= | J26: 0 | K26: s4= | L26: 0 | M26: n4= | N26: 0 | O26: s4= | P26: 0
C27: s5= | D27: 0.2 | G27: s5= | H27: 0.2 | K27: s5= | L27: 0 | O27: s5= | P27: 0
A32: F1 | E32: F2 | I32: F3 | M32: F4 | Q32: F5
A34: Hb= | B34: =B10+B37+0.05 -> 3.35 | C34: m | E34: Hb= | F34: =F10+F37+0.05 -> 2.65 | G34: m | I34: Hb= | J34: =J10+J37+0.05 -> 0.85 | K34: m | M34: Hb= | N34: =N10+N37+0.05 -> 0.85 | O34: m
A35: L= | B35: 3 | C35: m | E35: L= | F35: 2 | G35: m | I35: L= | J35: 1 | K35: m | M35: L= | N35: 1 | O35: m | Q35: L= | S35: m
A36: W= | B36: 3 | C36: m | E36: W= | F36: 2 | G36: m | I36: W= | J36: 1 | K36: m | M36: W= | N36: 1 | O36: m | Q36: W= | S36: m
A37: T= | B37: 0.8 | C37: m | E37: T= | F37: 0.6 | G37: m | I37: T= | J37: 0.25 | K37: m | M37: T= | N37: 0.25 | O37: m | Q37: H= | S37: m
A38: NO. OF PCS = | B38: 10 | C38: pcs | E38: NO. OF PCS = | F38: 20 | G38: pcs | I38: NO. OF PCS = | J38: 20 | K38: pcs | M38: NO. OF PCS = | N38: 20 | O38: pcs | Q38: NO. OF PCS = | S38: pcs
A39: V= | B39: =B37*B36*B35*B38 -> 72 | C39: cu.m. | E39: V= | F39: =F37*F36*F35*F38 -> 48 | G39: cu.m. | I39: V= | J39: =J37*J36*J35*J38 -> 5 | K39: cu.m. | M39: V= | N39: =N37*N36*N35*N38 -> 5 | O39: cu.m. | Q39: V= | R39: =R37*R36*R35*R38 -> 0 | S39: cu.m.
A40: BAR SIZE= | B40: 12 | C40: mm | E40: BAR SIZE= | F40: 12 | G40: mm | I40: BAR SIZE= | J40: 12 | K40: mm | M40: BAR SIZE= | N40: 12 | O40: mm
A41: NO.OF BAR | C41: pcs | E41: NO.OF BAR | G41: pcs | I41: NO.OF BAR | K41: pcs | M41: NO.OF BAR | O41: pcs
A42: PER ONE | B42: 5 | E42: PER ONE | F42: 5 | I42: PER ONE | J42: 5 | M42: PER ONE | N42: 5
A43: FOOTING L | E43: FOOTING | I43: FOOTING | M43: FOOTING
A44: NO.OF BAR | C44: pcs | E44: NO.OF BAR | G44: pcs | I44: NO.OF BAR | K44: pcs | M44: NO.OF BAR | O44: pcs
A45: PER ONE | B45: 5 | E45: PER ONE | F45: 5 | I45: PER ONE | J45: 5 | M45: PER ONE | N45: 5
A46: FOOTING W | E46: FOOTING 2 | I46: FOOTING 2 | M46: FOOTING 2
A52: TIE BEAM 1 | E52: TIE BEAM 2 | I52: TIE BEAM 3 | M52: TIE BEAM 4
A54: Total P.= | B54: 40 | C54: m | E54: Total P.= | F54: 50 | G54: m | I54: Total P.= | J54: 51.4 | K54: m | M54: Total P.= | N54: 51.4 | O54: m
A55: W= | B55: 0.4 | C55: m | E55: W= | F55: 0.3 | G55: m | I55: W= | J55: 4 | K55: m | M55: W= | N55: 4 | O55: m
A56: T= | B56: 0.8 | C56: m | E56: T= | F56: 0.4 | G56: m | I56: T= | J56: 0.25 | K56: m | M56: T= | N56: 0.25 | O56: m
A57: NO. OF PCS = | B57: 2 | C57: pcs | E57: NO. OF PCS = | F57: 4 | G57: pcs | I57: NO. OF PCS = | J57: 5 | K57: pcs | M57: NO. OF PCS = | N57: 5 | O57: pcs | Q57: NO. OF PCS = | S57: pcs
A58: Height from N.G.L to TB(top) | B58: 1.3 | C58: m | E58: Height from N.G.L to TB(top) | F58: 1.3 | G58: m | I58: Height from N.G.L to TB(top) | J58: 0.6 | K58: m | M58: Height from N.G.L to TB(top) | N58: 0.6 | O58: m
A59: V= | B59: =B56*B55*B54*B57 -> 25.6 | C59: cu.m. | E59: V= | F59: =F56*F55*F54*F57 -> 24 | G59: cu.m. | I59: V= | J59: =J56*J55*J54*J57 -> 257 | K59: cu.m. | M59: V= | N59: =N56*N55*N54*N57 -> 257 | O59: cu.m.
A61: HORIZONTAL BARS | E61: HORIZONTAL BARS | I61: HORIZONTAL BARS | M61: HORIZONTAL BARS
A63: h.b. Pcs, = | B63: 10 | C63: pcs | E63: h.b. Pcs, = | F63: 5 | G63: pcs | I63: h.b. Pcs, = | J63: 4 | K63: pcs | M63: h.b. Pcs, = | N63: 4 | O63: pcs
A64: SIZE of bars = | B64: 20 | C64: mm | E64: SIZE of bars = | F64: 20 | G64: mm | I64: SIZE of bars = | J64: 12 | K64: mm | M64: SIZE of bars = | N64: 12 | O64: mm
A66: CUTTING BARS | E66: CUTTING BARS | I66: CUTTING BARS | M66: CUTTING BARS
A68: SIZE of bars = | B68: 16 | C68: mm | E68: SIZE of bars = | F68: 16 | G68: mm | I68: SIZE of bars = | J68: 12 | K68: mm | M68: SIZE of bars = | N68: 12 | O68: mm
A69: Length per end support bar = | C69: =B54/4 -> 10 | D69: m | E69: Length per end support bar = | G69: =F54/4 -> 12.5 | H69: m | I69: Length per end support bar = | K69: =J54/4 -> 12.85 | L69: m | M69: Length per end support bar = | O69: =N54/4 -> 12.85 | P69: m
A70: cutt. Bars pcs. Support | C70: 2 | D70: m | E70: cutt. Bars pcs. Support | G70: 2 | H70: m | I70: cutt. Bars pcs. Support | K70: 4 | L70: m | M70: cutt. Bars pcs. Support | O70: 4 | P70: m
A71: Length per mid span bar = | C71: =B54-((B54/8)*(2)) -> 30 | D71: m | E71: Length per mid span bar = | G71: =F54-((F54/8)*(2)) -> 37.5 | H71: m | I71: Length per mid span bar = | K71: =J54-((J54/8)*(2)) -> 38.55 | L71: m | M71: Length per mid span bar = | O71: =N54-((N54/8)*(2)) -> 38.55 | P71: m
A72: cutt. Bars pcs. Mid | C72: 2 | D72: m | E72: cutt. Bars pcs. Mid | G72: 2 | H72: m | I72: cutt. Bars pcs. Mid | K72: 1 | L72: m | M72: cutt. Bars pcs. Mid | O72: 1 | P72: m
A74: STIRR UPS | E74: STIRR UPS | I74: STIRR UPS | M74: STIRR UPS
A75: BAR SIZE = | B75: 10 | C75: mm | E75: BAR SIZE = | F75: 10 | G75: mm | I75: BAR SIZE = | J75: 10 | K75: mm | M75: BAR SIZE = | N75: 10 | O75: mm
A76: n1= | B76: 10 | C76: s1= | D76: 0.05 | E76: n1= | F76: 10 | G76: s1= | H76: 0.05 | I76: n1= | J76: 10 | K76: s1= | L76: 0.05 | M76: n1= | N76: 10 | O76: s1= | P76: 0.05
A77: n2= | B77: 10 | C77: s2= | D77: 0.1 | E77: n2= | F77: 10 | G77: s2= | H77: 0.1 | I77: n2= | J77: 10 | K77: s2= | L77: 0.1 | M77: n2= | N77: 10 | O77: s2= | P77: 0.1
A78: n3= | B78: 10 | C78: s3= | D78: 0.15 | E78: n3= | F78: 10 | G78: s3= | H78: 0.15 | I78: n3= | J78: 10 | K78: s3= | L78: 0.15 | M78: n3= | N78: 10 | O78: s3= | P78: 0.15
A79: n4= | B79: 0 | C79: s4= | D79: 0 | E79: n4= | F79: 0 | G79: s4= | H79: 0 | I79: n4= | J79: 10 | K79: s4= | L79: 0.2 | M79: n4= | N79: 10 | O79: s4= | P79: 0.2
C80: s5= | D80: 0.2 | G80: s5= | H80: 0.2 | K80: s5= | L80: 0.25 | O80: s5= | P80: 0.25
A82: BEAM 1 | E82: BEAM 2 | I82: BEAM 3 | M82: BEAM 4
A84: Total P.= | B84: 51.4 | C84: m | E84: Total P.= | F84: 51.4 | G84: m | I84: Total P.= | J84: 51.4 | K84: m | M84: Total P.= | N84: 51.4 | O84: m
A85: W= | B85: 4 | C85: m | E85: W= | F85: 4 | G85: m | I85: W= | J85: 4 | K85: m | M85: W= | N85: 4 | O85: m
A86: T= | B86: 0.25 | C86: m | E86: T= | F86: 0.25 | G86: m | I86: T= | J86: 0.25 | K86: m | M86: T= | N86: 0.25 | O86: m
A87: NO. OF PCS = | B87: 5 | C87: pcs | E87: NO. OF PCS = | F87: 5 | G87: pcs | I87: NO. OF PCS = | J87: 5 | K87: pcs | M87: NO. OF PCS = | N87: 5 | O87: pcs | Q87: NO. OF PCS = | S87: pcs
A88: V= | B88: =B86*B85*B84*B87 -> 257 | C88: cu.m. | E88: V= | F88: =F86*F85*F84*F87 -> 257 | G88: cu.m. | I88: V= | J88: =J86*J85*J84*J87 -> 257 | K88: cu.m. | M88: V= | N88: =N86*N85*N84*N87 -> 257 | O88: cu.m.
A90: HORIZONTAL BARS | E90: HORIZONTAL BARS | I90: HORIZONTAL BARS | M90: HORIZONTAL BARS
A92: h.b. Pcs, = | B92: 4 | C92: pcs | E92: h.b. Pcs, = | F92: 4 | G92: pcs | I92: h.b. Pcs, = | J92: 4 | K92: pcs | M92: h.b. Pcs, = | N92: 4 | O92: pcs
A93: SIZE of bars = | B93: 12 | C93: mm | E93: SIZE of bars = | F93: 12 | G93: mm | I93: SIZE of bars = | J93: 12 | K93: mm | M93: SIZE of bars = | N93: 12 | O93: mm
A95: CUTTING BARS | E95: CUTTING BARS | I95: CUTTING BARS | M95: CUTTING BARS
A97: SIZE of bars = | B97: 12 | C97: mm | E97: SIZE of bars = | F97: 12 | G97: mm | I97: SIZE of bars = | J97: 12 | K97: mm | M97: SIZE of bars = | N97: 12 | O97: mm
A98: Length per end support bar = | C98: =B84/4 -> 12.85 | D98: m | E98: Length per end support bar = | G98: =F84/4 -> 12.85 | H98: m | I98: Length per end support bar = | K98: =J84/4 -> 12.85 | L98: m | M98: Length per end support bar = | O98: =N84/4 -> 12.85 | P98: m
A99: cutt. Bars pcs. Support | C99: 4 | D99: m | E99: cutt. Bars pcs. Support | G99: 4 | H99: m | I99: cutt. Bars pcs. Support | K99: 4 | L99: m | M99: cutt. Bars pcs. Support | O99: 4 | P99: m
A100: Length per mid span bar = | C100: =B84-((B84/8)*(2)) -> 38.55 | D100: m | E100: Length per mid span bar = | G100: =F84-((F84/8)*(2)) -> 38.55 | H100: m | I100: Length per mid span bar = | K100: =J84-((J84/8)*(2)) -> 38.55 | L100: m | M100: Length per mid span bar = | O100: =N84-((N84/8)*(2)) -> 38.55 | P100: m
A101: cutt. Bars pcs. Mid | C101: 1 | D101: m | E101: cutt. Bars pcs. Mid | G101: 1 | H101: m | I101: cutt. Bars pcs. Mid | K101: 1 | L101: m | M101: cutt. Bars pcs. Mid | O101: 1 | P101: m
A103: STIRR UPS | E103: STIRR UPS | I103: STIRR UPS | M103: STIRR UPS
A104: BAR SIZE = | B104: 10 | C104: mm | E104: BAR SIZE = | F104: 10 | G104: mm | I104: BAR SIZE = | J104: 10 | K104: mm | M104: BAR SIZE = | N104: 10 | O104: mm
A105: n1= | B105: 10 | C105: s1= | D105: 0.05 | E105: n1= | F105: 10 | G105: s1= | H105: 0.05 | I105: n1= | J105: 10 | K105: s1= | L105: 0.05 | M105: n1= | N105: 10 | O105: s1= | P105: 0.05
A106: n2= | B106: 10 | C106: s2= | D106: 0.1 | E106: n2= | F106: 10 | G106: s2= | H106: 0.1 | I106: n2= | J106: 10 | K106: s2= | L106: 0.1 | M106: n2= | N106: 10 | O106: s2= | P106: 0.1
A107: n3= | B107: 10 | C107: s3= | D107: 0.15 | E107: n3= | F107: 10 | G107: s3= | H107: 0.15 | I107: n3= | J107: 10 | K107: s3= | L107: 0.15 | M107: n3= | N107: 10 | O107: s3= | P107: 0.15
A108: n4= | B108: 10 | C108: s4= | D108: 0.2 | E108: n4= | F108: 10 | G108: s4= | H108: 0.2 | I108: n4= | J108: 10 | K108: s4= | L108: 0.2 | M108: n4= | N108: 10 | O108: s4= | P108: 0.2
C109: s5= | D109: 0.25 | G109: s5= | H109: 0.25 | K109: s5= | L109: 0.25 | O109: s5= | P109: 0.25
A111: WALL FOOTING
A113: Total P.= | B113: 64.6 | C113: m | D113: HORIZONTAL BAR | J113: TIES
A114: W= | B114: 0.4 | C114: m | F114: bar size = | G114: 10 | H114: mm | L114: bar size = | M114: 10 | N114: mm
A115: T= | B115: 0.15 | C115: m | E115: no. Of horizontal bar= | G115: 3 | H115: pcs | K115: no. Of horizontal bar= | M115: 3 | N115: pcs
A116: V= | B116: =B115*B114*B113 -> 3.876 | C116: cu.m. | L116: spacing | M116: 0.4 | N116: m
A118: RAMP
A119: AREA = | B119: 1.2 | C119: m
A120: THICKNESS= | B120: 0.1 | C120: m
A121: V= | B121: =B120*B119 -> 0.12 | C121: cu.m.
A122: bar size = | B122: 12 | C122: mm
A123: TOTAL LENGHT | B123: 100 | C123: m
A124: FLOORING
A126: AREA = | B126: 75.64 | C126: m | D126: spacing = | E126: 0.6 | F126: m
A127: THICKNESS= | B127: 0.1 | C127: m
A128: V= | B128: =B127*B126 -> 7.564 | C128: cu.m.
A129: bar size = | B129: 10 | C129: mm | D129: TOTAL LENGHT | F129: =((((B126)^0.5)/E126)*2)*((B126)^0.5) -> 252.13333 | G129: m
A131: SEPTIC VAULT
...

Sheet ESTIMATES
A1: ESTIMATES MATERIALS
A3: STRUCTURAL EXCAVATION
A5: Vse = (VOLUME OF CF + TB) +SP + CB
A6: Vse = | B6: =(SUM(C13,H13,M13,R13,D20,J20,P20,V20))+C23+(SUM(C31,I31,O31)) -> 2038.388 | C6: CU.M.
A8: C1F1 | F8: C2F2 | K8: C3F3 | P8: C4F4
B9: L+.25= | C9: ='PROJECT DETAILS'!B35+0.25 -> 3.25 | D9: m | G9: L+.25= | H9: ='PROJECT DETAILS'!F35+0.25 -> 2.25 | I9: m | L9: L+.25= | M9: ='PROJECT DETAILS'!J35+0.25 -> 1.25 | N9: m | Q9: L+.25= | R9: ='PROJECT DETAILS'!N35+0.25 -> 1.25 | S9: m
B10: W+.25= | C10: ='PROJECT DETAILS'!B36+0.25 -> 3.25 | D10: m | G10: W+.25= | H10: ='PROJECT DETAILS'!F36+0.25 -> 2.25 | I10: m | L10: W+.25= | M10: ='PROJECT DETAILS'!J35+0.25 -> 1.25 | N10: m | Q10: W+.25= | R10: ='PROJECT DETAILS'!N36+0.25 -> 1.25 | S10: m
B11: Hb= | C11: ='PROJECT DETAILS'!B34 -> 3.35 | D11: m | G11: Hb= | H11: ='PROJECT DETAILS'!F34 -> 2.65 | I11: m | L11: Hb= | M11: ='PROJECT DETAILS'!J34 -> 0.85 | N11: m | Q11: Hb= | R11: ='PROJECT DETAILS'!N34 -> 0.85 | S11: m
B12: NO.OF PCS= | C12: ='PROJECT DETAILS'!B38 -> 10 | D12: pcs | G12: NO.OF PCS= | H12: ='PROJECT DETAILS'!F38 -> 20 | I12: pcs | L12: NO.OF PCS= | M12: ='PROJECT DETAILS'!J38 -> 20 | N12: pcs | Q12: NO.OF PCS= | R12: ='PROJECT DETAILS'!N38 -> 20 | S12: pcs
B13: V= | C13: =C11*C10*C9*C12 -> 353.84375 | D13: m | G13: V= | H13: =H11*H10*H9*H12 -> 268.3125 | I13: m | L13: V= | M13: =M11*M10*M9*M12 -> 26.5625 | N13: m | Q13: V= | R13: =R11*R10*R9*R12 -> 26.5625 | S13: m
A15: TIE BEAM 1 | G15: TIE BEAM 2 | M15: TIE BEAM 3 | S15: TIE BEAM 4
C16: Total P.= | D16: ='PROJECT DETAILS'!B54 -> 40 | E16: m | I16: Total P.= | J16: ='PROJECT DETAILS'!F54 -> 50 | K16: m | O16: Total P.= | P16: ='PROJECT DETAILS'!J54 -> 51.4 | Q16: m | U16: Total P.= | V16: ='PROJECT DETAILS'!N54 -> 51.4 | W16: m
C17: W= | D17: ='PROJECT DETAILS'!B55 -> 0.4 | E17: m | I17: W= | J17: ='PROJECT DETAILS'!F55 -> 0.3 | K17: m | O17: W= | P17: ='PROJECT DETAILS'!J55 -> 4 | Q17: m | U17: W= | V17: ='PROJECT DETAILS'!N55 -> 4 | W17: m
C18: Height from N.G.L to TB(top) | D18: ='PROJECT DETAILS'!B58 -> 1.3 | E18: m | I18: Height from N.G.L to TB(top) | J18: ='PROJECT DETAILS'!F58 -> 1.3 | K18: m | O18: Height from N.G.L to TB(top) | P18: ='PROJECT DETAILS'!J58 -> 0.6 | Q18: m | U18: Height from N.G.L to TB(top) | V18: ='PROJECT DETAILS'!N58 -> 0.6 | W18: m
C19: NO. OF PCS = | D19: ='PROJECT DETAILS'!B57 -> 2 | E19: PCS | I19: NO. OF PCS = | J19: ='PROJECT DETAILS'!F57 -> 4 | K19: PCS | O19: NO. OF PCS = | P19: ='PROJECT DETAILS'!J57 -> 5 | Q19: PCS | U19: NO. OF PCS = | V19: ='PROJECT DETAILS'!N57 -> 5 | W19: PCS
C20: V= | D20: =D18*D17*D16*D19 -> 41.6 | E20: cu.m. | I20: V= | J20: =J18*J17*J16*J19 -> 78 | K20: cu.m. | O20: V= | P20: =P18*P17*P16*P19 -> 616.8 | Q20: cu.m. | U20: V= | V20: =V18*V17*V16*V19 -> 616.8 | W20: cu.m.
C22: SP = Hsp x Wsp x Lsp
B23: SP = | C23: =D25*D26*D27 -> 8.60625 | D23: cu.m.
C25: Hsp = | D25: ='PROJECT DETAILS'!B133 -> 1.7 | E25: m
C26: Wsp+.25 = | D26: ='PROJECT DETAILS'!B134+0.25 -> 1.35 | E26: m
C27: Lsp+.25 = | D27: ='PROJECT DETAILS'!B135+0.25 -> 3.75 | E27: m
A29: CB1 | G29: CB2 | M29: CB3
C30: CB = Hcb x Wcb x Lcb | I30: CB = Hcb x Wcb x Lcb | O30: CB = Hcb x Wcb x Lcb
B31: CB = | C31: =D33*D34*D35 -> 0.4335 | D31: cu.m. | H31: CB = | I31: =J33*J34*J35 -> 0.4335 | J31: cu.m. | N31: CB = | O31: =P33*P34*P35 -> 0.4335 | P31: cu.m.
C33: Hcb= | D33: ='PROJECT DETAILS'!B141 -> 0.6 | E33: m | I33: Hcb= | J33: ='PROJECT DETAILS'!F141 -> 0.6 | K33: m | O33: Hcb= | P33: ='PROJECT DETAILS'!J141 -> 0.6 | Q33: m
C34: Wcb+.25 = | D34: ='PROJECT DETAILS'!B142+0.25 -> 0.85 | E34: m | I34: Wcb+.25 = | J34: ='PROJECT DETAILS'!F142+0.25 -> 0.85 | K34: m | O34: Wcb+.25 = | P34: ='PROJECT DETAILS'!J142+0.25 -> 0.85 | Q34: m
C35: Lcb+.25 = | D35: ='PROJECT DETAILS'!B143+0.25 -> 0.85 | E35: m | I35: Lcb+.25 = | J35: ='PROJECT DETAILS'!F143+0.25 -> 0.85 | K35: m | O35: Lcb+.25 = | P35: ='PROJECT DETAILS'!J143+0.25 -> 0.85 | Q35: m
A37: EMBANKMENT
A39: Ve = Vse - Vcb - Voe + Veb
A40: Ve = | B40: =B6-C43-C65+C86 -> 1308.8595 | C40: CU.M.
B42: Vcb = CFb + Ocb + Mb
B43: Vcb = | C43: =D45+D55+D57 -> 169.7365 | D43: cu.m.
C45: CFb = | D45: =SUM(C53,F53,K53,N53,S53,V53,AA53,AD53) -> 166.345 | E45: cu.m.
A46: CFb
A47: C1 | E47: F1 | I47: C2 | M47: F2 | Q47: C3 | U47: F3 | Y47: C4 | AC47: F4
B49: L = | C49: ='PROJECT DETAILS'!B11 -> 0.7 | D49: m | E49: L = | F49: ='PROJECT DETAILS'!B35 -> 3 | G49: m | J49: L = | K49: ='PROJECT DETAILS'!F11 -> 0.6 | L49: m | M49: L = | N49: ='PROJECT DETAILS'!F35 -> 2 | O49: m | R49: L = | S49: ='PROJECT DETAILS'!J11 -> 0.35 | T49: m | U49: L = | V49: ='PROJECT DETAILS'!J35 -> 1 | W49: m | Z49: L = | AA49: ='PROJECT DETAILS'!N11 -> 0.35 | AB49: m | AC49: L = | AD49: ='PROJECT DETAILS'!N35 -> 1 | AE49: m
B50: W = | C50: ='PROJECT DETAILS'!B12 -> 1.1 | D50: m | E50: W = | F50: ='PROJECT DETAILS'!B36 -> 3 | G50: m | J50: W = | K50: ='PROJECT DETAILS'!F12 -> 0.6 | L50: m | M50: W = | N50: ='PROJECT DETAILS'!F36 -> 2 | O50: m | R50: W = | S50: ='PROJECT DETAILS'!J12 -> 0.35 | T50: m | U50: W = | V50: ='PROJECT DETAILS'!J36 -> 1 | W50: m | Z50: W = | AA50: ='PROJECT DETAILS'!N12 -> 0.35 | AB50: m | AC50: W = | AD50: ='PROJECT DETAILS'!N36 -> 1 | AE50: m
B51: Hb = | C51: ='PROJECT DETAILS'!B10 -> 2.5 | D51: m | E51: T = | F51: ='PROJECT DETAILS'!B37 -> 0.8 | G51: m | J51: Hb = | K51: ='PROJECT DETAILS'!F10 -> 2 | L51: m | M51: T = | N51: ='PROJECT DETAILS'!F37 -> 0.6 | O51: m | R51: Hb = | S51: ='PROJECT DETAILS'!J10 -> 0.55 | T51: m | U51: T = | V51: ='PROJECT DETAILS'!J37 -> 0.25 | W51: m | Z51: Hb = | AA51: ='PROJECT DETAILS'!N10 -> 0.55 | AB51: m | AC51: T = | AD51: ='PROJECT DETAILS'!N37 -> 0.25 | AE51: m
B52: NO. OF PCS = | C52: =C12 -> 10 | D52: pcs | E52: NO. OF PCS = | F52: =C52 -> 10 | G52: pcs | J52: NO. OF PCS = | K52: =H12 -> 20 | L52: pcs | M52: NO. OF PCS = | N52: =K52 -> 20 | O52: pcs | R52: NO. OF PCS = | S52: =M12 -> 20 | T52: pcs | U52: NO. OF PCS = | V52: =S52 -> 20 | W52: pcs | Z52: NO. OF PCS = | AA52: =R12 -> 20 | AB52: pcs | AC52: NO. OF PCS = | AD52: =AA52 -> 20 | AE52: pcs
C53: =C52*C51*C50*C49 -> 19.25 | F53: =F52*F51*F50*F49 -> 72 | K53: =K52*K51*K50*K49 -> 14.4 | N53: =N52*N51*N50*N49 -> 48 | S53: =S52*S51*S50*S49 -> 1.3475 | V53: =V52*V51*V50*V49 -> 5 | AA53: =AA52*AA51*AA50*AA49 -> 1.3475 | AD53: =AD52*AD51*AD50*AD49 -> 5
C55: Ocb = | D55: ='PROJECT DETAILS'!B151 -> 0 | E55: cu.m.
C57: Mb = | D57: =F59*F60*F61 -> 3.3915 | E57: cu.m.
E59: Pwallb= | F59: ='PROJECT DETAILS'!B157 -> 64.6 | G59: m
E60: Wchb = | F60: ='PROJECT DETAILS'!B158 -> 0.15 | G60: m
E61: Hwallb = | F61: ='PROJECT DETAILS'!B159 -> 0.35 | G61: m
B64: Voe = WFb + TB
B65: Voe = | C65: =D68+D76 -> 567.476 | D65: cu.m.
C67: WFb = WFt x TPWF x WWF
C68: WFb = | D68: =F70*F71*F72 -> 3.876 | E68: cu.m.
E70: Total P.= | F70: ='PROJECT DETAILS'!B113 -> 64.6 | G70: m
E71: W= | F71: ='PROJECT DETAILS'!B114 -> 0.4 | G71: m
E72: T= | F72: ='PROJECT DETAILS'!B115 -> 0.15 | G72: m
C75: TB = TBh x TBTP x TBW
C76: TB= | D76: =SUM(D83,P83,V83,J83) -> 563.6 | E76: cu.m.
A78: TIE BEAM 1 | G78: TIE BEAM 2 | M78: TIE BEAM 3 | S78: TIE BEAM 4
C79: Total P.= | D79: ='PROJECT DETAILS'!B54 -> 40 | E79: m | I79: Total P.= | J79: ='PROJECT DETAILS'!F54 -> 50 | K79: m | O79: Total P.= | P79: ='PROJECT DETAILS'!J54 -> 51.4 | Q79: m | U79: Total P.= | V79: ='PROJECT DETAILS'!N54 -> 51.4 | W79: m
C80: W= | D80: ='PROJECT DETAILS'!B55 -> 0.4 | E80: m | I80: W= | J80: ='PROJECT DETAILS'!F55 -> 0.3 | K80: m | O80: W= | P80: ='PROJECT DETAILS'!N55 -> 4 | Q80: m | U80: W= | V80: ='PROJECT DETAILS'!N55 -> 4 | W80: m
C81: T= | D81: ='PROJECT DETAILS'!B56 -> 0.8 | E81: m | I81: T= | J81: ='PROJECT DETAILS'!F56 -> 0.4 | K81: m | O81: T= | P81: ='PROJECT DETAILS'!N56 -> 0.25 | Q81: m | U81: T= | V81: ='PROJECT DETAILS'!N56 -> 0.25 | W81: m
C82: NO. OF PCS = | D82: ='PROJECT DETAILS'!B57 -> 2 | E82: PCS | I82: NO. OF PCS = | J82: ='PROJECT DETAILS'!F57 -> 4 | K82: PCS | O82: NO. OF PCS = | P82: ='PROJECT DETAILS'!J57 -> 5 | Q82: PCS | U82: NO. OF PCS = | V82: ='PROJECT DETAILS'!N57 -> 5 | W82: PCS
C83: V= | D83: =D81*D80*D79*D82 -> 25.6 | E83: cu.m. | I83: V= | J83: =J81*J80*J79*J82 -> 24 | K83: cu.m. | O83: V= | P83: =P81*P80*P79*P82 -> 257 | Q83: cu.m. | U83: V= | V83: =V81*V80*V79*V82 -> 257 | W83: cu.m.
B85: Veb = Vr + Vf
B86: Veb = | C86: =D88+D95 -> 7.684 | D86: cu.m.
C87: Vr = AR x RH
C88: Vr = | D88: =E90*E91 -> 0.12 | E88: cu.m.
D90: AREA = | E90: ='PROJECT DETAILS'!B119 -> 1.2 | F90: m
D91: THICKNESS= | E91: ='PROJECT DETAILS'!B120 -> 0.1 | F91: m
D92: V= | E92: =E91*E90 -> 0.12 | F92: cu.m.
C94: Vf = AF x FHN
C95: Vf = | D95: =E97*E98 -> 7.564 | E95: cu.m.
D97: AREA = | E97: ='PROJECT DETAILS'!B126 -> 75.64 | F97: sq.m
D98: THICKNESS= | E98: ='PROJECT DETAILS'!B127 -> 0.1 | F98: m
D99: V= | E99: =E98*E97 -> 7.564 | F99: cu.m.
A101: STRUCTURAL CONCRETE
A103: VOLUME = | B103: =SUM('PROJECT DETAILS'!B15,'PROJECT DETAILS'!F15,'PROJECT DETAILS'!J15,'PROJECT DETAILS'!N15,'PROJECT DETAILS'!F39,'PROJECT DETAILS'!J39,'PROJECT DETAILS'!N39,'PROJECT DETAILS'!B59,'PROJECT DETAILS'!F59,'PROJECT DETAILS'!J59,'PROJECT DETAILS'!N59,'PROJECT DETAILS'!B116,'PROJECT DETAILS'!B121,'PROJECT DETAILS'!B128,'PROJECT DETAILS'!B144,'PROJECT DETAILS'!F144,'PROJECT DETAILS'!J144,'PROJECT DETAILS'!B151,'PROJECT DETAILS'!B88,'PROJECT DETAILS'!F88,'PROJECT DETAILS'!J88,'PROJECT DETAILS'!N88) -> 1704.783 | C103: cu.m.
A105: REINFORCED STEEL BAR
A107: RSB | B107: =SUM(C110:C114) -> 91.184 | C107: KGS
B109: meter length | C109: kgs
A110: 32mm | B110: 0 | C110: =B110*6.313 -> 0
A111: 25mm | B111: 0 | C111: =B111*3.853 -> 0
A112: 16mm | B112: 0 | C112: =B112*1.578 -> 0
A113: 12mm | B113: =SUM(B122,B135,B191,B199,G199) -> 68 | C113: =B113*0.888 -> 60.384
A114: 10mm | B114: =SUM(B144,G144,B208,B222,F249) -> 50 | C114: =B114*0.616 -> 30.8
A116: FOOTING MATTING
A118: F1 | F118: F2 | K118: F3 | P118: F4
A120: MATTING
A122: size of bars= | B122: ='PROJECT DETAILS'!B40 -> 12 | C122: mm | F122: size of bars= | G122: ='PROJECT DETAILS'!F40 -> 12 | H122: mm | K122: size of bars= | L122: ='PROJECT DETAILS'!J40 -> 12 | M122: mm | P122: size of bars= | Q122: ='PROJECT DETAILS'!N40 -> 12 | R122: mm
A123: hook= | B123: =0.012*B122 -> 0.144 | C123: m | F123: hook= | G123: =0.012*G122 -> 0.144 | H123: m | K123: hook= | L123: =0.012*L122 -> 0.144 | M123: m | P123: hook= | Q123: =0.012*Q122 -> 0.144 | R123: m
A124: length per one bar matting L | C124: ='PROJECT DETAILS'!B35-0.08 -> 2.92 | D124: m | F124: length per one bar matting | H124: ='PROJECT DETAILS'!F35-0.08 -> 1.92 | I124: m | K124: length per one bar matting | M124: ='PROJECT DETAILS'!J35-0.08 -> 0.92 | N124: m | P124: length per one bar matting | R124: ='PROJECT DETAILS'!N35-0.08 -> 0.92 | S124: m
A125: no.of pcs. Per one footing | C125: ='PROJECT DETAILS'!B42 -> 5 | D125: pcs | F125: no.of pcs. Per one footing | H125: ='PROJECT DETAILS'!F42 -> 5 | I125: pcs | K125: no.of pcs. Per one footing | M125: ='PROJECT DETAILS'!J42 -> 5 | N125: pcs | P125: no.of pcs. Per one footing | R125: ='PROJECT DETAILS'!N42 -> 5 | S125: pcs
A126: width per one bar matting W | C126: ='PROJECT DETAILS'!B36-0.08 -> 2.92 | D126: m | F126: width per one bar matting | H126: ='PROJECT DETAILS'!F36-0.08 -> 1.92 | I126: m | K126: width per one bar matting | M126: ='PROJECT DETAILS'!J36-0.08 -> 0.92 | N126: m | P126: width per one bar matting | R126: ='PROJECT DETAILS'!N36-0.08 -> 0.92 | S126: m
A127: no.of pcs. Per one footing | C127: ='PROJECT DETAILS'!B45 -> 5 | D127: pcs | F127: no.of pcs. Per one footing | H127: ='PROJECT DETAILS'!F45 -> 5 | I127: pcs | K127: no.of pcs. Per one footing | M127: ='PROJECT DETAILS'!J45 -> 5 | N127: pcs | P127: no.of pcs. Per one footing | R127: ='PROJECT DETAILS'!N45 -> 5 | S127: pcs
B128: TOTAL LENGTH = | C128: =((C124*C125)+(C126*C127))*'PROJECT DETAILS'!B38 -> 292 | D128: m | G128: TOTAL LENGTH = | H128: =((H124*H125)+(H126*H127))*'PROJECT DETAILS'!F38 -> 384 | I128: m | L128: TOTAL LENGTH = | M128: =((M124*M125)+(M126*M127))*'PROJECT DETAILS'!J38 -> 184 | N128: m | Q128: TOTAL LENGTH = | R128: =((R124*R125)+(R126*R127))*'PROJECT DETAILS'!N38 -> 184 | S128: m
A131: C1 | F131: C2 | K131: C3 | P131: C4
A133: VERTICAL BAR
A135: size of bars = | B135: ='PROJECT DETAILS'!B16 -> 20 | C135: mm | F135: size of bars = | G135: ='PROJECT DETAILS'!F16 -> 20 | H135: mm | K135: size of bars = | L135: ='PROJECT DETAILS'!J16 -> 12 | M135: mm | P135: size of bars = | Q135: ='PROJECT DETAILS'!N16 -> 12 | R135: mm
A136: bend = | B136: =0.05*B135 -> 1 | C136: m | F136: bend = | G136: =0.05*G135 -> 1 | H136: m | K136: bend = | L136: =0.05*L135 -> 0.6 | M136: m | P136: bend = | Q136: =0.05*Q135 -> 0.6 | R136: m
A137: dowel = | B137: 0.5 | C137: m | F137: dowel = | G137: 0.5 | H137: m | K137: dowel = | L137: 0.5 | M137: m | P137: dowel = | Q137: 0.5 | R137: m
A138: Length per one bar v.b. = | C138: =B136+('PROJECT DETAILS'!B37-0.05)+'PROJECT DETAILS'!B10+'PROJECT DETAILS'!B13+B137 -> 8.35 | D138: m | F138: Length per one bar v.b. = | H138: =G136+('PROJECT DETAILS'!F37-0.05)+'PROJECT DETAILS'!F10+'PROJECT DETAILS'!F13+G137 -> 5.25 | I138: m | K138: Length per one bar v.b. = | M138: =L136+('PROJECT DETAILS'!J37-0.05)+'PROJECT DETAILS'!J10+'PROJECT DETAILS'!J13+L137 -> 4.85 | N138: m | P138: Length per one bar v.b. = | R138: =Q136+('PROJECT DETAILS'!N37-0.05)+'PROJECT DETAILS'!N10+'PROJECT DETAILS'!N13+Q137 -> 4.85 | S138: m
A139: no.of pcs. Per one column | C139: ='PROJECT DETAILS'!B18 -> 14 | D139: pcs | F139: no.of pcs. Per one column | H139: ='PROJECT DETAILS'!F18 -> 12 | I139: pcs | K139: no.of pcs. Per one column | M139: ='PROJECT DETAILS'!J18 -> 4 | N139: pcs | P139: no.of pcs. Per one column | R139: ='PROJECT DETAILS'!N18 -> 4 | S139: pcs
B140: TOTAL LENGTH = | C140: =C138*C139*'PROJECT DETAILS'!B14 -> 1169 | D140: m | G140: TOTAL LENGTH = | H140: =H138*H139*'PROJECT DETAILS'!F14 -> 1260 | I140: m | L140: TOTAL LENGTH = | M140: =M138*M139*'PROJECT DETAILS'!J14 -> 174.6 | N140: m | Q140: TOTAL LENGTH = | R140: =R138*R139*'PROJECT DETAILS'!N14 -> 174.6 | S140: m
...

Sheet SUMMARIZE QUANTITY
A1: SCOPE OF WORK | B1: QUANTITY | C1: UNITS
A3: STRUCTURAL EXCAVATION | B3: =ESTIMATES!B6 -> 2038.388 | C3: cu.m.
A4: EMBANKMENT | B4: =ESTIMATES!B40 -> 1308.8595 | C4: cu.m.
A5: MASONRY WORKS | B5: =ESTIMATES!C245 -> 130.7675 | C5: sq.m.
A6: STRUCTURAL CONCRETE | B6: =ESTIMATES!B103 -> 1704.783 | C6: cu.m.
A7: REINFORCE STEEL BAR | B7: =ESTIMATES!B107 -> 91.184 | C7: kgs
A8: STEEL WORKS | B8: =SUM(B10:B27,E10:E27) -> 243.33 | C8: ln.m.
A9: TOP BARS | D9: TOP BARS
A10: GIRT 1 | B10: =ESTIMATES!B265 -> 1 | C10: ln.m. | D10: GIRT 1 | E10: =ESTIMATES!I265 -> 0 | F10: ln.m.
A11: GIRT 2 | B11: =ESTIMATES!B266 -> 1 | C11: ln.m. | D11: GIRT 2 | E11: =ESTIMATES!I266 -> 0 | F11: ln.m.
A12: GIRT 3 | B12: =ESTIMATES!B267 -> 2 | C12: ln.m. | D12: GIRT 3 | E12: =ESTIMATES!I267 -> 0 | F12: ln.m.
A13: GIRT 4 | B13: =ESTIMATES!B268 -> 3 | C13: ln.m. | D13: GIRT 4 | E13: =ESTIMATES!I268 -> 0 | F13: ln.m.
A14: GIRT 5 | B14: =ESTIMATES!B269 -> 4 | C14: ln.m. | D14: GIRT 5 | E14: =ESTIMATES!I269 -> 0 | F14: ln.m.
A15: GIRT 6 | B15: =ESTIMATES!B270 -> 5 | C15: ln.m. | D15: GIRT 6 | E15: =ESTIMATES!I270 -> 0 | F15: ln.m.
A16: GIRT 7 | B16: =ESTIMATES!B271 -> 6 | C16: ln.m. | D16: GIRT 7 | E16: =ESTIMATES!I271 -> 0 | F16: ln.m.
A17: GIRT 8 | B17: =ESTIMATES!B272 -> 7 | C17: ln.m. | D17: GIRT 8 | E17: =ESTIMATES!I272 -> 0 | F17: ln.m.
A18: GIRT 9 | B18: =ESTIMATES!B273 -> 8 | C18: ln.m. | D18: GIRT 9 | E18: =ESTIMATES!I273 -> 0 | F18: ln.m.
A19: TRUSS 1 | B19: =ESTIMATES!E265 -> 53.44 | C19: ln.m. | D19: TRUSS 1 | E19: =ESTIMATES!L265 -> 45 | F19: ln.m.
A20: TRUSS 2 | B20: =ESTIMATES!E266 -> 53.44 | C20: ln.m. | D20: TRUSS 2 | E20: =ESTIMATES!L266 -> 21.95 | F20: ln.m.
A21: TRUSS 3 | B21: =ESTIMATES!E267 -> 25.4 | C21: ln.m. | D21: TRUSS 3 | E21: =ESTIMATES!L267 -> 7.1 | F21: ln.m.
A22: TRUSS 4 | B22: =ESTIMATES!E268 -> 0 | C22: ln.m. | D22: TRUSS 4 | E22: =ESTIMATES!L268 -> 0 | F22: ln.m.
A23: TRUSS 5 | B23: =ESTIMATES!E269 -> 0 | C23: ln.m. | D23: TRUSS 5 | E23: =ESTIMATES!L269 -> 0 | F23: ln.m.
A24: TRUSS 6 | B24: =ESTIMATES!E270 -> 0 | C24: ln.m. | D24: TRUSS 6 | E24: =ESTIMATES!L270 -> 0 | F24: ln.m.
A25: TRUSS 7 | B25: =ESTIMATES!E271 -> 0 | C25: ln.m. | D25: TRUSS 7 | E25: =ESTIMATES!L271 -> 0 | F25: ln.m.
A26: TRUSS 8 | B26: =ESTIMATES!E272 -> 0 | C26: ln.m. | D26: TRUSS 8 | E26: =ESTIMATES!L272 -> 0 | F26: ln.m.
A27: TRUSS 9 | B27: =ESTIMATES!E273 -> 0 | C27: ln.m. | D27: TRUSS 9 | E27: =ESTIMATES!L273 -> 0 | F27: ln.m.
A28: ROOFING WORKS | B28: =ESTIMATES!C254 -> 127.4 | C28: sq.m.
A29: PAINTING WORKS | B29: =ESTIMATES!B283 -> 388.935 | C29: sq.m.
A30: TILE WORKS | B30: =ESTIMATES!B279 -> 89.8 | C30: sq.m.
A31: SEPTIC VAULT | B31: ='PROJECT DETAILS'!B222 -> 1 | C31: lot
A32: PLUMBING WORKS | B32: ='PROJECT DETAILS'!B221 -> 1 | C32: lot
A33: ELETRICAL WORKS | B33: ='PROJECT DETAILS'!B220 -> 1 | C33: circuit
A34: FORMWORKS | B34: ='PROJECT DETAILS'!B226 -> 1 | C34: lumpsum
A35: CARPENTRY WORKS | B35: =ESTIMATES!C260 -> 127.4 | C35: sq.m.
A36: DOORS AND WINDOWS | B36: ='PROJECT DETAILS'!B227 -> 17 | C36: units
A37: BILLBOARDS | B37: ='PROJECT DETAILS'!B224 -> 1 | C37: lumpsum
A38: MOBILIZATION/DEMOLIZATION | B38: ='PROJECT DETAILS'!B228 -> 10 | C38: days
A39: SAFETY PROGRAM | B39: ='PROJECT DETAILS'!B223 -> 1 | C39: lumpsum
A40: BUNKHOUSE | B40: ='PROJECT DETAILS'!B225 -> 1 | C40: lot
A41: DEMOLITON | B41: ='PROJECT DETAILS'!B214 -> 123 | C41: sq.m.

Sheet materials
A1: Scope of Works | B1: Item Discription | C1: Unit | D1: hour rate | E1: CANVASS OF CONSTRUCTION MATERIALS
E2: HAPPY LIVING | F2: CSC | G2: CHUI KIM Int. | H2: CITI HARWARE | I2: HOME SOLUTION | J2: SPRINTER | K2: BUILT-N | L2: DYNAMIC | M2: ADOPTED PRICE
A3: STRUCTURAL EXCAVATION | C3: sq.m.
B5: EQUIPMENTS
B6: BACKHOE | D6: 1537
B7: DUMPTRUCK | D7: 676
A9: EMBANKMENT | C9: sq.m.
B11: EQUIPMENTS
B12: MOTORIZED ROAD GRADER | D12: 2173
B13: WATER TRUCK | D13: 1065
B14: VIBRATORY ROLLER | D14: 1507
B15: Backfill | C15: cu.m | J15: 450 | K15: 500 | L15: 500
B16: Common Borrow (W/ 25% Shringkage factor) | C16: cu.m. | M16: 400 | X16: =T16*Q16 -> 0
B17: Embankment (Heavy Mix) | C17: cu.m | J17: 450 | K17: 400 | L17: 400
A18: STRUCTURAL CONCRETE | C18: sq.m.
B20: Cement, Portland | C20: bags | F20: 320 | J20: 305 | K20: 290 | L20: 290
B21: Cement Sahara | C21: pcks | J21: 45 | K21: 50 | L21: 50
B22: Cement, Wallright | C22: bags | J22: 295 | K22: 287 | L22: 285
B23: Cement, Wallright | C23: bags | J23: 295 | K23: 287 | L23: 285
B24: Gravel, Passing 3/4"ɸ (round) | C24: cu.m | E24: 1010 | F24: 4000 | J24: 1150 | K24: 1200 | L24: 1200
B25: Gravel, Passing 3/4"ɸ (crash) | C25: cu.m | E25: 1055
B26: Gravel, Passing 1"ɸ (round) | C26: cu.m | E26: 795 | F26: 4000 | J26: 1200
B27: Gravel, Passing 1"ɸ (crash) | C27: cu.m | E27: 900
B28: Gravel, Passing 2"ɸ (round) | C28: cu.m | E28: 655 | F28: 4800 | J28: 1200
B29: Gravel, Passing 2"ɸ (crash) | C29: cu.m | E29: 655
B30: W. Sand | C30: cu.m | E30: 325 | F30: 1500 | J30: 450 | K30: 500 | L30: 500
B31: Screened Sand | C31: cu.m | F31: 3500 | J31: 500 | K31: 420
A33: REINFORCE STEEL BAR | C33: sq.m.
B35: Cutting Disc 4"ɸ, Steel | C35: pcs | J35: 95 | K35: 125 | L35: 600
B36: Def. Bar 25mmф | C36: length | F36: 1100 | J36: 990
B37: Def. Bar 20mmф | C37: length | F37: 650 | J37: 580
B38: Def. Bars, 10mmф | C38: length | F38: 150 | J38: 160 | K38: 155 | L38: 175
B39: Def. Bars, 12mmɸ | C39: length | F39: 200 | J39: 250 | K39: 250 | L39: 280
B40: Def. Bars, 16mmф | C40: length | F40: 380 | J40: 380 | K40: 410 | L40: 470
B41: Def. Bar 6mmф | C41: length | J41: 95 | L41: 80
B42: Def. Bars, 8mmф | C42: length | J42: 120 | K42: 120 | L42: 135
B43: Def. Bar, 9mmф | C43: length | J43: 135 | K43: 140 | L43: 165
B44: Hacksaw Blade | C44: pcs | J44: 80 | K44: 90 | L44: 90
B45: W. Sand | C45: cu.m | E45: 325 | F45: 1500 | J45: 450 | K45: 500 | L45: 500
B46: Screened Sand | C46: cu.m | F46: 3500 | J46: 500 | K46: 420
B47: Tie Wire #10 | J47: 80 | K47: 120 | L47: 110
B48: Tie Wire #16 | C48: kgs | F48: 80 | J48: 80 | K48: 90 | L48: 90
B49: Tie Wire #18 | C49: kgs | J49: 90 | K49: 100 | L49: 90
A51: Masonry Works | C51: sq.m.
B52: Boulders 4"ɸ-8"ɸ | C52: cu.m | J52: 950 | K52: 820 | L52: 1000
B53: Cement, Portland | C53: bags | F53: 320 | J53: 305 | K53: 290 | L53: 290
B54: Cement Sahara | C54: pcks | J54: 45 | K54: 50 | L54: 50
B55: Cement, Wallright | C55: bags | J55: 295 | K55: 287 | L55: 285
B56: CHB 4"x8"x16" | C56: pcs | F56: 10 | J56: 12 | K56: 12 | L56: 12
B57: CHB 6"X8"X6 | C57: pcs | F57: 15 | J57: 20 | K57: 20 | L57: 18
B58: Concrete Sealant (Concrete Bond) | C58: gals | J58: 950 | K58: 760
B59: Cut Off Wheel Blade, Concrete | C59: pcs | J59: 280 | K59: 360 | L59: 120
B60: Cut Off Wheel Blade 14" | C60: pcs | J60: 450 | K60: 305 | L60: 550
B61: Cutting Disc 4"ɸ, Steel | C61: pcs | J61: 95 | K61: 125 | L61: 600
B62: Def. Bar 25mmф | C62: length | F62: 1100 | J62: 990
B63: Def. Bar 20mmф | C63: length | F63: 650 | J63: 580
B64: Def. Bars, 10mmф | C64: length | F64: 150 | J64: 160 | K64: 155 | L64: 175
B65: Def. Bars, 12mmɸ | C65: length | F65: 200 | J65: 250 | K65: 250 | L65: 280
B66: Def. Bars, 16mmф | C66: length | F66: 380 | J66: 380 | K66: 410 | L66: 470
B67: Def. Bar 6mmф | C67: length | J67: 95 | L67: 80
B68: Def. Bars, 8mmф | C68: length | J68: 120 | K68: 120 | L68: 135
B69: Def. Bar, 9mmф | C69: length | J69: 135 | K69: 140 | L69: 165
B70: Empty Container | C70: pcs | J70: 180 | K70: 150 | L70: 150
B71: Empty Plastic Sack/Bag | C71: pcs | J71: 10 | K71: 15 | L71: 10
B72: Gravel, Passing 3/4"ɸ (round) | C72: cu.m | E72: 1010 | F72: 4000 | J72: 1150 | K72: 1200 | L72: 1200
B73: Gravel, Passing 3/4"ɸ (crash) | C73: cu.m | E73: 1055
B74: Gravel, Passing 1"ɸ (round) | C74: cu.m | E74: 795 | F74: 4000 | J74: 1200
B75: Gravel, Passing 1"ɸ (crash) | C75: cu.m | E75: 900
B76: Gravel, Passing 2"ɸ (round) | C76: cu.m | E76: 655 | F76: 4800 | J76: 1200
B77: Gravel, Passing 2"ɸ (crash) | C77: cu.m | E77: 655
B78: Grinder Disc | C78: pc | J78: 145 | K78: 85
B79: Hacksaw Blade | C79: pcs | J79: 80 | K79: 90 | L79: 90
B80: Hard ware cloth 1/8" | C80: ln.m. | J80: 130 | K80: 160 | L80: 160
B81: Hardiplex | C81: pc | J81: 615 | K81: 450 | L81: 550
B82: Leveling Hose | C82: m | J82: 18 | K82: 15 | L82: 12
B83: Nylon String | C83: rolls | J83: 65 | K83: 45 | L83: 35
B84: Nylon Strinf #18 | C84: rolls | J84: 65
B85: Plain Bars 10mm ф | C85: pc | F85: 160 | J85: 220
B86: Plain Bar 12mm ф | C86: pc | F86: 270 | J86: 310
B87: Plain Bars 16mmф | C87: pc | F87: 380 | J87: 380
B88: Plain Bars 20mmф | C88: pc | F88: 650 | J88: 680
B89: Plain Bar 25mmф | C89: pc | F89: 1500 | J89: 1050
B90: Rubber Pail | C90: pcs | J90: 85 | K90: 110
B91: River Mixed | C91: cu.m | J91: 450 | K91: 500 | L91: 500
B92: Screen Ga. 16x1x6m | K92: 240
B93: Tie Box | C93: rolls/kg | K93: 95 | L93: 75
B94: Tie Wire #10 | J94: 80 | K94: 120 | L94: 110
B95: Tie Wire #16 | C95: kgs | F95: 80 | J95: 80 | K95: 90 | L95: 90
B96: Tie Wire #18 | C96: kgs | J96: 90 | K96: 100 | L96: 90
B97: W. Sand | C97: cu.m | E97: 325 | F97: 1500 | J97: 450 | K97: 500 | L97: 500
B98: Screened Sand | C98: cu.m | F98: 3500 | J98: 500 | K98: 420
B99: W. Selected Gravel 1"ɸ | C99: cu.m | J99: 1150 | K99: 1100 | L99: 1100
B100: W.Gravel (Mixed) | C100: cu.m | J100: 1150 | K100: 1100 | L100: 1100
A101: SEPTIC VAULT AND PLUMBING WORKS | C101: sq.m.
B103: Adhesive (Tile Adhisive) | C103: bags | J103: 380 | K103: 315 | L103: 390
B104: Angle Valve 1/2"ɸ | C104: pc | J104: 175 | K104: 95 | L104: 250
B105: Angle Valve 1/2"ɸ (Single) | C105: pcs | J105: 175 | K105: 95
B106: Bushing Red 2x1 1/4" | C106: pcs | J106: 65
B107: Ceramic Lavatory w/ Pedestal | C107: sets | J107: 6500
B108: Ceramic Tiles 0.4mx0.4 (Glazed) | C108: pcs | J108: 80
...

Sheet OBR 
A1: Republic of the Philippines
A2: Province of South Cotabato
A3: City of Koronadal
A5: OBLIGATION REQUEST | E5: No. | F5: 100-2018-02
A6: Payee/Office
A7: Office: | B7: CEO | E7: Date:
A8: Address: | B8: City of Koronadal, South Cotabato
A9: Responsibilty | B9: Particulars | C9: F.P.P | D9: Account | E9: Amount
A10: Center | D10: Code
B11: Capital Outlay | D11: 300
B13: Local Development FUND | C13: 8919
B16: Other Structure | D16: 107-02-010
B17: ='POW COVER'!X9 -> Construction of Covered Pathway at City hall Entrance/Exit
B18: ='POW COVER'!E10 -> ( 29 SPAN, 3m length/span)
B19: Materials | F19: =BOM!G191 -> 141931
B20: Labor | F20: =BOM!G243 -> 541064.48
B21: Equipment Rental | F21: =BOM!G244 -> 21350
A24: Total | F24: =SUM(F19:F23) -> 704345.48
A25: Certified: | B25: Charges to appropriate/allotment
B26: necessary, lawful and under my direct supervision
D27: Existence of available appropriation
B28: Supporting Documents valid, proper and legal
A31: Signature: | D31: Signature:
A32: Printed Name: | B32: PETER B. MIGUEL, M.D.,FPSO-HNS | D32: Printed Name: | E32: JULIETA R. GASTALA, MPA
A33: Position: | B33: City Mayor | D33: Position: | E33: City Budget Officer
A35: Date: | D35: Date:
A48: Republic of the Philippines
A49: Province of South Cotabato
A50: City of Koronadal
A51: OBLIGATION REQUEST | E51: No. | F51: 100-2013-11-
A52: Payee/Office
A53: Office: | B53: CMO - SEF | E53: Date:
A54: Address: | B54: City of Koronadal, South Cotabato
A55: Responsibilty | B55: Particulars | C55: F.P.P | D55: Account | E55: Amount
A56: Center | D56: Code
B57: Capital Outlay | D57: 300
B59: Public Education | C59: 3321
B62: Other Structure | D62: 215
B63: Materials | F63: =+'[1]POW SEF'!F187 -> 19500
B64: Labor | F64: =+'[1]POW SEF'!F188+'[1]POW SEF'!F191 -> 15100
B65: Equipment Rental (One Bagger Concrete Mixer) | F65: =+'[1]POW SEF'!F189 -> 3600
B66: Equipment Rental (Welding Machine) | F66: =+'[1]POW SEF'!F190 -> 1800
A71: Total | F71: =SUM(F63:F70) -> 40000
A72: Certified: | B72: Charges to appropriate/allotment
B73: necessary, lawful and under my direct supervision
D74: Existence of available appropriation
B75: Supporting Documents valid, proper and legal
A78: Signature: | D78: Signature:
A79: Printed Name: | B79: PETER B. MIGUEL, M.D.,FPSO-HNS | D79: Printed Name: | E79: JULIETA R. GASTALA, MPA
A80: Position: | B80: City Mayor | D80: Position: | E80: City Budget Officer
A82: Date: | D82: Date:
A95: Republic of the Philippines
A96: Province of South Cotabato
A97: City of Koronadal
A98: OBLIGATION REQUEST | E98: No. | F98: 100-2013-11-
A99: Payee/Office
A100: Office: | B100: CMO - SEF | E100: Date:
A101: Address: | B101: City of Koronadal, South Cotabato
A102: Responsibilty | B102: Particulars | C102: F.P.P | D102: Account | E102: Amount
A103: Center | D103: Code
B104: Capital Outlay | D104: 300
B106: Public Education | C106: 3321
B109: Other Structure | D109: 215
B110: Materials | F110: =+'[1]POW SEF'!#REF! -> #REF!
B111: Labor | F111: =+'[1]POW SEF'!#REF!+'[1]POW SEF'!#REF! -> #REF!
B112: Equipment Rental (One Bagger Concrete Mixer) | F112: =+'[1]POW SEF'!#REF! -> #REF!
A118: Total | F118: =+F110+F111+F112 -> #REF!
A119: Certified: | B119: Charges to appropriate/allotment
B120: necessary, lawful and under my direct supervision
D121: Existence of available appropriation
B122: Supporting Documents valid, proper and legal
A125: Signature: | D125: Signature:
A126: Printed Name: | B126: PETER B. MIGUEL, M.D.,FPSO-HNS | D126: Printed Name: | E126: JULIETA R. GASTALA, MPA
A127: Position: | B127: City Mayor | D127: Position: | E127: City Budget Officer
A129: Date: | D129: Date:
A142: Republic of the Philippines
A143: Province of South Cotabato
A144: City of Koronadal
A145: OBLIGATION REQUEST | E145: No. | F145: 100-2013-11-
A146: Payee/Office
A147: Office: | B147: CMO - SEF | E147: Date:
A148: Address: | B148: City of Koronadal, South Cotabato
A149: Responsibilty | B149: Particulars | C149: F.P.P | D149: Account | E149: Amount
A150: Center | D150: Code
B151: Capital Outlay | D151: 300
B153: Public Education | C153: 3321
B156: Other Structure | D156: 215
B157: Materials | F157: =+'[1]POW SEF'!#REF! -> #REF!
B158: Labor | F158: =+'[1]POW SEF'!#REF!+'[1]POW SEF'!#REF! -> #REF!
B159: Equipment Rental (One Bagger Concrete Mixer) | F159: =+'[1]POW SEF'!#REF! -> #REF!
B160: Equipment Rental (Welding Machine) | F160: =+'[1]POW SEF'!#REF! -> #REF!
A165: Total | F165: =SUM(F157:F164) -> #REF!
A166: Certified: | B166: Charges to appropriate/allotment
B167: necessary, lawful and under my direct supervision
D168: Existence of available appropriation
B169: Supporting Documents valid, proper and legal
A172: Signature: | D172: Signature:
A173: Printed Name: | B173: PETER B. MIGUEL, M.D.,FPSO-HNS | D173: Printed Name: | E173: JULIETA R. GASTALA, MPA
A174: Position: | B174: City Mayor | D174: Position: | E174: City Budget Officer
A176: Date: | D176: Date:
...

Sheet BACKUP

Sheet BOM
A1: Republic of the Philippines
A2: Province of South Cotabato
A3: City of Koronadal
A4: OFFICE OF THE CITY ENGINEER | I4: 9
A5: Project: | B5: Proposed Covered Pathway at PRE Fabrication Isolation Facility
A6: Location: | B6: Back of New City Hall Building, Barangay Zone -111 Koronadal City
A7: Project Cost Php: | B7: =G245 -> 9764780 | H7: 1.1
A9: PROGRAM OF WORKS
A11: ITEM | B11: SCOPE OF WORKS
A13: SPL - 1 | B13: PRE FABRICATION FACILITY | C13: QUANTITY = | D13: 1 | E13: lumpsum
B14: 6m length x 3m width x 2.8m height
C18: a. sliding windows with PVC ( 1150mm x 1130mm) - 2 sets | D18: 18 | E18: lot | F18: 444444.44 | G18: =D18*F18 -> 8000000
C20: b. High Quality steel door 725mmx1970mm ( door panel 0.4mm thick, frame 1.0mm) - 2 sets
C22: c. Flooring 18mm MGO board with quality PVC Cover
C24: d. Wall 50mm polystyrene insulation
C25: e. 50mm glass wool with interior with interior ceilings
C27: f. 4mm powder coated Galvanized sheet roof cover
C28: g. Electrical ( 2 switch, 4 - 2gang, 2 electrical distribution box, 2 led light 18 wats, 2 led light 12 watts, 2 breaker, embedded electrical wiring )
C31: h. 2 -Table and 2 - Chairs for nurse station
C32: i. television - 2 sets
C33: j. steel bed- 2 sets (except for nurse station)
C34: k. foam 3 in 2- sets (except for nurse station)
C35: l. pillowcase - 2 sets (except for nurse station)
C36: m. bedsheet blanket - 4 sets (except for nurse station)
... C44: u. Installation of pre fabrication facility
F45: SUB TOTAL = | G45: =G18 -> 8000000
F47: DIRECT COST= | G47: =G45 -> 8000000
F48: UNIT COST = | G48: =G47/D18 -> 444444.44
A50: ='[2]DUPA KCES1'!F446 -> SPL-5 | B50: FORMWORKS | C50: QUANTITY = | D50: 1 | E50: lumpsum | I50: per span quantity | J50: =D50/17 -> 0.058823529 | K50: =J50*28 -> 1.6470588
A52: Materials
D53: QUANTITY | E53: UNITS | F53: UNIT COST | G53: AMOUNT
C55: 100 coco-lumber ( 2x3x12 ) | D55: 500 | E55: bd.ft | F55: 32.2 | G55: =D55*F55 -> 16100
C56: 100 coco lumber (2x2x12) | D56: 300 | E56: bd.ft | F56: 32.2 | G56: =D56*F56 -> 9660
C57: Marine plywood | D57: 8 | E57: sht | F57: 900 | G57: =D57*F57 -> 7200
C58: Leveling Hose | D58: 20 | E58: m | F58: 35 | G58: =D58*F58 -> 700
C59: Nylon string | D59: 15 | E59: roll | F59: 35 | G59: =D59*F59 -> 525
C60: CWN 4" | D60: 15 | E60: kgs | F60: 85 | G60: =D60*F60 -> 1275
C61: CWN 2 1/2" | D61: 15 | E61: kgs | F61: 85 | G61: =D61*F61 -> 1275
C62: CWN 1 1/2" | D62: 5 | E62: kgs | F62: 85 | G62: =D62*F62 -> 425
F63: SUB TOTAL = | G63: =SUM(G55:G62) -> 37160
F65: DIRECT COST= | G65: =G63 -> 37160
F66: UNIT COST = | G66: =G65/D50 -> 37160
B68: STEEL WORKS ( TRUSS ) | C68: QUANTITY = | D68: =I4*3 -> 27 | E68: sets | I68: per span quantity | J68: =D68/17 -> 1.5882353 | K68: =J68*28 -> 44.470588
A70: Materials
D71: QUANTITY | E71: UNITS | F71: UNIT COST | G71: AMOUNT
C73: 2" diam. GI PIPE SCHEDULE. 40 | D73: =ROUNDUP((D$68*I73)/6,0)+1 -> 45 | E73: length | F73: 2410 | G73: =F73*D73 -> 108450 | I73: =4.88+4.8 -> 9.68
C74: 1 1/2" diam. GI PIPE SCHEDULE. 40 | D74: =ROUNDUP((D$68*I74)/6,0)+1 -> 66 | E74: length | F74: 1765 | G74: =F74*D74 -> 116490 | I74: =6.57*2+1.1 -> 14.24
C75: 6mm thick gusset plate | D75: =ROUNDUP(((D$68*I75)/(1.22*2.44))+1,0) -> 2 | E75: sheet | F75: 6350 | G75: =F75*D75 -> 12700 | I75: =0.32*0.08*0.5*2 -> 0.0256 | K75: =9*3 -> 27
C76: 10mm thick Base plate | D76: =ROUNDUP(((D$68*I76)/6)+1,0) -> 2 | E76: sheet | F76: 6350 | G76: =F76*D76 -> 12700 | I76: =0.25*0.25*2 -> 0.125
C77: Cutting disc | D77: =D68*I77 -> 27 | E77: ='[2]DUPA KCES1'!O550 -> pcs | F77: 120 | G77: =F77*D77 -> 3240 | I77: 1
C78: Welding rod N (1630) | D78: =D68*I78 -> 108 | E78: kgs | F78: 150 | G78: =F78*D78 -> 16200 | I78: 4
F79: SUB TOTAL = | G79: =SUM(G73:G78) -> 269780
I80: =(0.72/(1.22*2.44))*27 -> 6.5305026
A81: Equipment
C82: 1-Electric sander | D82: 7 | E82: days | F82: 350 | G82: =F82*D82 -> 2450
C83: 1 Welding Machine | D83: 7 | E83: days | F83: 500 | G83: =F83*D83 -> 3500
F84: SUB TOTAL = | G84: =G82+G83 -> 5950
F86: DIRECT COST= | G86: =G84+G79 -> 275730
F87: UNIT COST = | G87: =G86/D68 -> 10212.222
B89: STEEL WORKS ( GIRT 1) | C89: QUANTITY = | D89: 2 | E89: sets | I89: per span quantity | J89: =D89/17 -> 0.11764706 | K89: =J89*28 -> 3.2941176
A91: Materials
D92: QUANTITY | E92: UNITS | F92: UNIT COST | G92: AMOUNT
C94: 1/4 x 1 1/2 " angle bar | D94: =ROUNDUP((I94/6)*D89,0)+2 -> 73 | E94: length | F94: 880 | G94: =F94*D94 -> 64240 | I94: =(62.8*2+0.3*2)+1.04*63+0.3*64 -> 210.92
C95: Cutting disc | D95: =ROUNDUP(D77*0.5,0) -> 14 | E95: pcs | F95: 120 | G95: =F95*D95 -> 1680 | I95: 3
C96: Welding rod N (1630) | D96: =D78*0.5 -> 54 | E96: kgs | F96: 150 | G96: =F96*D96 -> 8100 | I96: 4
F97: SUB TOTAL = | G97: =SUM(G94:G96) -> 74020
A99: Equipment
C100: 1 Welding Machine | D100: =D83 -> 7 | E100: days | F100: 500 | G100: =F100*D100 -> 3500
F101: SUB TOTAL = | G101: =G100 -> 3500
F103: DIRECT COST= | G103: =G101+G97 -> 77520
F104: UNIT COST = | G104: =G103/D89 -> 38760
B106: STEEL WORKS ( Gutter Frame ) | C106: QUANTITY = | D106: 2 | E106: set | I106: per span quantity | J106: =D106/17 -> 0.11764706 | K106: =J106*28 -> 3.2941176
A108: Materials
D109: QUANTITY | E109: UNITS | F109: UNIT COST | G109: AMOUNT | K109: =(6.32/6)*16 -> 16.853333
C111: 1/4 x 1 " angle bar | D111: =ROUNDUP((I111/6)*D106,0)+2 -> 74 | E111: length | F111: 550 | G111: =F111*D111 -> 40700 | I111: =(66.8*2+0.2*2)+1.02*67+0.2*67 -> 215.74
C112: Cutting disc | D112: =D95 -> 14 | E112: pcs | F112: 120 | G112: =F112*D112 -> 1680 | I112: 3
C113: Welding rod N (1630) | D113: =D96 -> 54 | E113: kgs | F113: 150 | G113: =F113*D113 -> 8100 | I113: 4
F114: SUB TOTAL = | G114: =SUM(G111:G113) -> 50480
A116: Equipment
C117: 1 Welding Machine | D117: =D100 -> 7 | E117: days | F117: 500 | G117: =F117*D117 -> 3500
F118: SUB TOTAL = | G118: =G117 -> 3500
F120: DIRECT COST= | G120: =G118+G114 -> 53980
F121: UNIT COST = | G121: =G120/D106 -> 26990
B123: Roofing Works | C123: QUANTITY = | D123: =66.8*4.88*1.3 -> 423.7792 | E123: sq.m. | I123: per span quantity | J123: =D123/17 -> 24.928188 | K123: =J123*28 -> 697.98927
A125: Materials
D126: QUANTITY | E126: UNITS | F126: UNIT COST | G126: AMOUNT | K126: =(6.32/6)*16 -> 16.853333
C128: PRE painted rib type long span ( 0.40mm ) | D128: =D123 -> 423.7792 | E128: sq.m. | F128: 260 | G128: =F128*D128 -> 110182.59
C129: PRE fabricated gutter ( 0.40mm ) | D129: =((66.8*2)+(1.3*2))*0.7 -> 95.34 | E129: sq.m. | F129: 52 | G129: =F129*D129 -> 4957.68
C130: 2x3x1.2mm CEE Purlins | D130: =ROUNDUP((4.88/7)*66.8,0)+2 -> 49 | E130: length | F130: 640 | G130: =F130*D130 -> 31360
C131: Vulcaseal | D131: 10 | E131: qrt | F131: 900 | G131: =F131*D131 -> 9000
C132: tex screw 2 1/2 | D132: 600 | E132: pcs | F132: 3 | G132: =F132*D132 -> 1800
C133: Cutting Disc | D133: =D112*0.7 -> 9.8 | E133: pcs | F133: 120 | G133: =F133*D133 -> 1176
C134: Welding rod N (1630) | D134: =D113*0.7 -> 37.8 | E134: kgs | F134: 150 | G134: =F134*D134 -> 5670 | I134: =-G134+#REF! -> #REF!
F135: SUB TOTAL = | G135: =SUM(G128:G134) -> 164146.27
A137: Equipment
C138: 1 Welding Machine | D138: =D117 -> 7 | E138: days | F138: 500 | G138: =F138*D138 -> 3500
C139: 1 Electril Drill | D139: =D138 -> 7 | E139: days | F139: 350 | G139: =F139*D139 -> 2450
C140: 1-Electric sander | D140: =D139 -> 7 | E140: days | F140: 350 | G140: =F140*D140 -> 2450
F141: SUB TOTAL = | G141: =G138+G140+G139 -> 8400
F143: DIRECT COST= | G143: =G135+G141 -> 172546.27
...

Sheet SUMARRY
D1: Republic of the Philippines
D2: Province of South Cotabato
D3: City of Koronadal
D4: CITY MAYORS OFFICE - BARANGAY DEVELOPMENT PROGRAM
D5: PROGRAM OF WORK/BUDGET COST FOR KORONADAL CITY INFRASTRUCTURE PROJECTS
D7: PROJECT: | G7: COMPLETION, RENOVATION AND IMPROVEMENT OF DAY CARE CENTER
N8: Date:
D9: Location: | G9: SITIO BADAC, BARANGAY SARAVIA, PUROK SAN FRANCISCO BARANGAY NEW PANGASINAN, | N9: Total No.of Units: | Q9: 18900000
G10: PUROK BAGONG LIPUNAN BARANGAY SAN ISIDRO AND PUROK KAUSWAGAN BARANGAY SARAVIA | N10: Classification: | Q10: =O136 -> #REF!
N11: Starting Date: | O11: Upon Approval
N12: Total Project Duration: | O12: 70 CD
D13: Estimated Project Cost: | G13: =O136 -> #REF! | N13: No. of Working Days:
D14: Source of Fund: | G14: 20 % LOCAL DEVELOPMENT PLAN ( AIP 2025 ) | N14: No. of Pre-determined:
D15: Project limits: | N15: Unworkable Days:
A17: ITEM | B17: DEPENDENCY | C17: CD | D17: ITEM NO. | F17: DESCRIPTION OF WORK | K17: % OF | L17: EQUIPMENT
K18: TOTAL | L18: QTY | N18: DESCRIPTION
A19: 1 | C19: 11 | D19: =D75 -> RENOVATION OF DAY CARE CENTER AT SITIO BADAC BARANGAY SARAVIA | L19: 3 | N19: ONE BAGGER MIXER
A20: 1 | C20: 11 | D20: =D76 -> I | F20: =F76 -> STRUCTURAL CONCRETE | K20: =O76/O$128 -> #REF! | L20: 5 | N20: BAR CUTTER
A21: 1 | C21: 11 | D21: =D77 -> II | F21: =F77 -> REINFORCE STEEL BAR | K21: =O77/O$128 -> #REF! | L21: 5 | N21: BAR BENDER
A22: 1 | C22: 11 | D22: =D78 -> III | F22: =F78 -> FORMWORKS | K22: =O78/O$128 -> #REF!
A23: 1 | C23: 11 | D23: =D79 -> IV | F23: =F79 -> MASONRY WORKS ( CHB Laying and Plastering ) | K23: =O79/O$128 -> #REF!
A24: 1 | C24: 11 | D24: =D80 -> V | F24: =F80 -> ROOFING WORKS | K24: =O80/O$128 -> #REF!
A25: 1 | C25: 11 | D25: =D81 -> VI | F25: =F81 -> PAINTING WORKS | K25: =O81/O$128 -> #REF!
A26: 1 | C26: 11 | D26: =D82 -> VII | F26: =F82 -> PLUMBING AND TILE WORKS | K26: =O82/O$128 -> #REF!
A27: 1 | C27: 11 | D27: =D83 -> VIII | F27: =F83 -> DOORS AND WINDOWS | K27: =O83/O$128 -> #REF!
A28: 1 | C28: 11 | D28: =D84 -> IX | F28: =F84 -> ELECTRICAL WORKS | K28: =O84/O$128 -> #REF!
A29: 1 | C29: 11 | D29: =D85 -> X | F29: =F85 -> BILLBOARD | K29: =O85/O$128 -> #REF!
A30: 1 | C30: 11 | D30: =D86 -> XI | F30: =F86 -> CEILING WORKS | K30: =O86/O$128 -> #REF!
A31: 1 | C31: 11 | D31: =D87 -> XII | F31: =F87 -> STEEL WORKS | K31: =O87/O$128 -> #REF!
A32: 1 | C32: 11 | D32: =D88 -> SUB TOTAL: | K32: =SUM(K20:K31) -> #REF!
A33: 1 | C33: 11 | D33: =D89 -> IMPROVEMENT OF DAY CARE CENTER AT PUROK SAN FRANCISCO BARANGAY SITE BARANGAY NEW PANGASINAN
A34: 1 | C34: 11 | D34: =D90 -> I | F34: =F90 -> STRUCTURAL CONCRETE | K34: =O90/O$128 -> #REF!
A35: 1 | C35: 11 | D35: =D91 -> II | F35: =F91 -> REINFORCE STEEL BAR | K35: =O91/O$128 -> #REF!
A36: 1 | C36: 11 | D36: =D92 -> III | F36: =F92 -> FORMWORKS | K36: =O92/O$128 -> #REF!
A37: 1 | C37: 11 | D37: =D93 -> IV | F37: =F93 -> MASONRY WORKS ( CHB Laying and Plastering ) | K37: =O93/O$128 -> #REF!
A38: 1 | C38: 11 | D38: =D94 -> V | F38: =F94 -> ROOFING WORKS | K38: =O94/O$128 -> #REF!
A39: 1 | C39: 11 | D39: =D95 -> VI | F39: =F95 -> PAINTING WORKS | K39: =O95/O$128 -> #REF!
A40: 1 | C40: 11 | D40: =D96 -> VII | F40: =F96 -> PLUMBING AND TILE WORKS | K40: =O96/O$128 -> #REF!
A41: 1 | C41: 11 | D41: =D97 -> VIII | F41: =F97 -> DOORS AND WINDOWS | K41: =O97/O$128 -> #REF!
A42: 1 | C42: 11 | D42: =D98 -> IX | F42: =F98 -> ELECTRICAL WORKS | K42: =O98/O$128 -> #REF!
A43: 1 | C43: 11 | D43: =D99 -> X | F43: =F99 -> BILLBOARD | K43: =O99/O$128 -> #REF!
A44: 1 | C44: 11 | D44: =D100 -> XI | F44: =F100 -> CEILING WORKS | K44: =O100/O$128 -> #REF!
A45: 1 | C45: 11 | D45: =D101 -> SUB TOTAL: | K45: =SUM(K34:K44) -> #REF!
A46: 1 | C46: 11 | D46: =D102 -> RENOVATION OF DAY CARE CENTER AT BAGONG LIPUNAN BARANGAY SAN ISIDRO
A47: 1 | C47: 11 | D47: =D103 -> I | F47: =F103 -> STRUCTURAL CONCRETE | K47: =O103/O$128 -> #REF!
A48: 1 | C48: 11 | D48: =D104 -> II | F48: =F104 -> REINFORCE STEEL BAR | K48: =O104/O$128 -> #REF!
A49: 1 | C49: 11 | D49: =D105 -> III | F49: =F105 -> FORMWORKS | K49: =O105/O$128 -> #REF!
A50: 1 | C50: 11 | D50: =D106 -> IV | F50: =F106 -> MASONRY WORKS ( CHB Laying and Plastering ) | K50: =O106/O$128 -> #REF!
A51: 1 | C51: 11 | D51: =D107 -> V | F51: =F107 -> ROOFING WORKS | K51: =O107/O$128 -> #REF!
A52: 1 | C52: 11 | D52: =D108 -> VI | F52: =F108 -> PAINTING WORKS | K52: =O108/O$128 -> #REF!
A53: 1 | C53: 11 | D53: =D109 -> VII | F53: =F109 -> PLUMBING AND TILE WORKS | K53: =O109/O$128 -> #REF!
A54: 1 | C54: 11 | D54: =D110 -> VIII | F54: =F110 -> DOORS AND WINDOWS | K54: =O110/O$128 -> #REF!
A55: 1 | C55: 11 | D55: =D111 -> IX | F55: =F111 -> ELECTRICAL WORKS | K55: =O111/O$128 -> #REF!
A56: 1 | C56: 11 | D56: =D112 -> X | F56: =F112 -> BILLBOARD | K56: =O112/O$128 -> #REF!
A57: 1 | C57: 11 | D57: =D113 -> XI | F57: =F113 -> CEILING WORKS | K57: =O113/O$128 -> #REF!
A58: 1 | C58: 11 | D58: =D114 -> XII | F58: =F114 -> STEEL WORKS | K58: =O114/O$128 -> #REF!
A59: 1 | C59: 11 | D59: =D115 -> SUB TOTAL: | K59: =SUM(K47:K58) -> #REF!
A60: 1 | C60: 11 | D60: =D116 -> CONSTRUCTION OF SEPTIC TANK
A61: 1 | C61: 11 | D61: =D117 -> 0 | F61: =F117 -> 0 | K61: =O117/O$128 -> #REF!
A62: 1 | C62: 11 | D62: =D118 -> #REF! | F62: =F118 -> #REF! | K62: =O118/O$128 -> #REF!
A63: 1 | C63: 11 | D63: =D119 -> #REF! | F63: =F119 -> #REF! | K63: =O119/O$128 -> #REF!
A64: 1 | C64: 11 | D64: =D120 -> #REF! | F64: =F120 -> #REF! | K64: =O120/O$128 -> #REF!
A65: 1 | C65: 11 | D65: =D121 -> #REF! | F65: =F121 -> #REF! | K65: =O121/O$128 -> #REF!
A66: 1 | C66: 11 | D66: =D122 -> #REF! | F66: =F122 -> #REF! | K66: =O122/O$128 -> #REF!
A67: 1 | C67: 11 | D67: =D123 -> #REF! | F67: =F123 -> #REF! | K67: =O123/O$128 -> #REF!
A68: 1 | C68: 11 | D68: =D124 -> #REF! | F68: =F124 -> #REF! | K68: =O124/O$128 -> #REF!
A69: 1 | C69: 11 | D69: =D125 -> VIII | F69: =F125 -> BILLBOARD | K69: =O125/O$128 -> #REF!
A70: 1 | C70: 11 | D70: =D126 -> SUB TOTAL: | K70: =SUM(K61:K69) -> #REF!
D71: GRAND TOTAL: | K71: =SUM(K70,K59,K45,K32) -> #REF! | Q71: =SUM(#REF!) -> #REF!
D72: ESTIMATED COST OF PROPOSED WORK
D73: ITEM NO. | F73: DESCRIPTION | J73: QUANTITY | L73: UNIT | N73: UNIT COST | O73: TOTAL COST
A75: 1 | D75: =BADAC!B6 -> RENOVATION OF DAY CARE CENTER AT SITIO BADAC BARANGAY SARAVIA | Q75: =O75-[3]DUPA!O75 -> -39061.05
A76: =#REF!+1 -> #REF! | D76: =BADAC!A15 -> I | F76: =BADAC!B15 -> STRUCTURAL CONCRETE | J76: =BADAC!D15 -> 2.444 | L76: =BADAC!E15 -> cu.m. | N76: =BADAC!G33 -> 14581.015 | O76: =J76*N76 -> 35636 | Q76: =O76-[3]DUPA!O227 -> 22190.75
A77: =#REF!+1 -> #REF! | D77: =BADAC!A35 -> II | F77: =BADAC!B35 -> REINFORCE STEEL BAR | J77: =BADAC!D35 -> 137.856 | L77: =BADAC!E35 -> kgs | N77: =BADAC!G53 -> 121.99687 | O77: =J77*N77 -> 16818 | Q77: =O77-[3]DUPA!O226 -> 16177.75
A78: =#REF!+1 -> #REF! | D78: =BADAC!A55 -> III | F78: =BADAC!B55 -> FORMWORKS | J78: =BADAC!D55 -> 1 | L78: =BADAC!E55 -> lumpsum | N78: =BADAC!G79 -> 15600.002 | O78: =J78*N78 -> 15600.002 | Q78: =O78-[3]DUPA!O227 -> 2154.752
A79: =#REF!+1 -> #REF! | D79: =BADAC!A81 -> IV | F79: =BADAC!B81 -> MASONRY WORKS ( CHB Laying and Plastering ) | J79: =BADAC!D81 -> 24 | L79: =BADAC!E81 -> sq.m. | N79: =BADAC!G100 -> 2230.25 | O79: =J79*N79 -> 53526 | Q79: =O79-[3]DUPA!O228 -> 40080.75
A80: =#REF!+1 -> #REF! | D80: =BADAC!A102 -> V | F80: =BADAC!B102 -> ROOFING WORKS | J80: =BADAC!D102 -> 18 | L80: =BADAC!E102 -> sq.m. | N80: =BADAC!G125 -> 1911.1111 | O80: =J80*N80 -> 34400 | Q80: =O80-[3]DUPA!O229 -> 34400
A81: =#REF!+1 -> #REF! | D81: =BADAC!A128 -> VI | F81: =BADAC!B128 -> PAINTING WORKS | J81: =BADAC!D128 -> 171 | L81: =BADAC!E128 -> sq.m. | N81: =BADAC!G156 -> 304.32749 | O81: =J81*N81 -> 52040 | Q81: =O81-[3]DUPA!O230 -> 52040
A82: =#REF!+1 -> #REF! | D82: =BADAC!A158 -> VII | F82: =BADAC!B158 -> PLUMBING AND TILE WORKS | J82: =BADAC!D158 -> 1 | L82: =BADAC!E158 -> l.s. | N82: =BADAC!G193 -> 27850 | O82: =J82*N82 -> 27850 | Q82: =O82-[3]DUPA!O231 -> 27850
A83: =#REF!+1 -> #REF! | D83: =BADAC!A195 -> VIII | F83: =BADAC!B195 -> DOORS AND WINDOWS | J83: =BADAC!D195 -> 4 | L83: =BADAC!E195 -> units | N83: =BADAC!G218 -> 11230.5 | O83: =J83*N83 -> 44922 | Q83: =O83-[3]DUPA!O232 -> 44922
A84: =#REF!+1 -> #REF! | D84: =BADAC!A220 -> IX | F84: =BADAC!B220 -> ELECTRICAL WORKS | J84: =BADAC!D220 -> 1 | L84: =BADAC!E220 -> l.s. | N84: =BADAC!G253 -> 19055 | O84: =J84*N84 -> 19055 | Q84: =O84-[3]DUPA!O233 -> 19055
A85: =#REF!+1 -> #REF! | D85: =BADAC!A255 -> X | F85: =BADAC!B255 -> BILLBOARD | J85: =BADAC!D255 -> 1 | L85: =BADAC!E255 -> unit | N85: =BADAC!G269 -> 2906 | O85: =J85*N85 -> 2906 | Q85: =O85-[3]DUPA!O234 -> 2906
A86: =#REF!+1 -> #REF! | D86: =BADAC!A271 -> XI | F86: =BADAC!B271 -> CEILING WORKS | J86: =BADAC!D271 -> 99 | L86: =BADAC!E271 -> sq.m. | N86: =BADAC!G292 -> 551.85354 | O86: =J86*N86 -> 54633.5 | Q86: =O86-[3]DUPA!O235 -> 54633.5
A87: =#REF!+1 -> #REF! | D87: =BADAC!A327 -> XII | F87: =BADAC!B327 -> STEEL WORKS | J87: =BADAC!D327 -> 1 | L87: =BADAC!E327 -> lot | N87: =BADAC!G348 -> 42613.5 | O87: =J87*N87 -> 42613.5 | Q87: =O87-[3]DUPA!O236 -> 42613.5
A88: =#REF!+1 -> #REF! | D88: SUB TOTAL: | O88: =SUM(O76:P87) -> 400000 | Q88: =O88-BADAC!G352 -> 0
A89: 1 | D89: ='SAN FRAN BO4'!B6 -> IMPROVEMENT OF DAY CARE CENTER AT PUROK SAN FRANCISCO BARANGAY SITE BARANGAY NEW PANGASINAN | Q89: =O89-[3]DUPA!O82 -> 0
A90: =#REF!+1 -> #REF! | D90: ='SAN FRAN BO4'!A15 -> I | F90: ='SAN FRAN BO4'!B15 -> STRUCTURAL CONCRETE | J90: ='SAN FRAN BO4'!D15 -> 9.644 | L90: ='SAN FRAN BO4'!E15 -> cu.m. | N90: ='SAN FRAN BO4'!G33 -> 6599.3364 | O90: =J90*N90 -> 63644 | Q90: =O90-[3]DUPA!O158 -> 63644
A91: =#REF!+1 -> #REF! | D91: ='SAN FRAN BO4'!A35 -> II | F91: ='SAN FRAN BO4'!B35 -> REINFORCE STEEL BAR | J91: ='SAN FRAN BO4'!D35 -> 30.712 | L91: ='SAN FRAN BO4'!E35 -> kgs | N91: ='SAN FRAN BO4'!G53 -> 885.90779 | O91: =J91*N91 -> 27208 | Q91: =O91-[3]DUPA!O234 -> 27208
A92: =#REF!+1 -> #REF! | D92: ='SAN FRAN BO4'!A55 -> III | F92: ='SAN FRAN BO4'!B55 -> FORMWORKS | J92: ='SAN FRAN BO4'!D55 -> 1 | L92: ='SAN FRAN BO4'!E55 -> lumpsum | N92: ='SAN FRAN BO4'!G79 -> 18429.003 | O92: =J92*N92 -> 18429.003 | Q92: =O92-[3]DUPA!O234 -> 18429.003
A93: =#REF!+1 -> #REF! | D93: ='SAN FRAN BO4'!A81 -> IV | F93: =BADAC!B81 -> MASONRY WORKS ( CHB Laying and Plastering ) | J93: ='SAN FRAN BO4'!D81 -> 24 | L93: ='SAN FRAN BO4'!E81 -> sq.m. | N93: ='SAN FRAN BO4'!G100 -> 2230.25 | O93: =J93*N93 -> 53526 | Q93: =O93-[3]DUPA!O235 -> 53526
A94: =#REF!+1 -> #REF! | D94: ='SAN FRAN BO4'!A102 -> V | F94: ='SAN FRAN BO4'!B102 -> ROOFING WORKS | J94: ='SAN FRAN BO4'!D102 -> 18 | L94: ='SAN FRAN BO4'!E102 -> sq.m. | N94: ='SAN FRAN BO4'!G125 -> 1911.1111 | O94: =J94*N94 -> 34400 | Q94: =O94-[3]DUPA!O236 -> 34400
A95: =#REF!+1 -> #REF! | D95: ='SAN FRAN BO4'!A128 -> VI | F95: ='SAN FRAN BO4'!B128 -> PAINTING WORKS | J95: ='SAN FRAN BO4'!D128 -> 171 | L95: ='SAN FRAN BO4'!E128 -> sq.m. | N95: ='SAN FRAN BO4'!G156 -> 422.98246 | O95: =J95*N95 -> 72330 | Q95: =O95-[3]DUPA!O237 -> #VALUE!
A96: =#REF!+1 -> #REF! | D96: ='SAN FRAN BO4'!A158 -> VII | F96: ='SAN FRAN BO4'!B158 -> PLUMBING AND TILE WORKS | J96: ='SAN FRAN BO4'!D158 -> 1 | L96: ='SAN FRAN BO4'!E158 -> l.s. | N96: ='SAN FRAN BO4'!G192 -> 27850 | O96: =J96*N96 -> 27850 | Q96: =O96-[3]DUPA!O238 -> 27850
A97: =#REF!+1 -> #REF! | D97: ='SAN FRAN BO4'!A195 -> VIII | F97: ='SAN FRAN BO4'!B195 -> DOORS AND WINDOWS | J97: ='SAN FRAN BO4'!D195 -> 4 | L97: ='SAN FRAN BO4'!E195 -> units | N97: ='SAN FRAN BO4'!G216 -> 7058.75 | O97: =J97*N97 -> 28235 | Q97: =O97-[3]DUPA!O239 -> 28235
A98: =#REF!+1 -> #REF! | D98: ='SAN FRAN BO4'!A218 -> IX | F98: ='SAN FRAN BO4'!B218 -> ELECTRICAL WORKS | J98: ='SAN FRAN BO4'!D218 -> 1 | L98: ='SAN FRAN BO4'!E218 -> l.s. | N98: ='SAN FRAN BO4'!G251 -> 19055 | O98: =J98*N98 -> 19055 | Q98: =O98-[3]DUPA!O240 -> 18875
A99: =#REF!+1 -> #REF! | D99: ='SAN FRAN BO4'!A253 -> X | F99: ='SAN FRAN BO4'!B253 -> BILLBOARD | J99: ='SAN FRAN BO4'!D253 -> 1 | L99: ='SAN FRAN BO4'!E253 -> unit | N99: ='SAN FRAN BO4'!G267 -> 2906 | O99: =J99*N99 -> 2906 | Q99: =O99-[3]DUPA!O241 -> 2621
A100: =#REF!+1 -> #REF! | D100: ='SAN FRAN BO4'!A269 -> XI | F100: ='SAN FRAN BO4'!B269 -> CEILING WORKS | J100: ='SAN FRAN BO4'!D269 -> 99 | L100: ='SAN FRAN BO4'!E269 -> sq.m. | N100: ='SAN FRAN BO4'!G290 -> 529.46465 | O100: =J100*N100 -> 52417 | Q100: =O100-[3]DUPA!O242 -> 52057
A101: =#REF!+1 -> #REF! | D101: SUB TOTAL: | O101: =SUM(O90:P100) -> 400000 | Q101: =O101-'SAN FRAN BO4'!G101 -> 400000
A102: 1 | D102: ='BAGONG LIP.'!B6 -> RENOVATION OF DAY CARE CENTER AT BAGONG LIPUNAN BARANGAY SAN ISIDRO | Q102: =O102-[3]DUPA!O95 -> 0
A103: =#REF!+1 -> #REF! | D103: ='BAGONG LIP.'!A15 -> I | F103: ='BAGONG LIP.'!B15 -> STRUCTURAL CONCRETE | J103: ='BAGONG LIP.'!D15 -> 2.444 | L103: ='BAGONG LIP.'!E15 -> cu.m. | N103: ='BAGONG LIP.'!G33 -> 16108.609 | O103: =J103*N103 -> 39369.44 | Q103: =O103-[3]DUPA!O171 -> 39369.44
...

Sheet PR
A2: Name of the Procuring Entity | E2: Project Reference Number:
E3: Name of Project:
E4: =SUMARRY!G7 -> COMPLETION, RENOVATION AND IMPROVEMENT OF DAY CARE CENTER
A6: Standard Form Number: SF-GOOD-59 | E6: Location of Project:
A7: Revised on July 04, 2022 | E7: =SUMARRY!G9 -> SITIO BADAC, BARANGAY SARAVIA, PUROK SAN FRANCISCO BARANGAY NEW PANGASINAN,
A8: Standard Form Title: Purchase Request
E9: =SUMARRY!G10 -> PUROK BAGONG LIPUNAN BARANGAY SAN ISIDRO AND PUROK KAUSWAGAN BARANGAY SARAVIA
A13: PURCHASE REQUEST
A14: CITY GOVERNMENT OF KORONADAL
A15: LGU
A16: Department: | C16: CMO-BDP | E16: PR No.: | F16: Date: February 24,2025
A17: Section: | E17: SAI No.:
A18: Stock | B18: Unit | C18: Item Description | E18: QTY. | F18: Unit Cost | G18: Amount
A19: No.
A20: =BADAC!B6 -> RENOVATION OF DAY CARE CENTER AT SITIO BADAC BARANGAY SARAVIA
A21: 1 | B21: =BADAC!E27 -> bags | C21: =BADAC!C27 -> Premium Portland Cement ASTM C595 | E21: =BADAC!D27 -> 24 | F21: =BADAC!F27 -> 310 | G21: =F21*E21 -> 7440
A22: =A21+1 -> 2 | B22: =BADAC!E28 -> cu.m. | C22: =BADAC!C28 -> W. Sand | E22: =BADAC!D28 -> 10 | F22: =BADAC!F28 -> 600 | G22: =F22*E22 -> 6000
A23: =A22+1 -> 3 | B23: =BADAC!E29 -> cu.m. | C23: =BADAC!C29 -> Gravel 3/4", Crushed | E23: =BADAC!D29 -> 5 | F23: =BADAC!F29 -> 1450 | G23: =F23*E23 -> 7250 | H23: =SUM(G21:G23) -> 20690
A24: =A23+1 -> 4 | B24: =BADAC!E46 -> length | C24: =BADAC!C46 -> 10mm diam x 6m corr. Deform bar | E24: =BADAC!D46 -> 20 | F24: =BADAC!F46 -> 210 | G24: =F24*E24 -> 4200
A25: =A24+1 -> 5 | B25: =BADAC!E47 -> length | C25: =BADAC!C47 -> 12mm diam x 6m corr. Deform bar | E25: =BADAC!D47 -> 12 | F25: =BADAC!F47 -> 310 | G25: =F25*E25 -> 3720
A26: =A25+1 -> 6 | B26: =BADAC!E48 -> kgs | C26: =BADAC!C48 -> Tie Wire # 16 | E26: =BADAC!D48 -> 10 | F26: =BADAC!F48 -> 110 | G26: =F26*E26 -> 1100
A27: =A26+1 -> 7 | B27: =BADAC!E49 -> pcs | C27: =BADAC!C49 -> Cutting Disc 4" ( Flexiarapid super A 60 U ) | E27: =BADAC!D49 -> 5 | F27: =BADAC!F49 -> 210 | G27: =F27*E27 -> 1050 | H27: =SUM(G24:G27) -> 10070
A28: =A27+1 -> 8 | B28: =BADAC!E67 -> bd.ft | C28: =BADAC!C67 -> Coco-lumber ( 2"x3"x12' ) | E28: =BADAC!D67 -> 120 | F28: =BADAC!F67 -> 38 | G28: =F28*E28 -> 4560
A29: =A28+1 -> 9 | B29: =BADAC!E68 -> bd.ft | C29: =BADAC!C68 -> Coco-lumber ( 2"x2"x12' ) | E29: =BADAC!D68 -> 80 | F29: =BADAC!F68 -> 38 | G29: =F29*E29 -> 3040
A30: =A29+1 -> 10 | B30: =BADAC!E69 -> sht | C30: =BADAC!C69 -> Ordinary plywood 10MM 4'X8' | E30: =BADAC!D69 -> 4 | F30: =BADAC!F69 -> 714 | G30: =F30*E30 -> 2856
A31: =A30+1 -> 11 | B31: =BADAC!E70 -> roll | C31: =BADAC!C70 -> Nylon string ( 0.40mm ) | E31: =BADAC!D70 -> 4 | F31: =BADAC!F70 -> 68 | G31: =F31*E31 -> 272
A32: =A31+1 -> 12 | B32: =BADAC!E71 -> kgs | C32: =BADAC!C71 -> CWN 4" | E32: =BADAC!D71 -> 5 | F32: =BADAC!F71 -> 94 | G32: =F32*E32 -> 470
A33: =A32+1 -> 13 | B33: =BADAC!E72 -> kgs | C33: =BADAC!C72 -> CWN 3" | E33: =BADAC!D72 -> 5 | F33: =BADAC!F72 -> 94 | G33: =F33*E33 -> 470
A34: =A33+1 -> 14 | B34: =BADAC!E73 -> kgs | C34: =BADAC!C73 -> Tie Wire # 16 | E34: =BADAC!D73 -> 3.1182 | F34: =BADAC!F73 -> 110 | G34: =F34*E34 -> 343.002
A35: =A34+1 -> 15 | B35: =BADAC!E74 -> kgs | C35: =BADAC!C74 -> CWN 1 1/2" | E35: =BADAC!D74 -> 3 | F35: =BADAC!F74 -> 94 | G35: =F35*E35 -> 282
A36: =A35+1 -> 16 | B36: =BADAC!E75 -> m | C36: =BADAC!C75 -> Hardware cloth 1/8" | E36: =BADAC!D75 -> 3 | F36: =BADAC!F75 -> 189 | G36: =F36*E36 -> 567 | H36: =SUM(G28:G36) -> 12860.002
A37: =A36+1 -> 17 | B37: =BADAC!E93 -> pcs | C37: =BADAC!C93 -> CHB 4"x8"x16" | E37: =BADAC!D93 -> 300 | F37: =BADAC!F93 -> 13 | G37: =F37*E37 -> 3900
A38: =A37+1 -> 18 | B38: =BADAC!E94 -> length | C38: =BADAC!C94 -> 10mm diam x 6m corr. Deform bar | E38: =BADAC!D94 -> 20 | F38: =BADAC!F94 -> 210 | G38: =F38*E38 -> 4200
A39: =A38+1 -> 19 | B39: =BADAC!E95 -> bags | C39: =BADAC!C95 -> Premium Portland Cement ASTM C595 | E39: =BADAC!D95 -> 90 | F39: =BADAC!F95 -> 310 | G39: =F39*E39 -> 27900
A40: =A39+1 -> 20 | B40: =BADAC!E96 -> cu.m. | C40: =BADAC!C96 -> W. Sand | E40: =BADAC!D96 -> 1 | F40: =BADAC!F96 -> 600 | G40: =F40*E40 -> 600 | H40: =SUM(G37:G40) -> 36600
A41: =A40+1 -> 21 | B41: =BADAC!E114 -> sq.m. | C41: =BADAC!C114 -> Pre fabricated Long Span (0.40mm THK) | E41: =BADAC!D114 -> 18 | F41: =BADAC!F114 -> 520 | G41: =F41*E41 -> 9360
A42: =A41+1 -> 22 | B42: =BADAC!E115 -> pcs | C42: =BADAC!C115 -> Tek Screw #2 | E42: =BADAC!D115 -> 200 | F42: =BADAC!F115 -> 3 | G42: =F42*E42 -> 600
A43: =A42+1 -> 23 | B43: =BADAC!E116 -> length | C43: =BADAC!C116 -> Cee-Purlins 1.2mmx2"x4"x6m | E43: =BADAC!D116 -> 7 | F43: =BADAC!F116 -> 650 | G43: =F43*E43 -> 4550
A44: =A43+1 -> 24 | B44: =BADAC!E117 -> length | C44: =BADAC!C117 -> Cee Purlins 1.2mmx2"x3"x6m | E44: =BADAC!D117 -> 12 | F44: =BADAC!F117 -> 550 | G44: =F44*E44 -> 6600
A45: =A44+1 -> 25 | B45: =BADAC!E118 -> pcs | C45: =BADAC!C118 -> Grinding Stone 4" | E45: =BADAC!D118 -> 5 | F45: =BADAC!F118 -> 120 | G45: =F45*E45 -> 600
A46: =A45+1 -> 26 | B46: =BADAC!E119 -> pcs | C46: =BADAC!C119 -> Drill bit 3/16 | E46: =BADAC!D119 -> 5 | F46: =BADAC!F119 -> 110 | G46: =F46*E46 -> 550
A47: =A46+1 -> 27 | B47: =BADAC!E120 -> kgs | C47: =BADAC!C120 -> Welding Rod 6013 | E47: =BADAC!D120 -> 5 | F47: =BADAC!F120 -> 190 | G47: =F47*E47 -> 950
A48: =A47+1 -> 28 | B48: =BADAC!E121 -> pcs | C48: =BADAC!C121 -> Cutting Disc 4" ( Flexiarapid super A 60 U ) | E48: =BADAC!D121 -> 5 | F48: =BADAC!F121 -> 210 | G48: =F48*E48 -> 1050 | H48: =SUM(G41:G48) -> 24260
A49: =A48+1 -> 29 | B49: =BADAC!E140 -> bags | C49: =BADAC!C140 -> Skim Coat | E49: =BADAC!D140 -> 5 | F49: =BADAC!F140 -> 615 | G49: =F49*E49 -> 3075
A50: =A49+1 -> 30 | B50: =BADAC!E141 -> gals | C50: =BADAC!C141 -> Epoxy Primer gray ( Premium quality ) | E50: =BADAC!D141 -> 5 | F50: =BADAC!F141 -> 850 | G50: =F50*E50 -> 4250
A51: =A50+1 -> 31 | B51: =BADAC!E142 -> gals | C51: =BADAC!C142 -> Semi-Gloss Latex (Raw Sienna) ( Premium quality ) | E51: =BADAC!D142 -> 10 | F51: =BADAC!F142 -> 800 | G51: =F51*E51 -> 8000
A52: =A51+1 -> 32 | B52: =BADAC!E143 -> gals | C52: =BADAC!C143 -> Flat Latex White ( Premium quality ) | E52: =BADAC!D143 -> 14 | F52: =BADAC!F143 -> 810 | G52: =F52*E52 -> 11340
A53: =A52+1 -> 33 | B53: =BADAC!E144 -> qrt | C53: =BADAC!C144 -> Polytuff with hardener | E53: =BADAC!D144 -> 8 | F53: =BADAC!F144 -> 350 | G53: =F53*E53 -> 2800
A54: =A53+1 -> 34 | B54: =BADAC!E145 -> gals | C54: =BADAC!C145 -> Lacquer Thinner ( Mayon ) | E54: =BADAC!D145 -> 7 | F54: =BADAC!F145 -> 650 | G54: =F54*E54 -> 4550
A55: =A54+1 -> 35 | B55: =BADAC!E146 -> sets | C55: =BADAC!C146 -> Roller Brush #7 with pan | E55: =BADAC!D146 -> 8 | F55: =BADAC!F146 -> 250 | G55: =F55*E55 -> 2000
A56: =A55+1 -> 36 | B56: =BADAC!E147 -> pcs | C56: =BADAC!C147 -> Paint Brush #1 | E56: =BADAC!D147 -> 8 | F56: =BADAC!F147 -> 35 | G56: =F56*E56 -> 280
A57: =A56+1 -> 37 | B57: =BADAC!E148 -> pcs | C57: =BADAC!C148 -> Paint Brush #2 | E57: =BADAC!D148 -> 5 | F57: =BADAC!F148 -> 45 | G57: =F57*E57 -> 225
A58: =A57+1 -> 38 | B58: =BADAC!E149 -> pcs | C58: =BADAC!C149 -> Paint Brush #3 | E58: =BADAC!D149 -> 5 | F58: =BADAC!F149 -> 95 | G58: =F58*E58 -> 475
A59: =A58+1 -> 39 | B59: =BADAC!E150 -> pcs | C59: =BADAC!C150 -> Paint Brush #4 | E59: =BADAC!D150 -> 5 | F59: =BADAC!F150 -> 135 | G59: =F59*E59 -> 675
A60: =A59+1 -> 40 | B60: =BADAC!E151 -> pcs | C60: =BADAC!C151 -> Baby Roller 4" | E60: =BADAC!D151 -> 5 | F60: =BADAC!F151 -> 65 | G60: =F60*E60 -> 325
A61: =A60+1 -> 41 | B61: =BADAC!E152 -> sheets | C61: =BADAC!C152 -> Sand Paper #120 | E61: =BADAC!D152 -> 10 | F61: =BADAC!F152 -> 25 | G61: =F61*E61 -> 250 | H61: =SUM(G49:G61) -> 38245
A62: =A61+1 -> 42 | B62: =BADAC!E170 -> pcs | C62: =BADAC!C170 -> Glazed Ceramic Tiles ( 0.60mx0.460m ) | E62: =BADAC!D170 -> 30 | F62: =BADAC!F170 -> 210 | G62: =F62*E62 -> 6300
A63: SUB TOTAL: | G63: =SUM(G20:G62) -> 149025 | H63: =G63-BADAC!H170 -> 0
A64: Purpose/Remarks: | C64: Materials for the SITIO BADAC, BARANGAY SARAVIA, PUROK SAN FRANCISCO BARANGAY PUROK BAGONG LIPUNAN BARANGAY SAN ISIDRO AND PUROK KAUSWAGAN BARANGAY SARAVIA CITY OF KORONADAL
C66: Requested by: | D66: Certified: As to Existence of Available Appropriation: | F66: Approved:
A68: Signature:
A69: Printed Name: | C69: ENGR. JOHN JOVI Z. ANGOR | D69: FRANCES EIREEN S. ABRIS-GATACELO,CPA | F69: ATTY. ELIORDO U. OGENA
A70: Designation: | C70: BDP Program Coordinator | D70: SAO ( Budget Office IV ) OIC Budget Officer | F70: City Mayor
A71: Date:
A73: Name of the Procuring Entity | E73: Project Reference Number:
E74: Name of Project:
E75: =E4 -> COMPLETION, RENOVATION AND IMPROVEMENT OF DAY CARE CENTER
A77: Standard Form Number: SF-GOOD-59 | E77: Location of Project:
A78: Revised on July 04, 2022 | E78: =E7 -> SITIO BADAC, BARANGAY SARAVIA, PUROK SAN FRANCISCO BARANGAY NEW PANGASINAN,
A79: Standard Form Title: Purchase Request
E80: =E9 -> PUROK BAGONG LIPUNAN BARANGAY SAN ISIDRO AND PUROK KAUSWAGAN BARANGAY SARAVIA
A86: PURCHASE REQUEST
A87: CITY GOVERNMENT OF KORONADAL
A88: LGU
A89: Department: | C89: CMO-BDP | E89: PR No.: | F89: =F16 -> Date: February 24,2025
A90: Section: | E90: SAI No.:
A91: Stock | B91: Unit | C91: Item Description | E91: QTY. | F91: Unit Cost | G91: Amount
A92: No.
A93: 43 | B93: =BADAC!E171 -> pcs | C93: =BADAC!C171 -> Unglazed Ceramic Tiles ( 0.40mx0.40m ) | E93: =BADAC!D171 -> 18 | F93: =BADAC!F171 -> 190 | G93: =F93*E93 -> 3420
A94: =A93+1 -> 44 | B94: =BADAC!E172 -> pcs | C94: =BADAC!C172 -> Glazed Ceramic Tiles ( 0.40mx0.40m ) | E94: =BADAC!D172 -> 10 | F94: =BADAC!F172 -> 190 | G94: =F94*E94 -> 1900
A95: =A94+1 -> 45 | B95: =BADAC!E173 -> bags | C95: =BADAC!C173 -> Tile Grout | E95: =BADAC!D173 -> 5 | F95: =BADAC!F173 -> 120 | G95: =F95*E95 -> 600
A96: =A95+1 -> 46 | B96: =BADAC!E174 -> lengths | C96: =BADAC!C174 -> PVC Pipe 4" S1000 | E96: =BADAC!D174 -> 2 | F96: =BADAC!F174 -> 800 | G96: =F96*E96 -> 1600
A97: =A96+1 -> 47 | B97: =BADAC!E175 -> lengths | C97: =BADAC!C175 -> PVC Pipe 2" S1000 | E97: =BADAC!D175 -> 2 | F97: =BADAC!F175 -> 280 | G97: =F97*E97 -> 560
A98: =A97+1 -> 48 | B98: =BADAC!E176 -> lengths | C98: =BADAC!C176 -> PVC Pipe 1/2" S1000 | E98: =BADAC!D176 -> 2 | F98: =BADAC!F176 -> 80 | G98: =F98*E98 -> 160
A99: =A98+1 -> 49 | B99: =BADAC!E177 -> pcs | C99: =BADAC!C177 -> PVC Elbow 90 deg. 4" | E99: =BADAC!D177 -> 3 | F99: =BADAC!F177 -> 60 | G99: =F99*E99 -> 180
A100: =A99+1 -> 50 | B100: =BADAC!E178 -> pcs | C100: =BADAC!C178 -> PVC Elbow 45 deg. 4" | E100: =BADAC!D178 -> 3 | F100: =BADAC!F178 -> 50 | G100: =F100*E100 -> 150
A101: =A100+1 -> 51 | B101: =BADAC!E179 -> pcs | C101: =BADAC!C179 -> PVC WYE Reducer 4"x 2" | E101: =BADAC!D179 -> 3 | F101: =BADAC!F179 -> 105 | G101: =F101*E101 -> 315
A102: =A101+1 -> 52 | B102: =BADAC!E180 -> pcs | C102: =BADAC!C180 -> PVC Clean out 4" | E102: =BADAC!D180 -> 3 | F102: =BADAC!F180 -> 60 | G102: =F102*E102 -> 180
A103: =A102+1 -> 53 | B103: =BADAC!E181 -> pcs | C103: =BADAC!C181 -> PVC P - Trap 2" | E103: =BADAC!D181 -> 2 | F103: =BADAC!F181 -> 60 | G103: =F103*E103 -> 120
A104: =A103+1 -> 54 | B104: =BADAC!E182 -> pcs | C104: =BADAC!C182 -> PVC Elbow 90 deg. 2" | E104: =BADAC!D182 -> 3 | F104: =BADAC!F182 -> 60 | G104: =F104*E104 -> 180
A105: =A104+1 -> 55 | B105: =BADAC!E183 -> rolls | C105: =BADAC!C183 -> Teflon Tape 3/4 | E105: =BADAC!D183 -> 5 | F105: =BADAC!F183 -> 20 | G105: =F105*E105 -> 100
... A110: =A109+1 -> 60 | B110: =BADAC!E188 -> sets | C110: =BADAC!C188 -> Water Close ( Nation ) | E110: =BADAC!D188 -> 2 | F110: =BADAC!F188 -> 1100 | G110: =F110*E110 -> 2200
A111: =A110+1 -> 61 | B111: =BADAC!E189 -> pcs | C111: =BADAC!C189 -> Stainless Floor Drain 4"x4" | E111: =BADAC!D189 -> 2 | F111: =BADAC!F189 -> 150 | G111: =F111*E111 -> 300 | H111: =SUM(G93:G111,G62) -> 19415
A112: 62 | B112: =BADAC!E207 -> set | C112: =BADAC!C207 -> Jalousie Windows with fixed Glass and complete accessories 2.45mx1.50m | E112: =BADAC!D207 -> 2 | F112: =BADAC!F207 -> 7000 | G112: =F112*E112 -> 14000
A114: 63 | B114: =BADAC!E209 -> set | C114: =BADAC!C209 -> Awning Window Analoc Frame with complete accessories | E114: =BADAC!D209 -> 2 | F114: =BADAC!F209 -> 1300 | G114: =F114*E114 -> 2600
A116: 64 | B116: =BADAC!E211 -> set | C116: =BADAC!C211 -> 1.00mx2.10m Pre Painted Decorative Wooden Panel Door With Heavy duty Door Knob and Complete accessories | E116: =BADAC!D211 -> 2 | F116: =BADAC!F211 -> 7500 | G116: =F116*E116 -> 15000
A118: 65 | B118: =BADAC!E213 -> set | C118: =BADAC!C213 -> 0.70mx2.10m PVC Door With Heavy duty Door Knob and Complete accessories | E118: =BADAC!D213 -> 2 | F118: =BADAC!F213 -> 1600 | G118: =F118*E118 -> 3200
H119: =G118+G116+G114+G112 -> 34800
A120: 66 | B120: =BADAC!E231 -> box | C120: =BADAC!C231 -> THHN Wire #2mm | E120: =BADAC!D231 -> 1 | F120: =BADAC!F231 -> 2200 | G120: =F120*E120 -> 2200
A121: =A120+1 -> 67 | B121: =BADAC!E232 -> box | C121: =BADAC!C232 -> THHN Wire #3.5mm | E121: =BADAC!D232 -> 1 | F121: =BADAC!F232 -> 3200 | G121: =F121*E121 -> 3200
...

Sheet BADAC
A1: Republic of the Philippines
A2: Province of South Cotabato | H2: =J270 -> 0.44738746
A3: City of Koronadal | H3: =H352 -> -0.002
A4: CITY MAYORS OFFICE - BARANGAY DEVELOPMENT PROGRAM
A6: Project: | B6: RENOVATION OF DAY CARE CENTER AT SITIO BADAC BARANGAY SARAVIA
A7: Location:
A8: Project Cost Php: | B8: 400000
A10: PROGRAM OF WORKS
A12: ITEM | B12: SCOPE OF WORKS
A15: I | B15: STRUCTURAL CONCRETE | C15: QUANTITY = | D15: =N16+N18+N20 -> 2.444 | E15: cu.m. | H15: 0.4 | J15: L | K15: W | L15: T | N15: VOLUME
H16: 0.4 | J16: 0.6 | K16: 0.6 | L16: 0.1 | M16: 4 | N16: =J16*K16*L16*M16 -> 0.144
A17: Labor | J17: L | K17: W | L17: T | N17: VOLUME
D18: NO. OF PERSONS | E18: NO. OF HOURS | F18: RATE PER HOUR | G18: AMOUNT | J18: 0.25 | K18: 0.25 | L18: 2 | M18: 4 | N18: =J18*K18*L18*M18 -> 0.5
C19: Construction Foreman | D19: 1 | E19: 6 | F19: 615 | G19: =F19*E19*D19 -> 3690 | J19: L | K19: W | L19: T | N19: VOLUME
C20: Skilled Worker ( Carpenter ) | D20: 1 | E20: =E19 -> 6 | F20: 414 | G20: =F20*E20*D20 -> 2484 | J20: 3 | K20: 6 | L20: 0.1 | M20: 1 | N20: =J20*K20*L20*M20 -> 1.8
C21: Skilled Worker ( Mason ) | D21: 2 | E21: =E20 -> 6 | F21: 390 | G21: =F21*E21*D21 -> 4680
C22: Laborer | D22: 2 | E22: =E21 -> 6 | F22: 341 | G22: =F22*E22*D22 -> 4092
F23: SUB TOTAL = | G23: =SUM(G19:G22) -> 14946 | H23: =G23/G32 -> 0.41940734
A24: Materials | H24: 1
D25: QUANTITY | E25: UNITS | F25: UNIT COST | G25: AMOUNT | H25: =#REF! -> #REF!
H26: =H15*H16*H24*H25 -> #REF!
C27: Premium Portland Cement ASTM C595 | D27: =ROUNDUP(D$15*9.5,0) -> 24 | E27: bags | F27: 310 | G27: =F27*D27 -> 7440
C28: W. Sand | D28: 10 | E28: cu.m. | F28: 600 | G28: =F28*D28 -> 6000
C29: Gravel 3/4", Crushed | D29: 5 | E29: cu.m. | F29: 1450 | G29: =F29*D29 -> 7250
F30: SUB TOTAL = | G30: =SUM(G27:G29) -> 20690
F32: DIRECT COST= | G32: =G30+G23 -> 35636
F33: UNIT COST = | G33: =G32/D15 -> 14581.015
A35: II | B35: REINFORCE STEEL BAR | C35: QUANTITY = | D35: =D46*0.616*6+D47*0.888*6 -> 137.856 | E35: kgs | H35: 0.4 | J35: VERT
H36: 0.4 | J36: l | K36: PCS | L36: LN.M.
A37: Labor | J37: 3 | K37: =110/0.4 -> 275 | L37: =J37*K37 -> 825
D38: NO. OF PERSONS | E38: NO. OF HOURS | F38: RATE PER HOUR | G38: AMOUNT
C39: Construction Foreman | D39: 1 | E39: 4 | F39: 615 | G39: =F39*E39*D39 -> 2460 | J39: HOR .BAR
C40: Skilled Worker ( Steel Man ) | D40: 1 | E40: =E39 -> 4 | F40: 390 | G40: =F40*E40*D40 -> 1560 | J40: 110 | K40: 10 | L40: =J40*K40 -> 1100
C41: Laborer | D41: 2 | E41: =E40 -> 4 | F41: 341 | G41: =F41*E41*D41 -> 2728
F42: SUB TOTAL = | G42: =SUM(G39:G41) -> 6748 | H42: =G42/G52 -> 0.40123677 | J42: PLANKS
A43: Materials | H43: 1 | J43: l | K43: PCS | L43: LN.M.
D44: QUANTITY | E44: UNITS | F44: UNIT COST | G44: AMOUNT | H44: =#REF! -> #REF! | J44: 4 | K44: 110 | L44: =J44*K44 -> 440
H45: =H35*H36*H43*H44 -> #REF!
C46: 10mm diam x 6m corr. Deform bar | D46: 20 | E46: length | F46: 210 | G46: =F46*D46 -> 4200
C47: 12mm diam x 6m corr. Deform bar | D47: 12 | E47: length | F47: 310 | G47: =F47*D47 -> 3720
C48: Tie Wire # 16 | D48: 10 | E48: kgs | F48: 110 | G48: =F48*D48 -> 1100
C49: Cutting Disc 4" ( Flexiarapid super A 60 U ) | D49: 5 | E49: pcs | F49: 210 | G49: =F49*D49 -> 1050
F50: SUB TOTAL = | G50: =SUM(G46:G49) -> 10070 | K50: =4*0.3+2 -> 3.2
F52: DIRECT COST= | G52: =G50+G42 -> 16818
F53: UNIT COST = | G53: =G52/D35 -> 121.99687
A55: III | B55: FORMWORKS | C55: QUANTITY = | D55: 1 | E55: lumpsum
A57: Labor
D58: NO. OF PERSONS | E58: NO. OF HOURS | F58: RATE PER HOUR | G58: AMOUNT
C59: Construction Foreman | D59: 1 | E59: 2 | F59: 615 | G59: =F59*E59*D59 -> 1230
C60: Skilled Worker ( Carpenter ) | D60: 1 | E60: =E59 -> 2 | F60: 414 | G60: =F60*E60*D60 -> 828
C61: Laborer | D61: 1 | E61: =E60 -> 2 | F61: 341 | G61: =F61*E61*D61 -> 682
F62: SUB TOTAL = | G62: =SUM(G59:G61) -> 2740 | H62: =G62/G76 -> 0.21306373 | J62: 1
A64: Materials
D65: QUANTITY | E65: UNITS | F65: UNIT COST | G65: AMOUNT
C67: Coco-lumber ( 2"x3"x12' ) | D67: =20*6 -> 120 | E67: bd.ft | F67: 38 | G67: =D67*F67 -> 4560 | J67: =D67*5 -> 600
C68: Coco-lumber ( 2"x2"x12' ) | D68: =20*4 -> 80 | E68: bd.ft | F68: 38 | G68: =D68*F68 -> 3040 | J68: =D68*5 -> 400
C69: Ordinary plywood 10MM 4'X8' | D69: 4 | E69: sht | F69: 714 | G69: =D69*F69 -> 2856 | J69: =D69*5 -> 20
C70: Nylon string ( 0.40mm ) | D70: 4 | E70: roll | F70: 68 | G70: =D70*F70 -> 272 | J70: =D70*5 -> 20
C71: CWN 4" | D71: 5 | E71: kgs | F71: 94 | G71: =D71*F71 -> 470 | J71: =D71*5 -> 25
C72: CWN 3" | D72: 5 | E72: kgs | F72: 94 | G72: =D72*F72 -> 470 | J72: =D72*5 -> 25
C73: Tie Wire # 16 | D73: 3.1182 | E73: kgs | F73: 110 | G73: =D73*F73 -> 343.002 | H73: =H352 -> -0.002 | J73: =D73*5 -> 15.591
C74: CWN 1 1/2" | D74: 3 | E74: kgs | F74: 94 | G74: =D74*F74 -> 282 | J74: =D74*5 -> 15
C75: Hardware cloth 1/8" | D75: 3 | E75: m | F75: 189 | G75: =D75*F75 -> 567 | J75: =D75*5 -> 15
F76: SUB TOTAL = | G76: =SUM(G67:G75) -> 12860.002 | H76: =G76*5 -> 64300.01
F78: DIRECT COST= | G78: =G76+G62 -> 15600.002
F79: UNIT COST = | G79: =G78/D55 -> 15600.002
A81: IV | B81: MASONRY WORKS ( CHB Laying and Plastering ) | C81: QUANTITY = | D81: 24 | E81: sq.m.
A84: Labor
D85: NO. OF PERSONS | E85: NO. OF HOURS | F85: RATE PER HOUR | G85: AMOUNT
C86: Construction Foreman | D86: 1 | E86: 7 | F86: 615 | G86: =F86*E86*D86 -> 4305
C87: Skilled Worker ( Mason ) | D87: 2 | E87: =E86 -> 7 | F87: 390 | G87: =F87*E87*D87 -> 5460
C88: Laborer | D88: 3 | E88: =E87 -> 7 | F88: 341 | G88: =F88*E88*D88 -> 7161
F89: SUB TOTAL = | G89: =SUM(G86:G88) -> 16926 | H89: =G89/G97 -> 0.46245902
A90: Materials
D91: QUANTITY | E91: UNITS | F91: UNIT COST | G91: AMOUNT
C93: CHB 4"x8"x16" | D93: =D81*12.5 -> 300 | E93: pcs | F93: 13 | G93: =F93*D93 -> 3900 | J93: =D93*5 -> 1500
C94: 10mm diam x 6m corr. Deform bar | D94: 20 | E94: length | F94: 210 | G94: =F94*D94 -> 4200 | J94: =52+145 -> 197 | K94: 5 | L94: =K94*J94 -> 985
C95: Premium Portland Cement ASTM C595 | D95: 90 | E95: bags | F95: 310 | G95: =F95*D95 -> 27900
C96: W. Sand | D96: =ROUNDUP(D81*(0.08+0.02),0)-2 -> 1 | E96: cu.m. | F96: 600 | G96: =F96*D96 -> 600
F97: SUB TOTAL = | G97: =SUM(G93:G96) -> 36600 | J97: =40*5 -> 200
F99: DIRECT COST= | G99: =G97+G89 -> 53526 | K99: =14*5 -> 70
F100: UNIT COST = | G100: =G99/D81 -> 2230.25
A102: V | B102: ROOFING WORKS | C102: QUANTITY = | D102: =6*3 -> 18 | E102: sq.m.
A105: Labor
D106: NO. OF PERSONS | E106: NO. OF HOURS | F106: RATE PER HOUR | G106: AMOUNT
C107: Construction Foreman | D107: 1 | E107: 5 | F107: 615 | G107: =F107*E107*D107 -> 3075
C108: Skilled Worker ( Tinsmith ) | D108: 1 | E108: =E107 -> 5 | F108: 390 | G108: =F108*E108*D108 -> 1950
C109: Laborer | D109: 3 | E109: =E108 -> 5 | F109: 341 | G109: =F109*E109*D109 -> 5115
F110: SUB TOTAL = | G110: =SUM(G107:G109) -> 10140 | H110: =G110/G122 -> 0.41797197
A111: Materials
D112: QUANTITY | E112: UNITS | F112: UNIT COST | G112: AMOUNT
J113: =D113*5 -> 0
C114: Pre fabricated Long Span (0.40mm THK) | D114: =D102 -> 18 | E114: sq.m. | F114: 520 | G114: =F114*D114 -> 9360 | J114: =D114*5 -> 90
C115: Tek Screw #2 | D115: 200 | E115: pcs | F115: 3 | G115: =F115*D115 -> 600 | J115: =D115*5 -> 1000
C116: Cee-Purlins 1.2mmx2"x4"x6m | D116: 7 | E116: length | F116: 650 | G116: =F116*D116 -> 4550 | J116: =D116*5 -> 35
C117: Cee Purlins 1.2mmx2"x3"x6m | D117: 12 | E117: length | F117: 550 | G117: =F117*D117 -> 6600 | J117: =D117*5 -> 60
C118: Grinding Stone 4" | D118: 5 | E118: pcs | F118: 120 | G118: =F118*D118 -> 600 | J118: =D118*5 -> 25
C119: Drill bit 3/16 | D119: 5 | E119: pcs | F119: 110 | G119: =F119*D119 -> 550 | J119: =D119*5 -> 25
C120: Welding Rod 6013 | D120: 5 | E120: kgs | F120: 190 | G120: =F120*D120 -> 950 | J120: =D120*5 -> 25
C121: Cutting Disc 4" ( Flexiarapid super A 60 U ) | D121: 5 | E121: pcs | F121: 210 | G121: =F121*D121 -> 1050 | J121: =D121*5 -> 25
...

Sheet SAN FRAN BO4
A1: Republic of the Philippines
A2: Province of South Cotabato | H2: =J268 -> 0.45156841
A3: City of Koronadal | H3: =H295 -> -0.003
A4: CITY MAYORS OFFICE - BARANGAY DEVELOPMENT PROGRAM
A6: Project: | B6: IMPROVEMENT OF DAY CARE CENTER AT PUROK SAN FRANCISCO BARANGAY SITE BARANGAY NEW PANGASINAN
A7: Location:
A8: Project Cost Php: | B8: 400000
A10: PROGRAM OF WORKS
A12: ITEM | B12: SCOPE OF WORKS
A15: I | B15: STRUCTURAL CONCRETE | C15: QUANTITY = | D15: =N16+N18+N20*5 -> 9.644 | E15: cu.m. | H15: 0.4 | J15: L | K15: W | L15: T | N15: VOLUME
H16: 0.4 | J16: 0.6 | K16: 0.6 | L16: 0.1 | M16: 4 | N16: =J16*K16*L16*M16 -> 0.144
A17: Labor | J17: L | K17: W | L17: T | N17: VOLUME
D18: NO. OF PERSONS | E18: NO. OF HOURS | F18: RATE PER HOUR | G18: AMOUNT | J18: 0.25 | K18: 0.25 | L18: 2 | M18: 4 | N18: =J18*K18*L18*M18 -> 0.5
C19: Construction Foreman | D19: 1 | E19: 6 | F19: 615 | G19: =F19*E19*D19 -> 3690 | J19: L | K19: W | L19: T | N19: VOLUME
C20: Skilled Worker ( Carpenter ) | D20: 1 | E20: =E19 -> 6 | F20: 414 | G20: =F20*E20*D20 -> 2484 | J20: 3 | K20: 6 | L20: 0.1 | M20: 1 | N20: =J20*K20*L20*M20 -> 1.8
C21: Skilled Worker ( Mason ) | D21: 3 | E21: =E20 -> 6 | F21: 390 | G21: =F21*E21*D21 -> 7020
C22: Laborer | D22: 5 | E22: =E21 -> 6 | F22: 341 | G22: =F22*E22*D22 -> 10230
F23: SUB TOTAL = | G23: =SUM(G19:G22) -> 23424 | H23: =G23/G32 -> 0.36804726
A24: Materials | H24: 1
D25: QUANTITY | E25: UNITS | F25: UNIT COST | G25: AMOUNT | H25: =#REF! -> #REF!
H26: =H15*H16*H24*H25 -> #REF!
C27: Premium Portland Cement ASTM C595 | D27: =ROUNDUP(D$15*9,0) -> 87 | E27: bags | F27: 310 | G27: =F27*D27 -> 26970
C28: W. Sand | D28: 10 | E28: cu.m. | F28: 600 | G28: =F28*D28 -> 6000
C29: Gravel 3/4", Crushed | D29: 5 | E29: cu.m. | F29: 1450 | G29: =F29*D29 -> 7250
F30: SUB TOTAL = | G30: =SUM(G27:G29) -> 40220
F32: DIRECT COST= | G32: =G30+G23 -> 63644
F33: UNIT COST = | G33: =G32/D15 -> 6599.3364
A35: II | B35: REINFORCE STEEL BAR | C35: QUANTITY = | D35: =D46*0.616+D47*0.888 -> 30.712 | E35: kgs | H35: 0.4 | J35: VERT
H36: 0.4 | J36: l | K36: PCS | L36: LN.M.
A37: Labor | J37: 3 | K37: =110/0.4 -> 275 | L37: =J37*K37 -> 825
D38: NO. OF PERSONS | E38: NO. OF HOURS | F38: RATE PER HOUR | G38: AMOUNT
C39: Construction Foreman | D39: 1 | E39: 6 | F39: 615 | G39: =F39*E39*D39 -> 3690 | J39: HOR .BAR
C40: Skilled Worker ( Steel Man ) | D40: 2 | E40: =E39 -> 6 | F40: 390 | G40: =F40*E40*D40 -> 4680 | J40: 110 | K40: 10 | L40: =J40*K40 -> 1100
C41: Laborer | D41: 3 | E41: =E40 -> 6 | F41: 341 | G41: =F41*E41*D41 -> 6138
F42: SUB TOTAL = | G42: =SUM(G39:G41) -> 14508 | H42: =G42/G52 -> 0.53322552 | J42: PLANKS
A43: Materials | H43: 1 | J43: l | K43: PCS | L43: LN.M.
D44: QUANTITY | E44: UNITS | F44: UNIT COST | G44: AMOUNT | H44: =#REF! -> #REF! | J44: 4 | K44: 110 | L44: =J44*K44 -> 440
H45: =H35*H36*H43*H44 -> #REF!
C46: 10mm diam x 6m corr. Deform bar | D46: 34 | E46: length | F46: 210 | G46: =F46*D46 -> 7140
C47: 12mm diam x 6m corr. Deform bar | D47: 11 | E47: length | F47: 310 | G47: =F47*D47 -> 3410
C48: Tie Wire # 16 | D48: 10 | E48: pcs | F48: 110 | G48: =F48*D48 -> 1100
C49: Cutting Disc 4" ( Flexiarapid super A 60 U ) | D49: 5 | E49: pcs | F49: 210 | G49: =F49*D49 -> 1050
F50: SUB TOTAL = | G50: =SUM(G46:G49) -> 12700 | K50: =4*0.3+2 -> 3.2
F52: DIRECT COST= | G52: =G50+G42 -> 27208
F53: UNIT COST = | G53: =G52/D35 -> 885.90779
A55: III | B55: FORMWORKS | C55: QUANTITY = | D55: 1 | E55: lumpsum
A57: Labor
D58: NO. OF PERSONS | E58: NO. OF HOURS | F58: RATE PER HOUR | G58: AMOUNT
C59: Construction Foreman | D59: 1 | E59: 4 | F59: 615 | G59: =F59*E59*D59 -> 2460
C60: Skilled Worker ( Carpenter ) | D60: 1 | E60: =E59 -> 4 | F60: 414 | G60: =F60*E60*D60 -> 1656
C61: Laborer | D61: 1 | E61: =E60 -> 4 | F61: 341 | G61: =F61*E61*D61 -> 1364
F62: SUB TOTAL = | G62: =SUM(G59:G61) -> 5480 | H62: =G62/G76 -> 0.4231986 | J62: 1
A64: Materials
D65: QUANTITY | E65: UNITS | F65: UNIT COST | G65: AMOUNT
C67: Coco-lumber ( 2"x3"x12' ) | D67: =20*6 -> 120 | E67: bd.ft | F67: 38 | G67: =D67*F67 -> 4560 | J67: =D67*5 -> 600
C68: Coco-lumber ( 2"x2"x12' ) | D68: =20*4 -> 80 | E68: bd.ft | F68: 38 | G68: =D68*F68 -> 3040 | J68: =D68*5 -> 400
C69: Ordinary plywood 10MM 4'X8' | D69: 4 | E69: sht | F69: 714 | G69: =D69*F69 -> 2856 | J69: =D69*5 -> 20
C70: Nylon string ( 0.40mm ) | D70: 4 | E70: roll | F70: 68 | G70: =D70*F70 -> 272 | J70: =D70*5 -> 20
C71: CWN 4" | D71: 5 | E71: kgs | F71: 94 | G71: =D71*F71 -> 470 | J71: =D71*5 -> 25
C72: CWN 3" | D72: 5 | E72: kgs | F72: 94 | G72: =D72*F72 -> 470 | J72: =D72*5 -> 25
C73: Tie Wire # 16 | D73: 3.9273 | E73: kgs | F73: 110 | G73: =D73*F73 -> 432.003 | H73: =H295 -> -0.003 | J73: =D73*5 -> 19.6365
C74: CWN 1 1/2" | D74: 3 | E74: kgs | F74: 94 | G74: =D74*F74 -> 282 | J74: =D74*5 -> 15
C75: Hardware cloth 1/8" | D75: 3 | E75: m | F75: 189 | G75: =D75*F75 -> 567 | J75: =D75*5 -> 15
F76: SUB TOTAL = | G76: =SUM(G67:G75) -> 12949.003 | H76: =G76*5 -> 64745.015
F78: DIRECT COST= | G78: =G76+G62 -> 18429.003
F79: UNIT COST = | G79: =G78/D55 -> 18429.003
A81: IV | B81: MASONRY WORKS ( CHB Laying and Plastering ) | C81: QUANTITY = | D81: 24 | E81: sq.m.
A84: Labor
D85: NO. OF PERSONS | E85: NO. OF HOURS | F85: RATE PER HOUR | G85: AMOUNT
C86: Construction Foreman | D86: 1 | E86: 7 | F86: 615 | G86: =F86*E86*D86 -> 4305
C87: Skilled Worker ( Mason ) | D87: 2 | E87: =E86 -> 7 | F87: 390 | G87: =F87*E87*D87 -> 5460
C88: Laborer | D88: 3 | E88: =E87 -> 7 | F88: 341 | G88: =F88*E88*D88 -> 7161
F89: SUB TOTAL = | G89: =SUM(G86:G88) -> 16926 | H89: =G89/G97 -> 0.46245902
A90: Materials
D91: QUANTITY | E91: UNITS | F91: UNIT COST | G91: AMOUNT
C93: CHB 4"x8"x16" | D93: =D81*12.5 -> 300 | E93: pcs | F93: 13 | G93: =F93*D93 -> 3900 | J93: =D93*5 -> 1500
C94: 10mm diam x 6m corr. Deform bar | D94: 20 | E94: length | F94: 210 | G94: =F94*D94 -> 4200 | J94: =52+145 -> 197 | K94: 5 | L94: =K94*J94 -> 985
C95: Premium Portland Cement ASTM C595 | D95: 90 | E95: bags | F95: 310 | G95: =F95*D95 -> 27900
C96: W. Sand | D96: =ROUNDUP(D81*(0.08+0.02),0)-2 -> 1 | E96: cu.m. | F96: 600 | G96: =F96*D96 -> 600
F97: SUB TOTAL = | G97: =SUM(G93:G96) -> 36600 | J97: =40*5 -> 200
F99: DIRECT COST= | G99: =G97+G89 -> 53526 | K99: =14*5 -> 70
F100: UNIT COST = | G100: =G99/D81 -> 2230.25
A102: V | B102: ROOFING WORKS | C102: QUANTITY = | D102: =6*3 -> 18 | E102: sq.m.
A105: Labor
D106: NO. OF PERSONS | E106: NO. OF HOURS | F106: RATE PER HOUR | G106: AMOUNT
C107: Construction Foreman | D107: 1 | E107: 5 | F107: 615 | G107: =F107*E107*D107 -> 3075
C108: Skilled Worker ( Tinsmith ) | D108: 1 | E108: =E107 -> 5 | F108: 390 | G108: =F108*E108*D108 -> 1950
C109: Laborer | D109: 3 | E109: =E108 -> 5 | F109: 341 | G109: =F109*E109*D109 -> 5115
F110: SUB TOTAL = | G110: =SUM(G107:G109) -> 10140 | H110: =G110/G122 -> 0.41797197
A111: Materials
D112: QUANTITY | E112: UNITS | F112: UNIT COST | G112: AMOUNT
J113: =D113*5 -> 0
C114: Pre fabricated Long Span (0.40mm THK) | D114: =D102 -> 18 | E114: sq.m. | F114: 520 | G114: =F114*D114 -> 9360 | J114: =D114*5 -> 90
C115: Tek Screw #2 | D115: 200 | E115: pcs | F115: 3 | G115: =F115*D115 -> 600 | J115: =D115*5 -> 1000
C116: Cee-Purlins 1.2mmx2"x4"x6m | D116: 7 | E116: length | F116: 650 | G116: =F116*D116 -> 4550 | J116: =D116*5 -> 35
C117: Cee Purlins 1.2mmx2"x3"x6m | D117: 12 | E117: length | F117: 550 | G117: =F117*D117 -> 6600 | J117: =D117*5 -> 60
C118: Grinding Stone 4" | D118: 5 | E118: pcs | F118: 120 | G118: =F118*D118 -> 600 | J118: =D118*5 -> 25
C119: Drill bit 3/16 | D119: 5 | E119: pcs | F119: 110 | G119: =F119*D119 -> 550 | J119: =D119*5 -> 25
C120: Welding Rod 6013 | D120: 5 | E120: kgs | F120: 190 | G120: =F120*D120 -> 950 | J120: =D120*5 -> 25
C121: Cutting Disc 4" ( Flexiarapid super A 60 U ) | D121: 5 | E121: pcs | F121: 210 | G121: =F121*D121 -> 1050 | J121: =D121*5 -> 25
...

Sheet BAGONG LIP.
A1: Republic of the Philippines
A2: Province of South Cotabato | H2: =J270 -> 0.46808423
A3: City of Koronadal | H3: =H352 -> -5719.762
A4: CITY MAYORS OFFICE - BARANGAY DEVELOPMENT PROGRAM
A6: Project: | B6: RENOVATION OF DAY CARE CENTER AT BAGONG LIPUNAN BARANGAY SAN ISIDRO
A7: Location:
A8: Project Cost Php: | B8: 400000
A10: PROGRAM OF WORKS
A12: ITEM | B12: SCOPE OF WORKS
A15: I | B15: STRUCTURAL CONCRETE | C15: QUANTITY = | D15: =N16+N18+N20 -> 2.444 | E15: cu.m. | H15: 0.4 | J15: L | K15: W | L15: T | N15: VOLUME
H16: 0.4 | J16: 0.6 | K16: 0.6 | L16: 0.1 | M16: 4 | N16: =J16*K16*L16*M16 -> 0.144
A17: Labor | J17: L | K17: W | L17: T | N17: VOLUME
D18: NO. OF PERSONS | E18: NO. OF HOURS | F18: RATE PER HOUR | G18: AMOUNT | J18: 0.25 | K18: 0.25 | L18: 2 | M18: 4 | N18: =J18*K18*L18*M18 -> 0.5
C19: Construction Foreman | D19: 1 | E19: 6 | F19: 718 | G19: =F19*E19*D19 -> 4308 | J19: L | K19: W | L19: T | N19: VOLUME
C20: Skilled Worker ( Carpenter ) | D20: 1 | E20: =E19 -> 6 | F20: 528.8 | G20: =F20*E20*D20 -> 3172.8 | J20: 3 | K20: 6 | L20: 0.1 | M20: 1 | N20: =J20*K20*L20*M20 -> 1.8
C21: Skilled Worker ( Mason ) | D21: 2 | E21: =E20 -> 6 | F21: 490.72 | G21: =F21*E21*D21 -> 5888.64
C22: Laborer | D22: 2 | E22: =E21 -> 6 | F22: 442.5 | G22: =F22*E22*D22 -> 5310
F23: SUB TOTAL = | G23: =SUM(G19:G22) -> 18679.44 | H23: =G23/G32 -> 0.47446547
A24: Materials | H24: 1
D25: QUANTITY | E25: UNITS | F25: UNIT COST | G25: AMOUNT | H25: =#REF! -> #REF!
H26: =H15*H16*H24*H25 -> #REF!
C27: Premium Portland Cement ASTM C595 | D27: =ROUNDUP(D$15*9.5,0) -> 24 | E27: bags | F27: 310 | G27: =F27*D27 -> 7440
C28: W. Sand | D28: 10 | E28: cu.m. | F28: 600 | G28: =F28*D28 -> 6000
C29: Gravel 3/4", Crushed | D29: 5 | E29: cu.m. | F29: 1450 | G29: =F29*D29 -> 7250
F30: SUB TOTAL = | G30: =SUM(G27:G29) -> 20690
F32: DIRECT COST= | G32: =G30+G23 -> 39369.44
F33: UNIT COST = | G33: =G32/D15 -> 16108.609
A35: II | B35: REINFORCE STEEL BAR | C35: QUANTITY = | D35: =SUM(L37,L40,L44,)*0.616 -> 1456.84 | E35: kgs | H35: 0.4 | J35: VERT
H36: 0.4 | J36: l | K36: PCS | L36: LN.M.
A37: Labor | J37: 3 | K37: =110/0.4 -> 275 | L37: =J37*K37 -> 825
D38: NO. OF PERSONS | E38: NO. OF HOURS | F38: RATE PER HOUR | G38: AMOUNT
C39: Construction Foreman | D39: 1 | E39: 4 | F39: 718 | G39: =F39*E39*D39 -> 2872 | J39: HOR .BAR
C40: Skilled Worker ( Steel Man ) | D40: 1 | E40: =E39 -> 4 | F40: 490.72 | G40: =F40*E40*D40 -> 1962.88 | J40: 110 | K40: 10 | L40: =J40*K40 -> 1100
C41: Laborer | D41: 2 | E41: =E40 -> 4 | F41: 442.5 | G41: =F41*E41*D41 -> 3540
F42: SUB TOTAL = | G42: =SUM(G39:G41) -> 8374.88 | H42: =G42/G52 -> 0.45404904 | J42: PLANKS
A43: Materials | H43: 1 | J43: l | K43: PCS | L43: LN.M.
D44: QUANTITY | E44: UNITS | F44: UNIT COST | G44: AMOUNT | H44: =#REF! -> #REF! | J44: 4 | K44: 110 | L44: =J44*K44 -> 440
H45: =H35*H36*H43*H44 -> #REF!
C46: 10mm diam x 6m corr. Deform bar | D46: 20 | E46: length | F46: 210 | G46: =F46*D46 -> 4200
C47: 12mm diam x 6m corr. Deform bar | D47: 12 | E47: length | F47: 310 | G47: =F47*D47 -> 3720
C48: Tie Wire # 16 | D48: 10 | E48: pcs | F48: 110 | G48: =F48*D48 -> 1100
C49: Cutting Disc 4" ( Flexiarapid super A 60 U ) | D49: 5 | E49: pcs | F49: 210 | G49: =F49*D49 -> 1050
F50: SUB TOTAL = | G50: =SUM(G46:G49) -> 10070 | K50: =4*0.3+2 -> 3.2
F52: DIRECT COST= | G52: =G50+G42 -> 18444.88
F53: UNIT COST = | G53: =G52/D35 -> 12.660882
A55: III | B55: FORMWORKS | C55: QUANTITY = | D55: 1 | E55: lumpsum
A57: Labor
D58: NO. OF PERSONS | E58: NO. OF HOURS | F58: RATE PER HOUR | G58: AMOUNT
C59: Construction Foreman | D59: 1 | E59: 2 | F59: 718 | G59: =F59*E59*D59 -> 1436
C60: Skilled Worker ( Carpenter ) | D60: 1 | E60: =E59 -> 2 | F60: 490.72 | G60: =F60*E60*D60 -> 981.44
C61: Laborer | D61: 1 | E61: =E60 -> 2 | F61: 341 | G61: =F61*E61*D61 -> 682
F62: SUB TOTAL = | G62: =SUM(G59:G61) -> 3099.44 | H62: =G62/G76 -> 0.24101396 | J62: 1
A64: Materials
D65: QUANTITY | E65: UNITS | F65: UNIT COST | G65: AMOUNT
C67: Coco-lumber ( 2"x3"x12' ) | D67: =20*6 -> 120 | E67: bd.ft | F67: 38 | G67: =D67*F67 -> 4560 | J67: =D67*5 -> 600
C68: Coco-lumber ( 2"x2"x12' ) | D68: =20*4 -> 80 | E68: bd.ft | F68: 38 | G68: =D68*F68 -> 3040 | J68: =D68*5 -> 400
C69: Ordinary plywood 10MM 4'X8' | D69: 4 | E69: sht | F69: 714 | G69: =D69*F69 -> 2856 | J69: =D69*5 -> 20
C70: Nylon string ( 0.40mm ) | D70: 4 | E70: roll | F70: 68 | G70: =D70*F70 -> 272 | J70: =D70*5 -> 20
C71: CWN 4" | D71: 5 | E71: kgs | F71: 94 | G71: =D71*F71 -> 470 | J71: =D71*5 -> 25
C72: CWN 3" | D72: 5 | E72: kgs | F72: 94 | G72: =D72*F72 -> 470 | J72: =D72*5 -> 25
C73: Tie Wire # 16 | D73: 3.1182 | E73: kgs | F73: 110 | G73: =D73*F73 -> 343.002 | H73: =H352 -> -5719.762 | J73: =D73*5 -> 15.591
C74: CWN 1 1/2" | D74: 3 | E74: kgs | F74: 94 | G74: =D74*F74 -> 282 | J74: =D74*5 -> 15
C75: Hardware cloth 1/8" | D75: 3 | E75: m | F75: 189 | G75: =D75*F75 -> 567 | J75: =D75*5 -> 15
F76: SUB TOTAL = | G76: =SUM(G67:G75) -> 12860.002 | H76: =G76*5 -> 64300.01
F78: DIRECT COST= | G78: =G76+G62 -> 15959.442
F79: UNIT COST = | G79: =G78/D55 -> 15959.442
A81: IV | B81: MASONRY WORKS ( CHB Laying and Plastering ) | C81: QUANTITY = | D81: 24 | E81: sq.m.
A84: Labor
D85: NO. OF PERSONS | E85: NO. OF HOURS | F85: RATE PER HOUR | G85: AMOUNT
C86: Construction Foreman | D86: 1 | E86: 7 | F86: 615 | G86: =F86*E86*D86 -> 4305
C87: Skilled Worker ( Mason ) | D87: 2 | E87: =E86 -> 7 | F87: 390 | G87: =F87*E87*D87 -> 5460
C88: Laborer | D88: 3 | E88: =E87 -> 7 | F88: 341 | G88: =F88*E88*D88 -> 7161
F89: SUB TOTAL = | G89: =SUM(G86:G88) -> 16926 | H89: =G89/G97 -> 0.46245902
A90: Materials
D91: QUANTITY | E91: UNITS | F91: UNIT COST | G91: AMOUNT
C93: CHB 4"x8"x16" | D93: =D81*12.5 -> 300 | E93: pcs | F93: 13 | G93: =F93*D93 -> 3900 | J93: =D93*5 -> 1500
C94: 10mm diam x 6m corr. Deform bar | D94: 20 | E94: length | F94: 210 | G94: =F94*D94 -> 4200 | J94: =52+145 -> 197 | K94: 5 | L94: =K94*J94 -> 985
C95: Premium Portland Cement ASTM C595 | D95: 90 | E95: bags | F95: 310 | G95: =F95*D95 -> 27900
C96: W. Sand | D96: =ROUNDUP(D81*(0.08+0.02),0)-2 -> 1 | E96: cu.m. | F96: 600 | G96: =F96*D96 -> 600
F97: SUB TOTAL = | G97: =SUM(G93:G96) -> 36600 | J97: =40*5 -> 200
F99: DIRECT COST= | G99: =G97+G89 -> 53526 | K99: =14*5 -> 70
F100: UNIT COST = | G100: =G99/D81 -> 2230.25
A102: V | B102: ROOFING WORKS | C102: QUANTITY = | D102: =6*3 -> 18 | E102: sq.m.
A105: Labor
D106: NO. OF PERSONS | E106: NO. OF HOURS | F106: RATE PER HOUR | G106: AMOUNT
C107: Construction Foreman | D107: 1 | E107: 5 | F107: 615 | G107: =F107*E107*D107 -> 3075
C108: Skilled Worker ( Tinsmith ) | D108: 1 | E108: =E107 -> 5 | F108: 390 | G108: =F108*E108*D108 -> 1950
C109: Laborer | D109: 3 | E109: =E108 -> 5 | F109: 341 | G109: =F109*E109*D109 -> 5115
F110: SUB TOTAL = | G110: =SUM(G107:G109) -> 10140 | H110: =G110/G122 -> 0.41797197
A111: Materials
D112: QUANTITY | E112: UNITS | F112: UNIT COST | G112: AMOUNT
J113: =D113*5 -> 0
C114: Pre fabricated Long Span (0.40mm THK) | D114: =D102 -> 18 | E114: sq.m. | F114: 520 | G114: =F114*D114 -> 9360 | J114: =D114*5 -> 90
C115: Tek Screw #2 | D115: 200 | E115: pcs | F115: 3 | G115: =F115*D115 -> 600 | J115: =D115*5 -> 1000
C116: Cee-Purlins 1.2mmx2"x4"x6m | D116: 7 | E116: length | F116: 650 | G116: =F116*D116 -> 4550 | J116: =D116*5 -> 35
C117: Cee Purlins 1.2mmx2"x3"x6m | D117: 12 | E117: length | F117: 550 | G117: =F117*D117 -> 6600 | J117: =D117*5 -> 60
C118: Grinding Stone 4" | D118: 5 | E118: pcs | F118: 120 | G118: =F118*D118 -> 600 | J118: =D118*5 -> 25
C119: Drill bit 3/16 | D119: 5 | E119: pcs | F119: 110 | G119: =F119*D119 -> 550 | J119: =D119*5 -> 25
C120: Welding Rod 6013 | D120: 5 | E120: kgs | F120: 190 | G120: =F120*D120 -> 950 | J120: =D120*5 -> 25
C121: Cutting Disc 4" ( Flexiarapid super A 60 U ) | D121: 5 | E121: pcs | F121: 210 | G121: =F121*D121 -> 1050 | J121: =D121*5 -> 25
...

Sheet MPDP
A1: Republic of the Philippines
A2: Province of South Cotabato
A3: City of Koronadal | O3: =(24*4+2.4*5) -> 108
A4: CITY MAYORS OFFICE - BARANGAY DEVELOPMENT PROGRAM | H4: direc cost | I4: =G24+G61+G102+G160 -> 180296.24 | L4: =E19+E43+E90++E151 -> 13 | M4: hours | N4: =(5*6+2.4*9) -> 51.6
H5: materials | I5: =G163 -> 218915.68 | L5: =L4 -> 13 | M5: wd
A6: Project Title: | B6: CONSTRUCTION OF SEPTIC TANK | H6: labor | I6: =G164 -> 161084.32 | J6: =I6/I4 -> 0.89344248 | N6: =I5*0.45 -> 98512.056
A7: Location: | B7: CITY OF KORONADAL, PUBLIC MARKET | I7: =I5+I6 -> 380000
A8: Project Cost: | B8: =G165 -> 380000 | P8: =500000-I6 -> 338915.68
A9: Duration: | B9: =E21+E32+E43+E69+E90+E109+E152+E134 -> 38 | C9: Working Days | P9: =500000-I7 -> 120000
A11: PROGRAM OF WORKS
A13: ITEM | B13: SCOPE OF WORKS
A15: I | B15: SITE SURVEY, LAYOUT AND | C15: QUANTITY = | D15: 1 | E15: ls
B16: INSTALLATION OF BARRACADE
A17: Labor
D18: NO. OF PERSONS | E18: NO. OF DAYS | F18: RATE PER DAY | G18: AMOUNT | J18: l | K18: w | L18: h | M18: volume | N18: 20% shrinkage | O18: total volume
C19: Construction Foreman | D19: 1 | E19: 2 | F19: 718 | G19: =F19*E19*D19 -> 1436 | J19: 30 | K19: 15 | L19: 0.2 | M19: =J19*K19*L19 -> 90 | N19: =M19*0.2 -> 18 | O19: =N19+M19 -> 108
C20: Skilled Worker | D20: 1 | E20: 2 | F20: 490.72 | G20: =F20*E20*D20 -> 981.44
C21: Laborer | D21: 4 | E21: 2 | F21: 442.5 | G21: =F21*E21*D21 -> 3540
F22: SUB TOTAL = | G22: =SUM(G19:G21) -> 5957.44 | H22: =#REF!*#REF! -> #REF! | I22: =G22/#REF! -> #REF!
F24: DIRECT COST= | G24: =G22 -> 5957.44
F25: UNIT COST = | G25: =G24/D15 -> 5957.44
A27: II | B27: DEMOLITION AND EXCAVATION | C27: QUANTITY = | D27: 70 | E27: cu.m.
A29: Labor
D30: NO. OF PERSONS | E30: NO. OF DAYS | F30: RATE PER DAY | G30: AMOUNT
C31: Construction Foreman | D31: 1 | E31: 10 | F31: 718 | G31: =F31*E31*D31 -> 7180
C32: Skilled Worker | D32: 2 | E32: 10 | F32: 490.72 | G32: =F32*E32*D32 -> 9814.4
C33: Laborer | D33: 6 | E33: 10 | F33: 442.5 | G33: =F33*E33*D33 -> 26550
F34: SUB TOTAL = | G34: =SUM(G31:G33) -> 43544.4
F36: DIRECT COST= | G36: =G34 -> 43544.4
F37: UNIT COST = | G37: =G36/D27 -> 622.06286
A39: III | B39: FORMWORKS | C39: QUANTITY = | D39: 1 | E39: ls
A41: Labor
D42: NO. OF PERSONS | E42: NO. OF DAYS | F42: RATE PER DAY | G42: AMOUNT
C43: Construction Foreman | D43: 1 | E43: 4 | F43: 718 | G43: =F43*E43*D43 -> 2872
C44: Skilled Worker | D44: 2 | E44: 4 | F44: 528.8 | G44: =F44*E44*D44 -> 4230.4
C45: Laborer | D45: 6 | E45: 4 | F45: 442.5 | G45: =F45*E45*D45 -> 10620
F46: SUB TOTAL = | G46: =SUM(G43:G45) -> 17722.4 | H46: =H59*G59 -> 25408.35
A47: Materials
D48: QUANTITY | E48: UNITS | F48: UNIT COST | G48: AMOUNT
C50: Marine Plywood 10mmx4'x8' | D50: 55 | E50: sheets | F50: 920 | G50: =F50*D50 -> 50600
C51: Coco Lumber 2"x2"x12' | D51: 45 | E51: bd.ft. | F51: 32 | G51: =F51*D51 -> 1440
C52: Coco Lumber 2"x3"x12' | D52: 45 | E52: bd.ft. | F52: 32 | G52: =F52*D52 -> 1440
C53: CWN #3 | D53: 7 | E53: kgs | F53: 104 | G53: =F53*D53 -> 728
C54: CWN #4 | D54: 7 | E54: kgs | F54: 104 | G54: =F54*D54 -> 728
C55: CWN #1.5 | D55: 3 | E55: kgs | F55: 104 | G55: =F55*D55 -> 312
C56: Cutting Disc 4" (Flexiarapid super A 60U) | D56: 6 | E56: pcs | F56: 120 | G56: =F56*D56 -> 720
C57: Nylon String 0.40mmx37m | D57: 3 | E57: rolls | F57: 40 | G57: =F57*D57 -> 120
C58: Level Hose (Yellow) | D58: 15 | E58: ln.m. | F58: 25 | G58: =F58*D58 -> 375
F59: SUB TOTAL = | G59: =SUM(G50:G58) -> 56463 | H59: 0.45
F61: DIRECT COST= | G61: =G59+G46 -> 74185.4
F62: UNIT COST = | G62: =G61/D39 -> 74185.4 | K62: l | L62: w | M62: AREA
A64: IV | B64: STEEL REINFORCEMENT | C64: QUANTITY = | D64: 1 | E64: ls
A66: Labor
D67: NO. OF PERSONS | E67: NO. OF DAYS | F67: RATE PER DAY | G67: AMOUNT
C68: Construction Foreman | D68: 1 | E68: 9 | F68: 718 | G68: =F68*E68*D68 -> 6462
C69: Skilled Worker | D69: 2 | E69: 9 | F69: 528.8 | G69: =F69*E69*D69 -> 9518.4
C70: Laborer | D70: 6 | E70: 9 | F70: 442.5 | G70: =F70*E70*D70 -> 23895
F71: SUB TOTAL = | G71: =SUM(G68:G70) -> 39875.4
A72: Materials
D73: QUANTITY | E73: UNITS | F73: UNIT COST | G73: AMOUNT
C75: Def. Bar 10mm x 6m, Grade 40 | D75: 90 | E75: lnts | F75: 250 | G75: =F75*D75 -> 22500
C76: Def. Bar 12mm x 6m, Grade 40 | D76: 90 | E76: lnts | F76: 325 | G76: =F76*D76 -> 29250
C77: Tie Wire #16 | D77: 25 | E77: kg | F77: 120 | G77: =F77*D77 -> 3000
C78: 1.2mmx2"x3" G.I. Cee Purlins | D78: 5 | E78: lengths | F78: 390 | G78: =F78*D78 -> 1950
C79: Hardware Cloth, 1/8" | D79: 1 | E79: ln.m. | F79: 174.94 | G79: =F79*D79 -> 174.94
F80: SUB TOTAL = | G80: =SUM(G75:G79) -> 56874.94
F82: DIRECT COST= | G82: =G80+G71 -> 96750.34
F83: UNIT COST = | G83: =G82/D64 -> 96750.34
A86: V | B86: CONCRETE/ MASONRY WORKS | C86: QUANTITY = | D86: 12 | E86: cu.m.
A88: Labor | J88: CHB LAYING
D89: NO. OF PERSONS | E89: NO. OF DAYS | F89: RATE PER DAY | G89: AMOUNT | J89: L | K89: H | L89: AREA
C90: Construction Foreman | D90: 1 | E90: 6 | F90: 718 | G90: =F90*E90*D90 -> 4308 | J90: 90 | K90: 0.6 | L90: =K90*J90 -> 54 | M90: =(L90*13)*1.1 -> 772.2
C91: Skilled Worker | D91: 2 | E91: 6 | F91: 528.8 | G91: =F91*E91*D91 -> 6345.6
C92: Laborer | D92: 6 | E92: 6 | F92: 442.5 | G92: =F92*E92*D92 -> 15930
F93: SUB TOTAL = | G93: =SUM(G90:G92) -> 26583.6 | H93: =G100*H100 -> 31770 | I93: =G93/G100 -> 0.37653824
A94: Materials
D95: QUANTITY | E95: UNITS | F95: UNIT COST | G95: AMOUNT
C96: Premium Portland Cement ASTM C595 | D96: 115 | E96: bags | F96: 310 | G96: =F96*D96 -> 35650
C97: Cement Sahara | D97: 115 | E97: bags | F97: 90 | G97: =F97*D97 -> 10350 | I97: =5*9 -> 45
C98: W. Sand | D98: 6 | E98: cu.m. | F98: 600 | G98: =F98*D98 -> 3600
C99: Gravel, 3/4" | D99: 12 | E99: cu.m. | F99: 1750 | G99: =F99*D99 -> 21000
F100: SUB TOTAL = | G100: =SUM(G96:G99) -> 70600 | H100: 0.45
F102: DIRECT COST= | G102: =G100+G93 -> 97183.6
F103: UNIT COST = | G103: =G102/D86 -> 8098.6333
A104: VI | B104: PLUMBING WORKS | C104: QUANTITY = | D104: 1 | E104: ls
A106: Labor
C107: Construction Foreman | D107: NO. OF PERSONS | E107: NO. OF DAYS | F107: RATE PER DAY | G107: AMOUNT
C108: Skilled Worker ( Mason ) | D108: 1 | E108: 4 | F108: 718 | G108: =F108*E108*D108 -> 2872
C109: Laborer | D109: 2 | E109: 4 | F109: 528.8 | G109: =F109*E109*D109 -> 4230.4
D110: 6 | E110: 4 | F110: 442.5 | G110: =F110*E110*D110 -> 10620
F111: SUB TOTAL = | G111: =SUM(G108:G110) -> 17722.4
A112: Materials
D113: QUANTITY | E113: UNITS | F113: UNIT COST | G113: AMOUNT
C114: PVC SANITARY PIPE #6 S1000 | D114: 5 | E114: lngt | F114: 1500 | G114: =F114*D114 -> 7500
C115: PVC SANITARY PIPE #4 S1000 | D115: 5 | E115: lngt | F115: 765 | G115: =F115*D115 -> 3825
C116: PVC SANITARY CLEAN OUT #6 S1000 | D116: 6 | E116: pcs | F116: 700 | G116: =F116*D116 -> 4200
C117: PVC SANITARY CLEAN OUT #4 S1000 | D117: 12 | E117: pcs | F117: 620 | G117: =F117*D117 -> 7440
C118: PVC SANITARY PIPE #6 S1000 LONG ELBOW | D118: 2 | E118: pcs | F118: 1200 | G118: =F118*D118 -> 2400
C119: PVC SANITARY WYEE 6"X6" S1000 | D119: 3 | E119: pcs | F119: 250 | G119: =F119*D119 -> 750
C120: PVC SANITARY WYEE 6"X4" S1000 | D120: 3 | E120: pcs | F120: 240 | G120: =F120*D120 -> 720
...

Sheet POW COVER
B1: Republic of the Philippines
B2: Province of South Cotabato
B3: City of Koronadal
B4: OFFICE OF THE CITY ENGINEER
B7: PROGRAM OF WORK/BUDGET COST FOR KORONADAL CITY INFRASTRUCTURE PROJECTS
B9: PROJECT: | E9: Construction of Covered Pathway at City hall Entrance/Exit ( 29 SPAN, 3m length/span) | Q9: Date: | X9: Construction of Covered Pathway at City hall Entrance/Exit
E10: ( 29 SPAN, 3m length/span) | Q10: Net Length:
B11: Location: | E11: CITY HALL SITE, CITY OF KORONADAL | Q11: Classification:
Q12: Starting Date: | S12: Upon Approval
B13: Estimated Project Cost: | E13: =S55 -> 1100000 | Q13: Total Project Duration: | T13: ='PROJECT DETAILS'!B4 -> 200 | U13: C.D.
B14: Source of Fund: | E14: ='PROJECT DETAILS'!B6:I6 -> 0 | Q14: No. of Working Days:
Q15: No. of Pre-determined:
B16: Project limits: | Q16: Unworkable Days:
A18: ITEM | B18: ITEM NO. | D18: DESCRIPTION OF WORK | N18: % OF | O18: EQUIPMENT | V18: COST
N19: TOTAL | O19: DESCRIPTION | R19: REQUIRED
A20: 1 | B20: 803 | D20: Structural excavation | N20: =T37/Y37 -> #REF! | S20: ='PROJECT DETAILS'!E232 -> 1 | V20: ='PROJECT DETAILS'!I232 -> 1
A21: 2 | B21: SPL - 3 | D21: Formworks | N21: =T38/Y38 -> #REF! | O21: Concrete Mixer One Bagger | S21: ='PROJECT DETAILS'!E233 -> 1 | V21: ='PROJECT DETAILS'!I233 -> 1
A22: 3 | B22: 900(7) | D22: Reinforce Concrete | N22: =T39/Y39 -> #REF! | O22: Conrete Vibrator | S22: ='PROJECT DETAILS'!E234 -> 1 | V22: ='PROJECT DETAILS'!I234 -> 1
B23: 1047 | D23: Steel Works ( support ) ( 6.5m ) | N23: =T40/Y40 -> #DIV/0!
A24: 4 | B24: 1047(1) | D24: Steel Works ( GIRT 1 ) ( 13.41m ) | N24: =T41/Y41 -> #DIV/0! | O24: Electric drill | S24: 1 | V24: ='PROJECT DETAILS'!I235 -> 1
B25: 1047(2) | D25: Steel Works ( GIRT 2 ) ( 12.13m ) | N25: =T42/Y42 -> #DIV/0!
B26: 1047(3) | D26: Steel Works ( TRUSS 1 ) ( 9.74m ) | N26: =T43/Y43 -> #REF!
A27: 5 | B27: 903(1) | D27: Roofing Works | N27: =T44/Y44 -> #REF! | O27: Electric Bar Cutter and Bar bender | S27: ='PROJECT DETAILS'!E235 -> 1 | V27: ='PROJECT DETAILS'!I236 -> 2
A28: 6 | B28: 1027 | D28: Painting Works | N28: =T45/Y45 -> #REF! | O28: Welding Machine | S28: ='PROJECT DETAILS'!E236 -> 2 | V28: ='PROJECT DETAILS'!I237 -> 1
A29: 13 | B29: SPL - 2 | D29: Billboards | N29: =T46/Y46 -> #REF! | V29: ='PROJECT DETAILS'!I244 -> 0
B30: SPL - 8 | D30: Mobilization / Demobilization | N30: =#REF!/#REF! -> #REF!
A31: 15 | B31: SPL -4 | D31: Construction of Safety and Health Program | N31: =T48/Y48 -> #DIV/0! | V31: ='PROJECT DETAILS'!I246 -> 0
B33: ESTIMATED COST OF PROPOSED WORK
B34: ITEM NO. | D34: DESCRIPTION | H34: LABOR | I34: MATERIALS | J34: OCM | K34: PROFIT | L34: VAT | M34: QUANTITY | O34: UNIT | Q34: TOTAL DIRECT COST | R34: UNIT COST | T34: ADJUSTED
T35: COST
A37: 1 | B37: =B20 -> 803 | D37: =D20 -> Structural excavation | H37: ='ITEM 1'!X16 -> 3584 | I37: ='ITEM 1'!X26 -> 0 | J37: ='ITEM 1'!AD28 -> 537.6 | K37: ='ITEM 1'!AD29 -> 358.4 | L37: ='ITEM 1'!AD30 -> 224 | M37: 29.41 | O37: ='SUMMARIZE QUANTITY'!C3 -> cu.m. | Q37: ='ITEM 1'!AD27 -> 3584 | R37: ='ITEM 1'!AD32 -> 159.9456 | T37: =R37*M37 -> 4704 | Y37: =S49 -> #REF!
A38: 2 | B38: =B21 -> SPL - 3 | D38: =D21 -> Formworks | H38: ='ITEM 2'!X16 -> 0 | I38: ='ITEM 2'!X34 -> 0 | J38: ='ITEM 2'!AD36 -> 0 | K38: ='ITEM 2'!AD37 -> 0 | L38: ='ITEM 2'!AD38 -> 0 | M38: 300 | O38: bd.ft. | Q38: ='ITEM 2'!AD35 -> 0 | R38: ='ITEM 2'!AD40 -> 0 | T38: =R38*M38 -> 0 | Y38: =S49 -> #REF!
A39: 3 | B39: =B22 -> 900(7) | D39: =D22 -> Reinforce Concrete | H39: ='ITEM 3'!X16 -> 0 | I39: ='ITEM 3'!X38 -> 0 | J39: ='ITEM 3'!AD40 -> 0 | K39: ='ITEM 3'!AD41 -> 0 | L39: ='ITEM 3'!AD42 -> 0 | M39: 8.721 | O39: ='SUMMARIZE QUANTITY'!C6 -> cu.m. | Q39: ='ITEM 3'!AD39 -> 0 | R39: ='ITEM 3'!AD44 -> 0 | T39: =R39*M39 -> 0 | Y39: =S49 -> #REF!
A40: 4 | B40: =B23 -> 1047 | D40: =D23 -> Steel Works ( support ) ( 6.5m ) | M40: 18 | O40: sets | T40: =R40*M40 -> 0
A41: 5 | B41: =B24 -> 1047(1) | D41: =D24 -> Steel Works ( GIRT 1 ) ( 13.41m ) | M41: 17 | O41: sets | T41: =R41*M41 -> 0
A42: 6 | B42: =B25 -> 1047(2) | D42: =D25 -> Steel Works ( GIRT 2 ) ( 12.13m ) | M42: 17 | O42: sets | T42: =R42*M42 -> 0
A43: 7 | B43: =B26 -> 1047(3) | D43: =D26 -> Steel Works ( TRUSS 1 ) ( 9.74m ) | H43: ='ITEM 4'!X16 -> 0 | I43: ='ITEM 4'!X36 -> 0 | J43: ='ITEM 4'!AD38 -> 0 | K43: ='ITEM 4'!AD39 -> 0 | L43: ='ITEM 4'!AD40 -> 0 | M43: 18 | O43: sets | Q43: ='ITEM 4'!AD37:AD37 -> 0 | R43: ='ITEM 4'!AD42 -> 0 | T43: =R43*M43 -> 0 | Y43: =S49 -> #REF!
A44: 8 | B44: =B27 -> 903(1) | D44: =D27 -> Roofing Works | H44: ='ITEM 5'!X16 -> 0 | I44: ='ITEM 5'!X36 -> 0 | J44: ='ITEM 5'!AD38 -> 0 | K44: ='ITEM 5'!AD39 -> 0 | L44: ='ITEM 5'!AD40 -> 0 | M44: 165.24 | O44: sq.m. | Q44: ='ITEM 5'!AD37 -> 0 | R44: ='ITEM 5'!AD42 -> 0 | T44: =R44*M44 -> 0 | Y44: =S49 -> #REF! | AA44: 1447461.6
A45: 9 | B45: =B28 -> 1027 | D45: =D28 -> Painting Works | H45: ='ITEM 6'!X16 -> 0 | I45: ='ITEM 6'!X34 -> 0 | J45: ='ITEM 6'!AD36 -> 0 | K45: ='ITEM 6'!AD37 -> 0 | L45: ='ITEM 6'!AD38 -> 0 | M45: 1 | O45: lumpsum | Q45: ='ITEM 6'!AD35 -> 0 | R45: ='ITEM 6'!AD40 -> 0 | T45: =R45*M45 -> 0 | Y45: =S49 -> #REF!
A46: 10 | B46: =B29 -> SPL - 2 | D46: =D29 -> Billboards | H46: =#REF! -> #REF! | I46: =#REF! -> #REF! | J46: =#REF! -> #REF! | K46: =#REF! -> #REF! | L46: =#REF! -> #REF! | M46: ='SUMMARIZE QUANTITY'!B37 -> 1 | O46: lumpsum | Q46: =#REF! -> #REF! | R46: =#REF! -> #REF! | T46: =R46*M46 -> #REF! | Y46: =S49 -> #REF!
A47: 11 | B47: =B31 -> SPL -4 | D47: =D31 -> Construction of Safety and Health Program | H47: =#REF! -> #REF! | I47: =#REF! -> #REF! | J47: =#REF! -> #REF! | K47: =#REF! -> #REF! | L47: =#REF! -> #REF! | M47: ='SUMMARIZE QUANTITY'!B40 -> 1 | O47: ='SUMMARIZE QUANTITY'!C40 -> lot | Q47: =#REF! -> #REF! | R47: =#REF! -> #REF! | T47: =R47*M47 -> #REF!
B48: BREAKDOWN OF EXPENDITURE:
B49: 1. | C49: Labor | F49: =SUM(H37:H47) -> #REF! | O49: A. | P49: Sub-Total | S49: =SUM(T37:U46) -> #REF!
B50: 2. | C50: Materials | F50: =SUM(I37:I47) -> #REF! | O50: B. | P50: Construction Contingencies
B51: 3. | C51: Rental of Equipment | F51: =SUM(V20:V31) -> 7 | O51: C. | P51: Total Construction Cost
B52: 4 | C52: Rental of Field Office | O52: D. | P52: Engineering and Admin. | S52: =S55-S49 -> #REF!
B53: 5 | C53: Direct Cost | F53: =F51+F50+F49 -> #REF! | P53: Overhead (%)
B54: 6 | C54: OCM, Profit, QC, MCB | F54: =SUM(J37:J47,K37:K46) -> #REF! | O54: E. | P54: Payment of Affected Improvements
B55: 7. | C55: VAT | F55: =SUM(L37:L46) -> #REF! | O55: F. | P55: TOTAL ESTIMATED COST | S55: =1100000 -> 1100000
B56: 8. | C56: Sub-Total | F56: =SUM(F53:M55) -> #REF!
B57: 9. | C57: Const. Contingencies
B58: 10. | C58: Engineering Overhead | F58: =F56*0.024647906 -> #REF!
B59: 11. | C59: Payment of Affected
C60: Improvements
B61: 12. | C61: TOTAL | G61: =F56+F58 -> #REF!
B67: Prepared by: | N67: Reviewed by:
C69: ENGR. JOHN JOVI Z. ANGOR | O69: ENGR. ZALDY A. GAYOSA
D70: ENGINEER 1 | O70: CMO-SEF PROGRAM HOLDER
B72: Noted By: | N72: Approved by:
D74: ENGR. RUEL C. TIANCHON | O74: PETER B. MIGUEL, M.D.,FPSO-HNS
D75: City Engineer | O75: City Mayor
Q97: =SUM(Q76:Q96) -> 0 | T97: =SUM(T76:U96) -> 0
Y154: =#REF! -> #REF! | Z154: =#REF! -> #REF!
Y155: =#REF! -> #REF! | Z155: =#REF! -> #REF!
Y156: =#REF! -> #REF! | Z156: =#REF! -> #REF!
Y157: =#REF! -> #REF! | Z157: =#REF! -> #REF!
Y158: =#REF! -> #REF! | Z158: =#REF! -> #REF!
AC165: =F56*0.024647906 -> #REF!
AC169: =G61-S49 -> #REF!
Z170: =3000000-S55 -> 1900000
Y172: =S55-G61 -> #REF!
Z173: 0.024647906
Z175: 3200000
Y176: =S49-F56 -> #REF! | Z176: =Z175-S55 -> 2100000
G1886: =[4]COVER!A104 -> 0

Sheet ITEM 1
A1: DETAILED UNIT PRICE ANALYSIS
A3: PROJECT | E3: : | F3: ='POW COVER'!E9 -> Construction of Covered Pathway at City hall Entrance/Exit ( 29 SPAN, 3m length/span)
A4: Item No. | E4: : | F4: ='POW COVER'!B37 -> 803
A5: Description | E5: : | F5: ='POW COVER'!D37 -> Structural excavation
A6: Quantity | E6: : | F6: ='POW COVER'!M37 -> 29.41 | G6: ='POW COVER'!O37 -> cu.m. | I6: sets
A7: Output Per Hour: | F7: =F6/AF9 -> 1.838125 | G7: =""&G6&" per hour" -> cu.m. per hour | AF7: 10
AF8: hours
B9: Designation | N9: No. of Person | Q9: No. of Hours | T9: Houry Rate | X9: AMOUNT | AF9: =MAX(Q12:S15,Q20:S20) -> 16
A10: A. | B10: Labor
B12: a. Construction Foreman | N12: 1 | Q12: 16 | T12: 60 | X12: =T12*Q12*N12 -> 960
B13: b. Skilled Labor | N13: 2 | Q13: 16 | T13: 43.75 | X13: =T13*Q13*N13 -> 1400
B14: c. Unskilled Labor | N14: 2 | Q14: 16 | T14: 38.25 | X14: =T14*Q14*N14 -> 1224
A16: Sub Total for A | X16: =SUM(X12:AC15) -> 3584
B17: Name & Capacity | N17: No. of units | Q17: No. of Hours | T17: Houry Rate | X17: AMOUNT
A18: B. | B18: Equipment
A21: Sub Total for B | X21: =SUM(X20:AC20) -> 0
B22: Name & Specifications | N22: Units | Q22: Quantity | T22: Unit cost | X22: AMOUNT
A23: C. | B23: Materials
A26: Sub-Total for C | X26: =SUM(X25:AC25) -> 0
A27: D. | B27: Total Direct Cost | U27: A+B+C | X27: =X26+X21+X16 -> 3584 | AD27: =X27 -> 3584
A28: E. | B28: Overhead,Contingencies and Miscellaneous | O28: (OCM) | U28: 15% of D | X28: =0.15*X27 -> 537.6 | AD28: =X28 -> 537.6
A29: F. | B29: Contractor's Profit (CP) | U29: 10%of D | X29: =0.1*X27 -> 358.4 | AD29: =X29 -> 358.4
A30: G. | B30: Value Added Tax (VAT) | T30: 5%*(D+E+F) | X30: =0.05*(X29+X28+X27) -> 224 | AD30: =X30 -> 224
A31: H. | B31: Total Cost | T31: (D+E+F+G) | X31: =X30+X29+X28+X27 -> 4704 | AD31: =X31 -> 4704
A32: I. | B32: Total Unit Cost | U32: H/Qty. | X32: =X31/F6 -> 159.9456 | AD32: =X32 -> 159.9456

Sheet ITEM 2
A1: DETAILED UNIT PRICE ANALYSIS
A3: PROJECT | E3: : | F3: ='POW COVER'!E9 -> Construction of Covered Pathway at City hall Entrance/Exit ( 29 SPAN, 3m length/span)
A4: Item No. | E4: : | F4: ='POW COVER'!B38 -> SPL - 3
A5: Description | E5: : | F5: ='POW COVER'!D38 -> Formworks
A6: Quantity | E6: : | F6: ='POW COVER'!M38 -> 300 | G6: sq.m. | I6: sets
A7: Output Per Hour: | F7: 4 | G7: =""&G6&" per hour" -> sq.m. per hour
AF8: hours
B9: Designation | N9: No. of Person | Q9: No. of Hours | T9: Houry Rate | X9: AMOUNT | AF9: =MAX(Q12:S15,Q20:S20) -> 0
A10: A. | B10: Labor
B12: a. Construction Foreman | X12: =T12*Q12*N12 -> 0
B13: b. Skilled Labor ( Welder ) | X13: =T13*Q13*O13 -> 0
B14: c. Unskilled Labor | X14: =T14*Q14*O14 -> 0
X15: =T15*Q15*O15 -> 0
A16: Sub Total for A | X16: =SUM(X12:AC15) -> 0
B17: Name & Capacity | N17: No. of units | Q17: No. of Hours | T17: Houry Rate | X17: AMOUNT
A18: B. | B18: Equipment
A21: Sub Total for B | X21: =SUM(X20:AC20) -> 0
B22: Name & Specifications | N22: Units | Q22: Quantity | T22: Unit cost | X22: AMOUNT
A23: C. | B23: Materials
B25: 100 coco-lumber ( 2x3x12 ) | N25: bd.ft | Q25: 600 | X25: =T25*Q25 -> 0
B26: 100 coco lumber (2x2x12) | N26: bd.ft | Q26: 400 | X26: =T26*Q26 -> 0
B27: Marine plywood | N27: sht | Q27: 10 | X27: =T27*Q27 -> 0
B28: Leveling Hose | N28: m | Q28: 20 | X28: =T28*Q28 -> 0
B29: Nylon string | N29: roll | Q29: 15 | X29: =T29*Q29 -> 0
B30: CWN 4" | N30: kgs. | Q30: 15 | X30: =T30*Q30 -> 0
B31: CWN 2 1/2" | N31: kgs. | Q31: 15 | X31: =T31*Q31 -> 0
B32: CWN 1 1/2" | N32: kgs. | Q32: 5 | X32: =T32*Q32 -> 0
A34: Sub-Total for C | X34: =SUM(X25:AC33) -> 0
A35: D. | B35: Total Direct Cost | U35: A+B+C | X35: =X34+X21+X16 -> 0 | AD35: =X35 -> 0
A36: E. | B36: Overhead,Contingencies and Miscellaneous | O36: (OCM) | U36: 15% of D | X36: =0.15*X35 -> 0 | AD36: =X36 -> 0
A37: F. | B37: Contractor's Profit (CP) | U37: 10%of D | X37: =0.1*X35 -> 0 | AD37: =X37 -> 0
A38: G. | B38: Value Added Tax (VAT) | T38: 5%*(D+E+F) | X38: =0.05*(X37+X36+X35) -> 0 | AD38: =X38 -> 0
A39: H. | B39: Total Cost | T39: (D+E+F+G) | X39: =X38+X37+X36+X35 -> 0 | AD39: =X39 -> 0
A40: I. | B40: Total Unit Cost | U40: H/Qty. | X40: =X39/F6 -> 0 | AD40: =X40 -> 0

Sheet ITEM 3
A1: DETAILED UNIT PRICE ANALYSIS
A3: PROJECT | E3: : | F3: ='POW COVER'!E9 -> Construction of Covered Pathway at City hall Entrance/Exit ( 29 SPAN, 3m length/span)
A4: Item No. | E4: : | F4: ='POW COVER'!B39 -> 900(7)
A5: Description | E5: : | F5: ='POW COVER'!D39 -> Reinforce Concrete
A6: Quantity | E6: : | F6: ='POW COVER'!M39 -> 8.721 | G6: ='POW COVER'!O39 -> cu.m. | I6: sets
A7: Output Per Hour: | F7: 2 | G7: =""&G6&" per hour" -> cu.m. per hour
AF8: hours
B9: Designation | N9: No. of Person | Q9: No. of Hours | T9: Houry Rate | X9: AMOUNT | AF9: =MAX(Q12:S15,Q20:S23) -> 0
A10: A. | B10: Labor
B12: a. Construction Foreman | X12: =T12*Q12*N12 -> 0
B13: b. Skilled Labor ( Welder ) | X13: =T13*Q13*O13 -> 0
B14: c. Unskilled Labor | X14: =T14*Q14*O14 -> 0
A16: Sub Total for A | X16: =SUM(X12:AC15) -> 0
B17: Name & Capacity | N17: No. of units | Q17: No. of Hours | T17: Houry Rate | X17: AMOUNT
A18: B. | B18: Equipment
B20: Concrete Vibrator | X20: =T20*Q20*N20 -> 0
B21: Concrete Mixer one bagger | X21: =T21*Q21*N21 -> 0
B22: Electric Bar Cutter and Bar bender | X22: =T22*Q22*N22 -> 0
A24: Sub Total for B | X24: =SUM(X20:AC23) -> 0
B25: Name & Specifications | N25: Units | Q25: Quantity | T25: Unit cost | X25: AMOUNT
A26: C. | B26: Materials
B28: Cement | N28: bag | Q28: 84 | X28: =T28*Q28 -> 0
B29: 12mm RSB | N29: length | Q29: 75 | X29: =T29*Q29 -> 0
B30: 10mm RSB | N30: length | Q30: 72 | X30: =T30*Q30 -> 0
B31: Sand | N31: cu.m. | Q31: =8.72*0.5 -> 4.36 | X31: =T31*Q31 -> 0
B32: Empty container | N32: pc | Q32: 10 | X32: =T32*Q32 -> 0
B33: tie wire GA. 16 | N33: kgs | Q33: 10 | X33: =T33*Q33 -> 0
B34: Gravel 3/4 | N34: cu.m. | Q34: 8.72 | X34: =T34*Q34 -> 0
B35: Anchor bolt w/ nut & washer ( 12mm ) | N35: pcs | Q35: 11 | X35: =T35*Q35 -> 0
B36: Steel Plate ( 6mm ) | N36: sq.m. | Q36: 1.35 | X36: =T36*Q36 -> 0
A38: Sub-Total for C | X38: =SUM(X28:AC37) -> 0
A39: D. | B39: Total Direct Cost | U39: A+B+C | X39: =X38+X24+X16 -> 0 | AD39: =X39 -> 0
A40: E. | B40: Overhead,Contingencies and Miscellaneous | O40: (OCM) | U40: 15% of D | X40: =0.15*X39 -> 0 | AD40: =X40 -> 0
A41: F. | B41: Contractor's Profit (CP) | U41: 10%of D | X41: =0.1*X39 -> 0 | AD41: =X41 -> 0
A42: G. | B42: Value Added Tax (VAT) | T42: 5%*(D+E+F) | X42: =0.05*(X41+X40+X39) -> 0 | AD42: =X42 -> 0
A43: H. | B43: Total Cost | T43: (D+E+F+G) | X43: =X42+X41+X40+X39 -> 0 | AD43: =X43 -> 0
A44: I. | B44: Total Unit Cost | U44: H/Qty. | X44: =X43/F6 -> 0 | AD44: =X44 -> 0

Sheet ITEM 4
A1: DETAILED UNIT PRICE ANALYSIS
A3: PROJECT | E3: : | F3: ='POW COVER'!E9 -> Construction of Covered Pathway at City hall Entrance/Exit ( 29 SPAN, 3m length/span)
A4: Item No. | E4: : | F4: ='POW COVER'!B40 -> 1047
A5: Description | E5: : | F5: ='POW COVER'!D40 -> Steel Works ( support ) ( 6.5m )
A6: Quantity | E6: : | F6: ='POW COVER'!M40 -> 18 | G6: ='POW COVER'!O40 -> sets | I6: sets
A7: Output Per Hour: | F7: 0.1 | G7: =""&G6&" per hour" -> sets per hour
AF8: hours
B9: Designation | N9: No. of Person | Q9: No. of Hours | T9: Houry Rate | X9: AMOUNT | AF9: =MAX(Q12:S15,Q20:S22) -> 0
A10: A. | B10: Labor
B12: a. Construction Foreman | X12: =T12*Q12*N12 -> 0
B13: b. Skilled Labor ( Welder ) | X13: =T13*Q13*O13 -> 0
B14: c. Unskilled Labor | X14: =T14*Q14*O14 -> 0
X15: =T15*Q15*O15 -> 0
A16: Sub Total for A | X16: =SUM(X12:AC15) -> 0
B17: Name & Capacity | N17: No. of units | Q17: No. of Hours | T17: Houry Rate | X17: AMOUNT
A18: B. | B18: Equipment
B20: Welding Machine | X20: =T20*Q20*N20 -> 0
B21: Electric Sander | X21: =T21*Q21*N21 -> 0
A23: Sub Total for B | X23: =SUM(X20:AC22) -> 0
B24: Name & Specifications | N24: Units | Q24: Quantity | T24: Unit cost | X24: AMOUNT
A25: C. | B25: Materials
B27: G.I. Pipe 2 diam. Schd. 20 | N27: length | X27: =T27*Q27 -> 0
B28: G.I. Pipe 1 1/2 diam. Schd. 20 | N28: length | X28: =T28*Q28 -> 0
B29: G.I. Pipe 1 diam. Schd. 20 | N29: length | X29: =T29*Q29 -> 0
B30: Angle Bar ( 1/4 x 1 1/2 ) | N30: length | X30: =T30*Q30 -> 0
B31: Angle Bar ( 1/4 x 1 1/4 ) | N31: length | X31: =T31*Q31 -> 0
B32: Angle Bar ( 1/4 x 1 ) | N32: length | X32: =T32*Q32 -> 0
B33: Welding Rod | N33: kgs | X33: =T33*Q33 -> 0
B34: Cut Off Wheel Blade # 14" | N34: pcs | X34: =T34*Q34 -> 0
A36: Sub-Total for C | X36: =SUM(X27:AC35) -> 0
A37: D. | B37: Total Direct Cost | U37: A+B+C | X37: =X36+X23+X16 -> 0 | AD37: =X37 -> 0
A38: E. | B38: Overhead,Contingencies and Miscellaneous | O38: (OCM) | U38: 15% of D | X38: =0.15*X37 -> 0 | AD38: =X38 -> 0
A39: F. | B39: Contractor's Profit (CP) | U39: 10%of D | X39: =0.1*X37 -> 0 | AD39: =X39 -> 0
A40: G. | B40: Value Added Tax (VAT) | T40: 5%*(D+E+F) | X40: =0.05*(X39+X38+X37) -> 0 | AD40: =X40 -> 0
A41: H. | B41: Total Cost | T41: (D+E+F+G) | X41: =X40+X39+X38+X37 -> 0 | AD41: =X41 -> 0
A42: I. | B42: Total Unit Cost | U42: H/Qty. | X42: =X41/F6 -> 0 | AD42: =X42 -> 0

Sheet ITEM 5
A1: DETAILED UNIT PRICE ANALYSIS
A3: PROJECT | E3: : | F3: ='POW COVER'!E9 -> Construction of Covered Pathway at City hall Entrance/Exit ( 29 SPAN, 3m length/span)
A4: Item No. | E4: : | F4: ='POW COVER'!B41 -> 1047(1)
A5: Description | E5: : | F5: ='POW COVER'!D41 -> Steel Works ( GIRT 1 ) ( 13.41m )
A6: Quantity | E6: : | F6: ='POW COVER'!M41 -> 17 | G6: ='POW COVER'!O41 -> sets | I6: sets
A7: Output Per Hour: | F7: 15 | G7: =""&G6&" per hour" -> sets per hour
AF8: hours
B9: Designation | N9: No. of Person | Q9: No. of Hours | T9: Houry Rate | X9: AMOUNT | AF9: =MAX(Q12:S15,Q20:S23) -> 0
A10: A. | B10: Labor
B12: a. Construction Foreman | X12: =T12*Q12*N12 -> 0
B13: b. Skilled Labor ( Welder ) | X13: =T13*Q13*O13 -> 0
B14: c. Unskilled Labor | X14: =T14*Q14*O14 -> 0
X15: =T15*Q15*O15 -> 0
A16: Sub Total for A | X16: =SUM(X12:AC15) -> 0
B17: Name & Capacity | N17: No. of units | Q17: No. of Hours | T17: Houry Rate | X17: AMOUNT
A18: B. | B18: Equipment
B20: Welding Machine | X20: =T20*Q20*N20 -> 0
B21: Electric sander | X21: =T21*Q21*N21 -> 0
B22: Electric drill | X22: =T22*Q22*N22 -> 0
A24: Sub Total for B | X24: =SUM(X20:AC23) -> 0
B25: Name & Specifications | N25: Units | Q25: Quantity | T25: Unit cost | X25: AMOUNT
A26: C. | B26: Materials
B28: PRE Painted rib type Long Span ( 0.40mm) | N28: ln.m. | X28: =T28*Q28 -> 0
B29: PRE Fabricated rib type Blind gutter ( 0.40mm) | N29: ln.m. | X29: =T29*Q29 -> 0
B30: 2x3x1.2mm CEE purlins | N30: length | X30: =T30*Q30 -> 0
B31: tex crew 2 1/2 | N31: pcs | X31: =T31*Q31 -> 0
B32: Vulcaseal | N32: qrt | X32: =T32*Q32 -> 0
B33: welding rod ( N 1630 ) | N33: kl | X33: =T33*Q33 -> 0
B34: cutting disc | N34: pc | X34: =T34*Q34 -> 0
A36: Sub-Total for C | X36: =SUM(X28:AC35) -> 0
A37: D. | B37: Total Direct Cost | U37: A+B+C | X37: =X36+X24+X16 -> 0 | AD37: =X37 -> 0
A38: E. | B38: Overhead,Contingencies and Miscellaneous | O38: (OCM) | U38: 15% of D | X38: =0.15*X37 -> 0 | AD38: =X38 -> 0
A39: F. | B39: Contractor's Profit (CP) | U39: 10%of D | X39: =0.1*X37 -> 0 | AD39: =X39 -> 0
A40: G. | B40: Value Added Tax (VAT) | T40: 5%*(D+E+F) | X40: =0.05*(X39+X38+X37) -> 0 | AD40: =X40 -> 0
A41: H. | B41: Total Cost | T41: (D+E+F+G) | X41: =X40+X39+X38+X37 -> 0 | AD41: =X41 -> 0
A42: I. | B42: Total Unit Cost | U42: H/Qty. | X42: =X41/F6 -> 0 | AD42: =X42 -> 0

Sheet ITEM 6
A1: DETAILED UNIT PRICE ANALYSIS
A3: PROJECT | E3: : | F3: ='POW COVER'!E9 -> Construction of Covered Pathway at City hall Entrance/Exit ( 29 SPAN, 3m length/span)
A4: Item No. | E4: : | F4: ='POW COVER'!B42 -> 1047(2)
A5: Description | E5: : | F5: ='POW COVER'!D42 -> Steel Works ( GIRT 2 ) ( 12.13m )
A6: Quantity | E6: : | F6: ='POW COVER'!M42 -> 17 | G6: ='POW COVER'!O42 -> sets | I6: sets
A7: Output Per Hour: | F7: 5 | G7: =""&G6&" per hour" -> sets per hour
AF8: hours
B9: Designation | N9: No. of Person | Q9: No. of Hours | T9: Houry Rate | X9: AMOUNT | AF9: =MAX(Q12:S15,Q20:S20) -> 0
A10: A. | B10: Labor
B12: a. Construction Foreman | X12: =T12*Q12*N12 -> 0
B13: b. Skilled Labor ( Welder ) | X13: =T13*Q13*O13 -> 0
B14: c. Unskilled Labor | X14: =T14*Q14*O14 -> 0
A16: Sub Total for A | X16: =SUM(X12:AC15) -> 0
B17: Name & Capacity | N17: No. of units | Q17: No. of Hours | T17: Houry Rate | X17: AMOUNT
A18: B. | B18: Equipment
A21: Sub Total for B | X21: =SUM(X20:AC20) -> 0
B22: Name & Specifications | N22: Units | Q22: Quantity | T22: Unit cost | X22: AMOUNT
A23: C. | B23: Materials
B25: Red Oxide | X25: =T25*Q25 -> 0
B26: Automotive paint ( silver ) | X26: =T26*Q26 -> 0
B27: paint thinner | X27: =T27*Q27 -> 0
B28: lacquer thinner | X28: =T28*Q28 -> 0
B29: paint brush ( 4" ) | X29: =T29*Q29 -> 0
B30: paint brush ( 2" ) | X30: =T30*Q30 -> 0
B31: paint brush ( 1" ) | X31: =T31*Q31 -> 0
X32: =T32*Q32 -> 0
A34: Sub-Total for C | X34: =SUM(X25:AC33) -> 0
A35: D. | B35: Total Direct Cost | U35: A+B+C | X35: =X34+X21+X16 -> 0 | AD35: =X35 -> 0
A36: E. | B36: Overhead,Contingencies and Miscellaneous | O36: (OCM) | U36: 15% of D | X36: =0.15*X35 -> 0 | AD36: =X36 -> 0
A37: F. | B37: Contractor's Profit (CP) | U37: 10%of D | X37: =0.1*X35 -> 0 | AD37: =X37 -> 0
A38: G. | B38: Value Added Tax (VAT) | T38: 5%*(D+E+F) | X38: =0.05*(X37+X36+X35) -> 0 | AD38: =X38 -> 0
A39: H. | B39: Total Cost | T39: (D+E+F+G) | X39: =X38+X37+X36+X35 -> 0 | AD39: =X39 -> 0
A40: I. | B40: Total Unit Cost | U40: H/Qty. | X40: =X39/F6 -> 0 | AD40: =X40 -> 0

Sheet ITEM 7
A1: DETAILED UNIT PRICE ANALYSIS
A3: PROJECT | E3: : | F3: ='POW COVER'!E9 -> Construction of Covered Pathway at City hall Entrance/Exit ( 29 SPAN, 3m length/span)
A4: Item No. | E4: : | F4: ='POW COVER'!B43 -> 1047(3)
A5: Description | E5: : | F5: ='POW COVER'!D43 -> Steel Works ( TRUSS 1 ) ( 9.74m )
A6: Quantity | E6: : | F6: ='POW COVER'!M43 -> 18 | G6: ='POW COVER'!O43 -> sets | I6: sets
A7: Output Per Hour: | F7: 5 | G7: =""&G6&" per hour" -> sets per hour
AF8: hours
B9: Designation | N9: No. of Person | Q9: No. of Hours | T9: Houry Rate | X9: AMOUNT | AF9: =MAX(Q12:S15,Q20:S20) -> 0
A10: A. | B10: Labor
B12: a. Construction Foreman | X12: =T12*Q12*N12 -> 0
B13: b. Skilled Labor ( Welder ) | X13: =T13*Q13*O13 -> 0
B14: c. Unskilled Labor | X14: =T14*Q14*O14 -> 0
A16: Sub Total for A | X16: =SUM(X12:AC15) -> 0
B17: Name & Capacity | N17: No. of units | Q17: No. of Hours | T17: Houry Rate | X17: AMOUNT
A18: B. | B18: Equipment
A21: Sub Total for B | X21: =SUM(X20:AC20) -> 0
B22: Name & Specifications | N22: Units | Q22: Quantity | T22: Unit cost | X22: AMOUNT
A23: C. | B23: Materials
B25: Red Oxide | X25: =T25*Q25 -> 0
B26: Automotive paint ( silver ) | X26: =T26*Q26 -> 0
B27: paint thinner | X27: =T27*Q27 -> 0
B28: lacquer thinner | X28: =T28*Q28 -> 0
B29: paint brush ( 4" ) | X29: =T29*Q29 -> 0
B30: paint brush ( 2" ) | X30: =T30*Q30 -> 0
B31: paint brush ( 1" ) | X31: =T31*Q31 -> 0
X32: =T32*Q32 -> 0
A34: Sub-Total for C | X34: =SUM(X25:AC33) -> 0
A35: D. | B35: Total Direct Cost | U35: A+B+C | X35: =X34+X21+X16 -> 0 | AD35: =X35 -> 0
A36: E. | B36: Overhead,Contingencies and Miscellaneous | O36: (OCM) | U36: 15% of D | X36: =0.15*X35 -> 0 | AD36: =X36 -> 0
A37: F. | B37: Contractor's Profit (CP) | U37: 10%of D | X37: =0.1*X35 -> 0 | AD37: =X37 -> 0
A38: G. | B38: Value Added Tax (VAT) | T38: 5%*(D+E+F) | X38: =0.05*(X37+X36+X35) -> 0 | AD38: =X38 -> 0
A39: H. | B39: Total Cost | T39: (D+E+F+G) | X39: =X38+X37+X36+X35 -> 0 | AD39: =X39 -> 0
A40: I. | B40: Total Unit Cost | U40: H/Qty. | X40: =X39/F6 -> 0 | AD40: =X40 -> 0

Sheet ITEM 8
A1: DETAILED UNIT PRICE ANALYSIS
A3: PROJECT | E3: : | F3: ='POW COVER'!E9 -> Construction of Covered Pathway at City hall Entrance/Exit ( 29 SPAN, 3m length/span)
A4: Item No. | E4: : | F4: ='POW COVER'!B44 -> 903(1)
A5: Description | E5: : | F5: ='POW COVER'!D44 -> Roofing Works
A6: Quantity | E6: : | F6: ='POW COVER'!M44 -> 165.24 | G6: ='POW COVER'!O44 -> sq.m. | I6: sets
A7: Output Per Hour: | F7: 5 | G7: =""&G6&" per hour" -> sq.m. per hour
AF8: hours
B9: Designation | N9: No. of Person | Q9: No. of Hours | T9: Houry Rate | X9: AMOUNT | AF9: =MAX(Q12:S15,Q20:S20) -> 0
A10: A. | B10: Labor
B12: a. Construction Foreman | X12: =T12*Q12*N12 -> 0
B13: b. Skilled Labor ( Welder ) | X13: =T13*Q13*O13 -> 0
B14: c. Unskilled Labor | X14: =T14*Q14*O14 -> 0
A16: Sub Total for A | X16: =SUM(X12:AC15) -> 0
B17: Name & Capacity | N17: No. of units | Q17: No. of Hours | T17: Houry Rate | X17: AMOUNT
A18: B. | B18: Equipment
A21: Sub Total for B | X21: =SUM(X20:AC20) -> 0
B22: Name & Specifications | N22: Units | Q22: Quantity | T22: Unit cost | X22: AMOUNT
A23: C. | B23: Materials
B25: Red Oxide | X25: =T25*Q25 -> 0
B26: Automotive paint ( silver ) | X26: =T26*Q26 -> 0
B27: paint thinner | X27: =T27*Q27 -> 0
B28: lacquer thinner | X28: =T28*Q28 -> 0
B29: paint brush ( 4" ) | X29: =T29*Q29 -> 0
B30: paint brush ( 2" ) | X30: =T30*Q30 -> 0
B31: paint brush ( 1" ) | X31: =T31*Q31 -> 0
X32: =T32*Q32 -> 0
A34: Sub-Total for C | X34: =SUM(X25:AC33) -> 0
A35: D. | B35: Total Direct Cost | U35: A+B+C | X35: =X34+X21+X16 -> 0 | AD35: =X35 -> 0
A36: E. | B36: Overhead,Contingencies and Miscellaneous | O36: (OCM) | U36: 15% of D | X36: =0.15*X35 -> 0 | AD36: =X36 -> 0
A37: F. | B37: Contractor's Profit (CP) | U37: 10%of D | X37: =0.1*X35 -> 0 | AD37: =X37 -> 0
A38: G. | B38: Value Added Tax (VAT) | T38: 5%*(D+E+F) | X38: =0.05*(X37+X36+X35) -> 0 | AD38: =X38 -> 0
A39: H. | B39: Total Cost | T39: (D+E+F+G) | X39: =X38+X37+X36+X35 -> 0 | AD39: =X39 -> 0
A40: I. | B40: Total Unit Cost | U40: H/Qty. | X40: =X39/F6 -> 0 | AD40: =X40 -> 0

Sheet ITEM 9
A1: DETAILED UNIT PRICE ANALYSIS
A3: PROJECT | E3: : | F3: ='POW COVER'!E9 -> Construction of Covered Pathway at City hall Entrance/Exit ( 29 SPAN, 3m length/span)
A4: Item No. | E4: : | F4: ='POW COVER'!B45 -> 1027
A5: Description | E5: : | F5: ='POW COVER'!D45 -> Painting Works
A6: Quantity | E6: : | F6: ='POW COVER'!M45 -> 1 | G6: ='POW COVER'!O45 -> lumpsum | I6: sets
A7: Output Per Hour: | F7: 5 | G7: =""&G6&" per hour" -> lumpsum per hour
AF8: hours
B9: Designation | N9: No. of Person | Q9: No. of Hours | T9: Houry Rate | X9: AMOUNT | AF9: =MAX(Q12:S15,Q20:S20) -> 0
A10: A. | B10: Labor
B12: a. Construction Foreman | X12: =T12*Q12*N12 -> 0
B13: b. Skilled Labor ( Welder ) | X13: =T13*Q13*O13 -> 0
B14: c. Unskilled Labor | X14: =T14*Q14*O14 -> 0
A16: Sub Total for A | X16: =SUM(X12:AC15) -> 0
B17: Name & Capacity | N17: No. of units | Q17: No. of Hours | T17: Houry Rate | X17: AMOUNT
A18: B. | B18: Equipment
A21: Sub Total for B | X21: =SUM(X20:AC20) -> 0
B22: Name & Specifications | N22: Units | Q22: Quantity | T22: Unit cost | X22: AMOUNT
A23: C. | B23: Materials
B25: Red Oxide | X25: =T25*Q25 -> 0
B26: Automotive paint ( silver ) | X26: =T26*Q26 -> 0
B27: paint thinner | X27: =T27*Q27 -> 0
B28: lacquer thinner | X28: =T28*Q28 -> 0
B29: paint brush ( 4" ) | X29: =T29*Q29 -> 0
B30: paint brush ( 2" ) | X30: =T30*Q30 -> 0
B31: paint brush ( 1" ) | X31: =T31*Q31 -> 0
X32: =T32*Q32 -> 0
A34: Sub-Total for C | X34: =SUM(X25:AC33) -> 0
A35: D. | B35: Total Direct Cost | U35: A+B+C | X35: =X34+X21+X16 -> 0 | AD35: =X35 -> 0
A36: E. | B36: Overhead,Contingencies and Miscellaneous | O36: (OCM) | U36: 15% of D | X36: =0.15*X35 -> 0 | AD36: =X36 -> 0
A37: F. | B37: Contractor's Profit (CP) | U37: 10%of D | X37: =0.1*X35 -> 0 | AD37: =X37 -> 0
A38: G. | B38: Value Added Tax (VAT) | T38: 5%*(D+E+F) | X38: =0.05*(X37+X36+X35) -> 0 | AD38: =X38 -> 0
A39: H. | B39: Total Cost | T39: (D+E+F+G) | X39: =X38+X37+X36+X35 -> 0 | AD39: =X39 -> 0
A40: I. | B40: Total Unit Cost | U40: H/Qty. | X40: =X39/F6 -> 0 | AD40: =X40 -> 0

Sheet ITEM 10
A1: DETAILED UNIT PRICE ANALYSIS
A3: PROJECT | E3: : | F3: ='POW COVER'!E9 -> Construction of Covered Pathway at City hall Entrance/Exit ( 29 SPAN, 3m length/span)
A4: Item No. | E4: : | F4: ='POW COVER'!B46 -> SPL - 2
A5: Description | E5: : | F5: ='POW COVER'!D46 -> Billboards
A6: Quantity | E6: : | F6: ='POW COVER'!M46 -> 1 | G6: ='POW COVER'!O46 -> lumpsum | I6: sets
A7: Output Per Hour: | F7: 5 | G7: =""&G6&" per hour" -> lumpsum per hour
AF8: hours
B9: Designation | N9: No. of Person | Q9: No. of Hours | T9: Houry Rate | X9: AMOUNT | AF9: =MAX(Q12:S15,Q20:S20) -> 0
A10: A. | B10: Labor
B12: a. Construction Foreman | X12: =T12*Q12*N12 -> 0
B13: b. Skilled Labor ( Welder ) | X13: =T13*Q13*O13 -> 0
B14: c. Unskilled Labor | X14: =T14*Q14*O14 -> 0
A16: Sub Total for A | X16: =SUM(X12:AC15) -> 0
B17: Name & Capacity | N17: No. of units | Q17: No. of Hours | T17: Houry Rate | X17: AMOUNT
A18: B. | B18: Equipment
A21: Sub Total for B | X21: =SUM(X20:AC20) -> 0
B22: Name & Specifications | N22: Units | Q22: Quantity | T22: Unit cost | X22: AMOUNT
A23: C. | B23: Materials
B25: Red Oxide | X25: =T25*Q25 -> 0
B26: Automotive paint ( silver ) | X26: =T26*Q26 -> 0
B27: paint thinner | X27: =T27*Q27 -> 0
B28: lacquer thinner | X28: =T28*Q28 -> 0
B29: paint brush ( 4" ) | X29: =T29*Q29 -> 0
B30: paint brush ( 2" ) | X30: =T30*Q30 -> 0
B31: paint brush ( 1" ) | X31: =T31*Q31 -> 0
X32: =T32*Q32 -> 0
A34: Sub-Total for C | X34: =SUM(X25:AC33) -> 0
A35: D. | B35: Total Direct Cost | U35: A+B+C | X35: =X34+X21+X16 -> 0 | AD35: =X35 -> 0
A36: E. | B36: Overhead,Contingencies and Miscellaneous | O36: (OCM) | U36: 15% of D | X36: =0.15*X35 -> 0 | AD36: =X36 -> 0
A37: F. | B37: Contractor's Profit (CP) | U37: 10%of D | X37: =0.1*X35 -> 0 | AD37: =X37 -> 0
A38: G. | B38: Value Added Tax (VAT) | T38: 5%*(D+E+F) | X38: =0.05*(X37+X36+X35) -> 0 | AD38: =X38 -> 0
A39: H. | B39: Total Cost | T39: (D+E+F+G) | X39: =X38+X37+X36+X35 -> 0 | AD39: =X39 -> 0
A40: I. | B40: Total Unit Cost | U40: H/Qty. | X40: =X39/F6 -> 0 | AD40: =X40 -> 0

Sheet ITEM 11
A1: DETAILED UNIT PRICE ANALYSIS
A3: PROJECT | E3: : | F3: ='POW COVER'!E9 -> Construction of Covered Pathway at City hall Entrance/Exit ( 29 SPAN, 3m length/span)
A4: Item No. | E4: : | F4: ='POW COVER'!B47 -> SPL -4
A5: Description | E5: : | F5: ='POW COVER'!D47 -> Construction of Safety and Health Program
A6: Quantity | E6: : | F6: ='POW COVER'!M47 -> 1 | G6: ='POW COVER'!O47 -> lot | I6: sets
A7: Output Per Hour: | F7: 5 | G7: =""&G6&" per hour" -> lot per hour
AF8: hours
B9: Designation | N9: No. of Person | Q9: No. of Hours | T9: Houry Rate | X9: AMOUNT | AF9: =MAX(Q12:S15,Q20:S20) -> 0
A10: A. | B10: Labor
B12: a. Construction Foreman | X12: =T12*Q12*N12 -> 0
B13: b. Skilled Labor ( Welder ) | X13: =T13*Q13*O13 -> 0
B14: c. Unskilled Labor | X14: =T14*Q14*O14 -> 0
A16: Sub Total for A | X16: =SUM(X12:AC15) -> 0
B17: Name & Capacity | N17: No. of units | Q17: No. of Hours | T17: Houry Rate | X17: AMOUNT
A18: B. | B18: Equipment
A21: Sub Total for B | X21: =SUM(X20:AC20) -> 0
B22: Name & Specifications | N22: Units | Q22: Quantity | T22: Unit cost | X22: AMOUNT
A23: C. | B23: Materials
B25: Red Oxide | X25: =T25*Q25 -> 0
B26: Automotive paint ( silver ) | X26: =T26*Q26 -> 0
B27: paint thinner | X27: =T27*Q27 -> 0
B28: lacquer thinner | X28: =T28*Q28 -> 0
B29: paint brush ( 4" ) | X29: =T29*Q29 -> 0
B30: paint brush ( 2" ) | X30: =T30*Q30 -> 0
B31: paint brush ( 1" ) | X31: =T31*Q31 -> 0
X32: =T32*Q32 -> 0
A34: Sub-Total for C | X34: =SUM(X25:AC33) -> 0
A35: D. | B35: Total Direct Cost | U35: A+B+C | X35: =X34+X21+X16 -> 0 | AD35: =X35 -> 0
A36: E. | B36: Overhead,Contingencies and Miscellaneous | O36: (OCM) | U36: 15% of D | X36: =0.15*X35 -> 0 | AD36: =X36 -> 0
A37: F. | B37: Contractor's Profit (CP) | U37: 10%of D | X37: =0.1*X35 -> 0 | AD37: =X37 -> 0
A38: G. | B38: Value Added Tax (VAT) | T38: 5%*(D+E+F) | X38: =0.05*(X37+X36+X35) -> 0 | AD38: =X38 -> 0
A39: H. | B39: Total Cost | T39: (D+E+F+G) | X39: =X38+X37+X36+X35 -> 0 | AD39: =X39 -> 0
A40: I. | B40: Total Unit Cost | U40: H/Qty. | X40: =X39/F6 -> 0 | AD40: =X40 -> 0
